Workbook

Sheet Cover
B2: ETERNAL LIMITED (Formerly known as Zomato Limited)
B9: EQUITY RESEARCH | FINANCIAL MODEL & DCF VALUATION
B12: Prepared by: Aditi Garg | MBA | Galgotias College of Engineering and Technology
B13: Model Version: 1.0 | Date: April 2026 | For Academic Research Purposes
B15: COMPANY OVERVIEW
B17: Eternal Limited (formerly Zomato Limited) is India's largest consumer commerce platform operating across four segments: Food Delivery, Quick Commerce (Blinkit), Going-Out (District), and B2B Supplies (Hyperpure). Listed on NSE/BSE (Scrip: ETERNAL), the company achieved consolidated PAT profitability in FY24 and Blinkit EBITDA breakeven in Q3FY26.
C21: Business Description | H21: STOCK INFORMATION (As of April 2026)
C22: Sector | E22: Consumer Internet / E-Commerce | H22: Current Market Price: INR 249
C23: Industry | E23: Online Food & Quick Commerce | H23: 52-Week High | J23: INR 285
C24: Exchange | E24: NSE | BSE | H24: 52-Week Low | J24: INR 165
C25: Scrip Symbol | E25: ETERNAL | H25: Market Cap | J25: INR ₹ 2,46,595 Cr
C26: ISIN | E26: INE758T01015 | H26: Enterprise Value | J26: INR ₹ 2,33,886 Cr
C27: Face Value | E27: INR 1 per share | H27: Shares Outstanding | J27: 906 Cr (Basic) | 940 Cr (Diluted)
C28: Listing Date | E28: 44400 | H28: Free Float | J28: 0.63
C29: Auditor | E29: Deloitte Haskins & Sells | H29: Foreign Holding - 36.68%
C30: Registrar | E30: MUFG Intime India Pvt. Ltd. | H30: Promoter Holding: 0% (widely held)
C31: Company Website | E31: www.eternal.com | H31: Index Constituent - Nifty 50 | Sensex
C32: IR Contact | E32: ir@eternal.com | H32: Bloomberg Ticker - ETERNAL IN Equity
B34: KEY FINANCIAL METRICS TABLE | ₹ Crores
C36: Metric | E36: FY22A | F36: FY23A | G36: FY24A | H36: FY25A | I36: FY26E | J36: FY27E | K36: FY28E | L36: FY29E
C37: Revenue from Operations | E37: ='Historical Financials'!C12 -> 4193 | F37: ='Historical Financials'!D12 -> 7079 | G37: ='Historical Financials'!E12 -> 12114 | H37: ='Historical Financials'!F12 -> 20243 | I37: ='3-Statement'!G7 -> 28641.422 | J37: ='3-Statement'!H7 -> 40122.272 | K37: ='3-Statement'!I7 -> 53093.729 | L37: ='3-Statement'!J7 -> 65159.791
C38: Revenue Growth % | E38: - | F38: =F37/E37-1 -> 0.68829001 | G38: =G37/F37-1 -> 0.71125865 | H38: =H37/G37-1 -> 0.67104177 | I38: =I37/H37-1 -> 0.41488029 | J38: =J37/I37-1 -> 0.40084779 | K38: =K37/J37-1 -> 0.32329816 | L38: =L37/K37-1 -> 0.22725964
C39: Adj. EBITDA | E39: ='3-Statement'!C27 -> -973 | F39: ='3-Statement'!D27 -> -765 | G39: ='3-Statement'!E27 -> 372 | H39: ='3-Statement'!F27 -> 1079 | I39: ='3-Statement'!G27 -> 2274.8515 | J39: ='3-Statement'!H27 -> 3753.0491 | K39: ='3-Statement'!I27 -> 6529.8646 | L39: ='3-Statement'!J27 -> 9407.7513
C40: Adj. EBITDA Margin % | E40: ='3-Statement'!C28 -> -0.23205342 | F40: ='3-Statement'!D28 -> -0.10806611 | G40: ='3-Statement'!E28 -> 0.030708271 | H40: ='3-Statement'!F28 -> 0.053302376 | I40: ='3-Statement'!G28 -> 0.079425229 | J40: ='3-Statement'!H28 -> 0.093540291 | K40: ='3-Statement'!I28 -> 0.12298749 | L40: ='3-Statement'!J28 -> 0.1443797
C41: EBIT | E41: ='3-Statement'!C38 -> -1519 | F41: ='3-Statement'!D38 -> -1342 | G41: ='3-Statement'!E38 -> -553 | H41: ='3-Statement'!F38 -> 216 | I41: ='3-Statement'!G38 -> 1144.8515 | J41: ='3-Statement'!H38 -> 2373.0491 | K41: ='3-Statement'!I38 -> 4939.8646 | L41: ='3-Statement'!J38 -> 7667.7513
C42: Profit Before Tax | E42: ='3-Statement'!C45 -> -1221 | F42: ='3-Statement'!D45 -> -1015 | G42: ='3-Statement'!E45 -> 291 | H42: ='3-Statement'!F45 -> 697 | I42: ='3-Statement'!G45 -> 1960.8515 | J42: ='3-Statement'!H45 -> 2956.0491 | K42: ='3-Statement'!I45 -> 5357.8646 | L42: ='3-Statement'!J45 -> 7990.7513
C43: Profit After Tax | E43: ='3-Statement'!C53 -> -1223 | F43: ='3-Statement'!D53 -> -971 | G43: ='3-Statement'!E53 -> 351 | H43: ='3-Statement'!F53 -> 527 | I43: ='3-Statement'!G53 -> 1593.8515 | J43: ='3-Statement'!H53 -> 2357.0491 | K43: ='3-Statement'!I53 -> 4064.8646 | L43: ='3-Statement'!J53 -> 6038.7513
C44: PAT Margin % | E44: ='3-Statement'!C54 -> -0.2916766 | F44: ='3-Statement'!D54 -> -0.13716627 | G44: ='3-Statement'!E54 -> 0.02897474 | H44: ='3-Statement'!F54 -> 0.026033691 | I44: ='3-Statement'!G54 -> 0.055648476 | J44: ='3-Statement'!H54 -> 0.058746649 | K44: ='3-Statement'!I54 -> 0.076560164 | L44: ='3-Statement'!J54 -> 0.092676039
C45: EPS (INR) | E45: ='3-Statement'!C55 -> -1.6007853 | F45: ='3-Statement'!D55 -> -1.1614833 | G45: ='3-Statement'!E55 -> 0.40437788 | H45: ='3-Statement'!F55 -> 0.58103638 | I45: ='3-Statement'!G55 -> 1.6955867 | J45: ='3-Statement'!H55 -> 2.4552594 | K45: ='3-Statement'!I55 -> 4.1690919 | L45: ='3-Statement'!J55 -> 6.130712
C46: Total Assets | E46: ='3-Statement'!C83 -> 17327 | F46: ='3-Statement'!D83 -> 21602 | G46: ='3-Statement'!E83 -> 23356 | H46: ='3-Statement'!F83 -> 35623 | I46: ='3-Statement'!G83 -> 38686.851 | J46: ='3-Statement'!H83 -> 43937.901 | K46: ='3-Statement'!I83 -> 50517.765 | L46: ='3-Statement'!J83 -> 58514.517
C47: Total Equity | E47: ='3-Statement'!C89 -> 16499 | F47: ='3-Statement'!D89 -> 19452 | G47: ='3-Statement'!E89 -> 20406 | H47: ='3-Statement'!F89 -> 30310 | I47: ='3-Statement'!G89 -> 32836.851 | J47: ='3-Statement'!H89 -> 36160.901 | K47: ='3-Statement'!I89 -> 41135.765 | L47: ='3-Statement'!J89 -> 48034.517
C48: Cash Position | E48: ='3-Statement'!C76 -> 392 | F48: ='3-Statement'!D76 -> 218 | G48: ='3-Statement'!E76 -> 309 | H48: ='3-Statement'!F76 -> 666 | I48: ='3-Statement'!G76 -> 28.851476 | J48: ='3-Statement'!H76 -> 371.90053 | K48: ='3-Statement'!I76 -> 1820.7652 | L48: ='3-Statement'!J76 -> 5090.5165
B50: VALUATION SUMMARY & INVESTMENT RECOMMENDATION
B52: Label | D52: Value | E52: Notes | H52: INVESTMENT RATING H O L D Current Price: INR 249 Target Price: INR 211 Upside/(Downside): (15.3%) Time Horizon: 12 Months Risk Level: HIGH
B53: DCF Base Case | D53: ="₹" & ROUND('SOTP Valution'!D40,0) -> ₹170 | E53: WACC 13.95%, g=6.0%
B54: DCF Bull Case | D54: ="₹" & ROUND('SOTP Valution'!E40,0) -> ₹229 | E54: WACC 12.65%, g=6.5%
B55: DCF Bear Case | D55: ="₹" & ROUND('SOTP Valution'!C40,0) -> ₹149 | E55: WACC 15.9%, g=5.0%
B56: EV/Revenue Comps | D56: INR 137 | E56: 3.5x FY26E Revenue
B57: EV/EBITDA Comps | D57: INR 126 | E57: 23x FY26E Adj. EBITDA
B58: P/E Comps | D58: INR 154 | E58: 40x FY26E EPS
B59: SOTP Valuation | D59: ="₹" & ROUND('SOTP Valution'!D32,0) -> ₹271 | E59: Segment-wise build
B60: WEIGHTED TARGET | D60: ="₹" & ROUND('SOTP Valution'!D43,0) -> ₹211 | E60: 30% DCF + 30% SOTP + 40% Comps
B62: MODEL NAVIGATION & STRUCTURE
B63: Instruction text | D63: Click on any tab name below to navigate directly to that section of the model.
B65: KEY ASSUMPTIONS SNAPSHOT
E67: Key Assumptions Snapshot | G67: Value | I67: Assumption | K67: Value
E68: Forecast Period | G68: FY26E-FY29E | I68: WACC | K68: =Assumptions!F149 -> 0.13125
E69: Base Currency | G69: INR Crore | I69: Terminal Growth Rate | K69: =Assumptions!F152 -> 0.045
E70: Reporting Standard | G70: Ind AS | I70: Risk-Free Rate (India) | K70: =Assumptions!F145 -> 0.068
E71: Consolidation | G71: Eternal Ltd (Consol.) | I71: Equity Risk Premium | K71: =Assumptions!F146 -> 0.055
E72: Food Delivery NOV CAGR | G72: 19% (FY25-29E) | I72: Beta (Adjusted) | K72: =Assumptions!F147 -> 0.95
E73: Blinkit Stores FY29E | G73: 4500 | I73: Tax Rate (normalized) | K73: =Assumptions!H123 -> 0.25
E74: Blinkit EBITDA % NOV FY29E | G74: 0.05 | I74: Shares (Diluted) | K74: =Assumptions!E158&" Cr" -> 940 Cr
E75: Hyperpure Revenue CAGR | G75: 38% (FY25-29E) | I75: Net Cash (FY25A) | K75: INR 14,754 Cr
E76: Terminal EBIT Margin | G76: 0.13 | I76: Investment Rating | K76: HOLD
B78: DISCLAIMER
B79: DISCLAIMER: "This financial model and valuation analysis has been prepared solely for academic and educational purposes as part of an MBA Finance research project. All projections, assumptions, and valuations contained herein are the author's own estimates and do not represent investment advice. Historical data sourced from Eternal Limited's Annual Reports (FY22-FY25), BSE/NSE filings, and publicly available earnings call transcripts. This document should not be used for actual investment decisions. The author holds no positions in Eternal Limited's securities."

Sheet Historical Financials
B2: Historical financial Statement - ETERNAL LIMITED | ₹ Crores
B3: Particulars | C3: FY2022A | D3: FY2023A | E3: FY2024A | F3: FY2025A
A5: # | B5: Income Statement (₹ Crores)
B6: Revenue from Operations
B7: Food Delivery Platform Revenue | C7: 3415 | D7: 4533 | E7: 6361 | F7: 8080
B8: Blinkit Quick Commerce Revenue | C8: - | D8: 806 | E8: 2301 | F8: 5206
B9: Hyperpure B2B Supplies Revenue | C9: 538 | D9: 1506 | E9: 3172 | F9: 6196
B10: District / Going Out Revenue | C10: - | D10: - | E10: 258 | F10: 737
B11: Bistro & Others Revenue | C11: 240 | D11: 234 | E11: 22 | F11: 24
B12: Total Revenue from Operations | C12: =SUM(C7:C11) -> 4193 | D12: =SUM(D7:D11) -> 7079 | E12: =SUM(E7:E11) -> 12114 | F12: =SUM(F7:F11) -> 20243
B13: YoY Revenue Growth % | C13: - | D13: =D12/C12-1 -> 0.68829001 | E13: =E12/D12-1 -> 0.71125865 | F13: =F12/E12-1 -> 0.67104177
B15: Other Income | C15: 495 | D15: 681 | E15: 847 | F15: 1077
B16: TOTAL INCOME | C16: =SUM(C15,C12) -> 4688 | D16: =SUM(D15,D12) -> 7760 | E16: =SUM(E15,E12) -> 12961 | F16: =SUM(F15,F12) -> 21320
B18: COST OF REVENUE
B19: Purchases of Stock-in-Trade | C19: 552 | D19: 1438 | E19: 2887 | F19: 5653
B20: Changes in Inventories of Stock-in-Trade | C20: -43 | D20: -28 | E20: -5 | F20: -88
B21: Delivery Partner & Fulfilment Costs | C21: 1814 | D21: 2537 | E21: 3915 | F21: 5728
B23: Gross Profit | C23: =C12-C19-C20-C21 -> 1870 | D23: =D12-D19-D20-D21 -> 3132 | E23: =E12-E19-E20-E21 -> 5317 | F23: =F12-F19-F20-F21 -> 8950
B24: Gross Margin % of Revenue | C24: =C23/C12 -> 0.4459814 | D24: =D23/D12 -> 0.44243537 | E24: =E23/E12 -> 0.43891365 | F24: =F23/F12 -> 0.44212814
B26: PEOPLE COSTS
B27: Employee Benefits Expense (Cash) | C27: 755 | D27: 959 | E27: 1144 | F27: 1760
B28: ESOP / Share-Based Compensation Expense | C28: 878 | D28: 506 | E28: 515 | F28: 798
B29: Total People Costs | C29: =SUM(C27:C28) -> 1633 | D29: =SUM(D27:D28) -> 1465 | E29: =SUM(E27:E28) -> 1659 | F29: =SUM(F27:F28) -> 2558
B31: OPERATING EXPENSES
B32: Advertising & Marketing Expense | C32: 1633 | D32: 1465 | E32: 526 | F32: 863
B33: Technology & Platform Infrastructure Costs | C33: 289 | D33: 387 | E33: 485 | F33: 644
B34: Short-term Lease & Facility Costs | C34: 10 | D34: 42 | E34: 44 | F34: 68
B35: Warehousing Management Expenses | C35: 25 | D35: 129 | E35: 211 | F35: 400
B36: Outsourced Support Cost | C36: 172 | D36: 297 | E36: 330 | F36: 570
B37: Payment Gateway Charges | C37: 119 | D37: 155 | E37: 190 | F37: 228
B38: Other Operating Expenses | C38: 1254 | D38: 1185 | E38: 2839 | F38: 7601
B39: Other Expenses | C39: 353 | D39: 1770 | E39: 2906 | F39: 1109
B40: Total Other Expenses | C40: =SUM(C32:C39) -> 3855 | D40: =SUM(D32:D39) -> 5430 | E40: =SUM(E32:E39) -> 7531 | F40: =SUM(F32:F39) -> 11483
B42: ADJUSTED EBITDA | C42: =SUM(C46:C51) -> -973 | D42: =SUM(D46:D51) -> -765 | E42: =SUM(E46:E51) -> 372 | F42: =SUM(F46:F51) -> 1079
B43: Adj. EBITDA Margin % | C43: =C42/C12 -> -0.23205342 | D43: =D42/D12 -> -0.10806611 | E43: =E42/E12 -> 0.030708271 | F43: =F42/F12 -> 0.053302376
B45: Segment-wise Adj. EBITDA:
B46: - Food | C46: -766 | D46: -5 | E46: 912 | F46: 1505
B47: - Blinkit | C47: - | D47: -1016 | E47: -384 | F47: -292
B48: - Hyperpure | C48: -139 | D48: -194 | E48: -126 | F48: -84
B49: - District/Going Out | C49: - | D49: - | E49: -6 | F49: -38
B50: Others | C50: -68 | D50: -3 | E50: -24 | F50: -
B51: Unallocated / Corporate | C51: - | D51: 453 | E51: - | F51: -12
B53: NON-CASH CHARGES
B54: Depreciation on PPE | C54: 287 | D54: 212 | E54: 524 | F54: 247
B55: Amortisation of Intangibles | C55: 108 | D55: 256 | E55: 242 | F55: 287
B56: Depreciation on ROU Assets | C56: 151 | D56: 109 | E56: 159 | F56: 329
B57: Total D&A | C57: =SUM(C54:C56) -> 546 | D57: =SUM(D54:D56) -> 577 | E57: =SUM(E54:E56) -> 925 | F57: =SUM(F54:F56) -> 863
B59: EBITDA (Reported) | C59: =C42-C28 -> -1851 | D59: =D42-D28 -> -1271 | E59: =E42-E28 -> -143 | F59: =F42-F28 -> 281
B60: EBITDA Margin% | C60: =C59/C12 -> -0.44145004 | D60: =D59/D12 -> -0.17954513 | E60: =E59/E12 -> -0.011804524 | F60: =F59/F12 -> 0.013881342
B61: EBIT | C61: =C42-C57 -> -1519 | D61: =D42-D57 -> -1342 | E61: =E42-E57 -> -553 | F61: =F42-F57 -> 216
B62: EBIT Margin % | C62: =C61/C12 -> -0.36227045 | D62: =D61/D12 -> -0.1895748 | E62: =E61/E12 -> -0.045649662 | F62: =F61/F12 -> 0.010670355
B63: Interest on Borrowings | C63: 15 | D63: 24 | E63: - | F63: -
B64: Interest on Lease Liabilities | C64: 9 | D64: 41 | E64: 67 | F64: 147
B65: Total Finance Costs | C65: 12 | D65: 49 | E65: 72 | F65: 154
B66: Exceptional Items (₹ Cr) | C66: 297 | D66: 0 | E66: 0 | F66: 0
B68: PROFIT BEFORE TAX | C68: -1221 | D68: -1015 | E68: 291 | F68: 697
B69: PBT Margin % | C69: =C68/C12 -> -0.29119962 | D69: =D68/D12 -> -0.14338183 | E69: =E68/E12 -> 0.024021793 | F69: =F68/F12 -> 0.034431655
B71: TAX
B72: Current Tax | C72: 0 | D72: 0 | E72: 200 | F72: 267
B73: Deferred Tax | C73: -4 | D73: -44 | E73: -60 | F73: -97
B74: Total Tax Expense (VIII) | C74: =C72+C73 -> -4 | D74: =D72+D73 -> -44 | E74: =E72+E73 -> 140 | F74: =F72+F73 -> 170
B76: PROFIT AFTER TAX | C76: -1223 | D76: -971 | E76: 351 | F76: 527
B77: PAT Margin % | C77: =C76/C12 -> -0.2916766 | D77: =D76/D12 -> -0.13716627 | E77: =E76/E12 -> 0.02897474 | F77: =F76/F12 -> 0.026033691
B79: Basic EPS | C79: =C76/764 -> -1.6007853 | D79: =D76/836 -> -1.1614833 | E79: =E76/868 -> 0.40437788 | F79: =F76/907 -> 0.58103638
B80: Diluted EPS | C80: -1.67 | D80: -1.2 | E80: 0.4 | F80: 0.58
A83: # | B83: Balance Sheet (₹ Crores)
B84: TOTAL NON-CURRENT ASSETS
B85: Property, Plant & Equipment (Net) | C85: 51 | D85: 209 | E85: 287 | F85: 965
B86: Capital Work-in-Progress | C86: 18 | D86: 18 | E86: 51 | F86: 0
B87: Right-of-Use Assets | C87: 64 | D87: 427 | E87: 690 | F87: 1918
B88: Goodwill | C88: 1209 | D88: 4717 | E88: 4717 | F88: 5737
B89: Other Intangible Assets | C89: 63 | D89: 991 | E89: 754 | F89: 912
B90: Non-Current Investments | C90: 3086 | D90: 2280 | E90: 10365 | F90: 10920
B91: Other Non-Current Financial Assets | C91: 5219 | D91: 1894 | E91: 747 | F91: 2744
B92: Deferred Tax Assets | C92: 67 | D92: 116 | E92: 221 | F92: 129
B93: Other Non-Current Assets | C93: 5 | D93: 118 | E93: 66 | F93: 597
B94: TOTAL NON-CURRENT ASSETS | C94: =SUM(C85:C93) -> 9782 | D94: =SUM(D85:D93) -> 10770 | E94: =SUM(E85:E93) -> 17898 | F94: =SUM(F85:F93) -> 23922 | K94: =SUM(G85:G93) -> 0 | L94: =SUM(H85:H93) -> 0 | M94: =SUM(I85:I93) -> 0
B96: TOTAL CURRENT ASSETS
B97: Inventories | C97: 40 | D97: 83 | E97: 88 | F97: 176
B98: Current Investments | C98: 1632 | D98: 4485 | E98: 1280 | F98: 2272
B99: Trade Receivables | C99: 16 | D99: 45 | E99: 779 | F99: 1946
B100: Cash & Cash Equivalents | C100: 392 | D100: 218 | E100: 309 | F100: 666
B101: Bank Balances | C101: 1183 | D101: 799 | E101: 422 | F101: 2948
B102: Loans (Current) | C102: 375 | D102: 0 | E102: 0 | F102: 0
B103: Other Current Financial Assets | C103: 3667 | D103: 4830 | E103: 2324 | F103: 2769
B104: Other Current Assets | C104: 240 | D104: 372 | E104: 256 | F104: 924
B105: TOTAL CURRENT ASSETS | C105: =SUM(C97:C104) -> 7545 | D105: =SUM(D97:D104) -> 10832 | E105: =SUM(E97:E104) -> 5458 | F105: =SUM(F97:F104) -> 11701
B107: TOTAL ASSETS | C107: =SUM(C105,C94) -> 17327 | D107: =SUM(D105,D94) -> 21602 | E107: =SUM(E105,E94) -> 23356 | F107: =SUM(F105,F94) -> 35623
B109: EQUITY
B110: Share Capital | C110: 764 | D110: 836 | E110: 868 | F110: 907
B111: Other Equity | C111: 15742 | D111: 18623 | E111: 19545 | F111: 29410
B112: Non-Controlling Interest | C112: -7 | D112: -7 | E112: -7 | F112: -7
B113: TOTAL EQUITY | C113: =SUM(C110:C112) -> 16499 | D113: =SUM(D110:D112) -> 19452 | E113: =SUM(E110:E112) -> 20406 | F113: =SUM(F110:F112) -> 30310
B115: NON-CURRENT LIABILITIES
B116: Lease Liabilities (Non-Current) | C116: 52 | D116: 351 | E116: 585 | F116: 1654
B117: Borrowings (Non-Current) | C117: 0 | D117: 0 | E117: 6 | F117: 0
B118: Deferred Tax Liabilities | D118: 250 | E118: 188 | F118: 212
B119: Non-Current Provisions | C119: 65 | D119: 94 | E119: 88 | F119: 120
B120: Other Non-Current Financial Liabilities | C120: 0 | D120: 10 | E120: - | F120: 1
B121: TOTAL NON-CURRENT LIABILITIES | C121: =SUM(C116:C120) -> 117 | D121: =SUM(D116:D120) -> 705 | E121: =SUM(E116:E120) -> 867 | F121: =SUM(F116:F120) -> 1987
...

Sheet KPIs
B2: KPI - ETERNAL LIMITED | ₹ Crores
B3: Particulars | C3: FY2022A | D3: FY2023A | E3: FY2024A | F3: FY2025A
A5: # | B5: GROUP-LEVEL FINANCIAL KPIs
B6: Total Revenue from Operations (₹ Cr) | C6: ='Historical Financials'!C12 -> 4193 | D6: ='Historical Financials'!D12 -> 7079 | E6: ='Historical Financials'!E12 -> 12114 | F6: ='Historical Financials'!F12 -> 20243
B7: YoY Revenue Growth % | C7: ='Historical Financials'!C13 -> - | D7: ='Historical Financials'!D13 -> 0.68829001 | E7: ='Historical Financials'!E13 -> 0.71125865 | F7: ='Historical Financials'!F13 -> 0.67104177
B8: Gross Profit (₹ Cr) | C8: ='Historical Financials'!C23 -> 1870 | D8: ='Historical Financials'!D23 -> 3132 | E8: ='Historical Financials'!E23 -> 5317 | F8: ='Historical Financials'!F23 -> 8950
B9: Gross Margin % | C9: ='Historical Financials'!C24 -> 0.4459814 | D9: ='Historical Financials'!D24 -> 0.44243537 | E9: ='Historical Financials'!E24 -> 0.43891365 | F9: ='Historical Financials'!F24 -> 0.44212814
B10: Adjusted EBITDA (₹ Cr) | C10: ='Historical Financials'!C42 -> -973 | D10: ='Historical Financials'!D42 -> -765 | E10: ='Historical Financials'!E42 -> 372 | F10: ='Historical Financials'!F42 -> 1079
B11: Adjusted EBITDA Margin % | C11: ='Historical Financials'!C43 -> -0.23205342 | D11: ='Historical Financials'!D43 -> -0.10806611 | E11: ='Historical Financials'!E43 -> 0.030708271 | F11: ='Historical Financials'!F43 -> 0.053302376
B12: Reported EBITDA (₹ Cr) | C12: ='Historical Financials'!C59 -> -1851 | D12: ='Historical Financials'!D59 -> -1271 | E12: ='Historical Financials'!E59 -> -143 | F12: ='Historical Financials'!F59 -> 281
B13: Reported EBITDA Margin % | C13: ='Historical Financials'!C60 -> -0.44145004 | D13: ='Historical Financials'!D60 -> -0.17954513 | E13: ='Historical Financials'!E60 -> -0.011804524 | F13: ='Historical Financials'!F60 -> 0.013881342
B14: EBIT (₹ Cr) | C14: ='Historical Financials'!C61 -> -1519 | D14: ='Historical Financials'!D61 -> -1342 | E14: ='Historical Financials'!E61 -> -553 | F14: ='Historical Financials'!F61 -> 216
B15: EBIT Margin % | C15: ='Historical Financials'!C62 -> -0.36227045 | D15: ='Historical Financials'!D62 -> -0.1895748 | E15: ='Historical Financials'!E62 -> -0.045649662 | F15: ='Historical Financials'!F62 -> 0.010670355
B16: PBT (₹ Cr) | C16: ='Historical Financials'!C68 -> -1221 | D16: ='Historical Financials'!D68 -> -1015 | E16: ='Historical Financials'!E68 -> 291 | F16: ='Historical Financials'!F68 -> 697
B17: PBT Margin % | C17: ='Historical Financials'!C69 -> -0.29119962 | D17: ='Historical Financials'!D69 -> -0.14338183 | E17: ='Historical Financials'!E69 -> 0.024021793 | F17: ='Historical Financials'!F69 -> 0.034431655
B18: PAT (₹ Cr) | C18: ='Historical Financials'!C76 -> -1223 | D18: ='Historical Financials'!D76 -> -971 | E18: ='Historical Financials'!E76 -> 351 | F18: ='Historical Financials'!F76 -> 527
B19: PAT Margin % | C19: ='Historical Financials'!C77 -> -0.2916766 | D19: ='Historical Financials'!D77 -> -0.13716627 | E19: ='Historical Financials'!E77 -> 0.02897474 | F19: ='Historical Financials'!F77 -> 0.026033691
B20: Basic EPS (₹) | C20: ='Historical Financials'!C79 -> -1.6007853 | D20: ='Historical Financials'!D79 -> -1.1614833 | E20: ='Historical Financials'!E79 -> 0.40437788 | F20: ='Historical Financials'!F79 -> 0.58103638
B21: Diluted EPS (₹) | C21: ='Historical Financials'!C80 -> -1.67 | D21: ='Historical Financials'!D80 -> -1.2 | E21: ='Historical Financials'!E80 -> 0.4 | F21: ='Historical Financials'!F80 -> 0.58
B22: Book Value Per Share (₹) | C22: ='Historical Financials'!C113/C218 -> 21.587073 | D22: ='Historical Financials'!D113/D218 -> 23.256815 | E22: ='Historical Financials'!E113/E218 -> 23.509217 | F22: ='Historical Financials'!F113/F218 -> 33.406811
B24: COST STRUCTURE KPIs
B25: Employee Cost (% of Revenue) | C25: ='Historical Financials'!C29/'Historical Financials'!C12 -> 0.38945862 | D25: ='Historical Financials'!D29/'Historical Financials'!D12 -> 0.20695013 | E25: ='Historical Financials'!E29/'Historical Financials'!E12 -> 0.13694898 | F25: ='Historical Financials'!F29/'Historical Financials'!F12 -> 0.12636467
B26: ESOP (% of Revenue) | C26: ='Historical Financials'!C28/'Historical Financials'!C12 -> 0.20939661 | D26: ='Historical Financials'!D28/'Historical Financials'!D12 -> 0.071479022 | E26: ='Historical Financials'!E28/'Historical Financials'!E12 -> 0.042512795 | F26: ='Historical Financials'!F28/'Historical Financials'!F12 -> 0.039421034
B27: Cash Employee Cost (% of Revenue) | C27: =C25-C26 -> 0.18006201 | D27: =D25-D26 -> 0.13547111 | E27: =E25-E26 -> 0.09443619 | F27: =F25-F26 -> 0.086943635
B28: Marketing & Advertising (% of Revenue) | C28: ='Historical Financials'!C32/'Historical Financials'!C12 -> 0.38945862 | D28: ='Historical Financials'!D32/'Historical Financials'!D12 -> 0.20695013 | E28: ='Historical Financials'!E32/'Historical Financials'!E12 -> 0.043420835 | F28: ='Historical Financials'!F32/'Historical Financials'!F12 -> 0.042632021
B29: Technology Cost (% of Revenue) | C29: ='Historical Financials'!C33/'Historical Financials'!C12 -> 0.068924398 | D29: ='Historical Financials'!D33/'Historical Financials'!D12 -> 0.054668739 | E29: ='Historical Financials'!E33/'Historical Financials'!E12 -> 0.040036322 | F29: ='Historical Financials'!F33/'Historical Financials'!F12 -> 0.031813466
B30: Delivery & Fulfilment (% of Revenue) | C30: ='Historical Financials'!C21/'Historical Financials'!C12 -> 0.4326258 | D30: ='Historical Financials'!D21/'Historical Financials'!D12 -> 0.35838395 | E30: ='Historical Financials'!E21/'Historical Financials'!E12 -> 0.32317979 | F30: ='Historical Financials'!F21/'Historical Financials'!F12 -> 0.28296201
B31: Total Other Expenses (% of Revenue) | C31: ='Historical Financials'!C40/'Historical Financials'!C12 -> 0.91938946 | D31: ='Historical Financials'!D40/'Historical Financials'!D12 -> 0.76705749 | E31: ='Historical Financials'!E40/'Historical Financials'!E12 -> 0.6216774 | F31: ='Historical Financials'!F40/'Historical Financials'!F12 -> 0.56725782
B33: CAPITAL EFFICIENCY KPIs
B34: Return on Equity (%) | C34: ='Historical Financials'!C76/'Historical Financials'!C113 -> -0.074125705 | D34: ='Historical Financials'!D76/'Historical Financials'!D113 -> -0.049917746 | E34: ='Historical Financials'!E76/'Historical Financials'!E113 -> 0.017200823 | F34: ='Historical Financials'!F76/'Historical Financials'!F113 -> 0.017387001
B35: Return on Capital Employed (%) | C35: ='Historical Financials'!C61/('Historical Financials'!C113+'Historical Financials'!C121) -> -0.09141791 | D35: ='Historical Financials'!D61/('Historical Financials'!D113+'Historical Financials'!D121) -> -0.066577368 | E35: ='Historical Financials'!E61/('Historical Financials'!E113+'Historical Financials'!E121) -> -0.025995393 | F35: ='Historical Financials'!F61/('Historical Financials'!F113+'Historical Financials'!F121) -> 0.0066879277
B36: Asset Turnover (x) | C36: ='Historical Financials'!C12/'Historical Financials'!C107 -> 0.24199227 | D36: ='Historical Financials'!D12/'Historical Financials'!D107 -> 0.32770114 | E36: ='Historical Financials'!E12/'Historical Financials'!E107 -> 0.51866758 | F36: ='Historical Financials'!F12/'Historical Financials'!F107 -> 0.56825646
B37: Capex (% of Revenue) | C37: =ABS('Historical Financials'!C178)/'Historical Financials'!C12 -> 0.014071071 | D37: =ABS('Historical Financials'!D178)/'Historical Financials'!D12 -> 0.014550078 | E37: =ABS('Historical Financials'!E178)/'Historical Financials'!E12 -> 0.01774806 | F37: =ABS('Historical Financials'!F178)/'Historical Financials'!F12 -> 0.046238206
B38: Capex (% of Adj EBITDA) | C38: =ABS('Historical Financials'!C178)/ABS(C10) -> 0.060637205 | D38: =ABS('Historical Financials'!D178)/ABS(D10) -> 0.13464052 | E38: =ABS('Historical Financials'!E178)/ABS(E10) -> 0.57795699 | F38: =ABS('Historical Financials'!F178)/ABS(F10) -> 0.86746988
B40: WORKING CAPITAL KPIs
B41: Debtor Days | C41: ='Historical Financials'!C99/'Historical Financials'!C12*365 -> 1.3927975 | D41: ='Historical Financials'!D99/'Historical Financials'!D12*365 -> 2.320243 | E41: ='Historical Financials'!E99/'Historical Financials'!E12*365 -> 23.471603 | F41: ='Historical Financials'!F99/'Historical Financials'!F12*365 -> 35.088179
B42: Creditor Days | C42: =('Historical Financials'!C125+'Historical Financials'!C126)/'Historical Financials'!C12*365 -> 37.344383 | D42: =('Historical Financials'!D125+'Historical Financials'!D126)/'Historical Financials'!D12*365 -> 35.061449 | E42: =('Historical Financials'!E125+'Historical Financials'!E126)/'Historical Financials'!E12*365 -> 26.695559 | F42: =('Historical Financials'!F125+'Historical Financials'!F126)/'Historical Financials'!F12*365 -> 27.6955
B43: Inventory Days | C43: ='Historical Financials'!C97/'Historical Financials'!C12*365 -> 3.4819938 | D43: ='Historical Financials'!D97/'Historical Financials'!D12*365 -> 4.2795593 | E43: ='Historical Financials'!E97/'Historical Financials'!E12*365 -> 2.6514776 | F43: ='Historical Financials'!F97/'Historical Financials'!F12*365 -> 3.1734427
B44: Cash Conversion Ratio (CFO/PAT) | C44: =ROUND(('Historical Financials'!C175/'Historical Financials'!C76),2) & "x" -> 0.44x | D44: =ROUND(('Historical Financials'!D175/'Historical Financials'!D76),2) & "x" -> 0.87x | E44: =ROUND(('Historical Financials'!E175/'Historical Financials'!E76),2) & "x" -> 1.84x | F44: =ROUND(('Historical Financials'!F175/'Historical Financials'!F76),2) & "x" -> 0.58x
B45: CFO / Adjusted EBITDA | C45: =ROUND('Historical Financials'!C175/ABS(C10),2) & "x" -> -0.55x | D45: =ROUND('Historical Financials'!D175/ABS(D10),2) & "x" -> -1.1x | E45: =ROUND('Historical Financials'!E175/ABS(E10),2) & "x" -> 1.74x | F45: =ROUND('Historical Financials'!F175/ABS(F10),2) & "x" -> 0.29x
B47: LIQUIDITY & LEVERAGE KPIs
B48: Cash & Cash Equivalents (₹ Cr) | C48: ='Historical Financials'!C100 -> 392 | D48: ='Historical Financials'!D100 -> 218 | E48: ='Historical Financials'!E100 -> 309 | F48: ='Historical Financials'!F100 -> 666
B49: Total Liquid Assets (₹ Cr) | C49: ='Historical Financials'!C100+'Historical Financials'!C98+'Historical Financials'!C101 -> 3207 | D49: ='Historical Financials'!D100+'Historical Financials'!D98+'Historical Financials'!D101 -> 5502 | E49: ='Historical Financials'!E100+'Historical Financials'!E98+'Historical Financials'!E101 -> 2011 | F49: ='Historical Financials'!F100+'Historical Financials'!F98+'Historical Financials'!F101 -> 5886
B50: Net Cash Position (₹ Cr) | C50: ='Historical Financials'!C100+'Historical Financials'!C98+'Historical Financials'!C90+'Historical Financials'!C91-'Historical Financials'!C121-'Historical Financials'!C127 -> 10212 | D50: ='Historical Financials'!D100+'Historical Financials'!D98+'Historical Financials'!D90+'Historical Financials'!D91-'Historical Financials'!D121-'Historical Financials'!D127 -> 8047 | E50: ='Historical Financials'!E100+'Historical Financials'!E98+'Historical Financials'!E90+'Historical Financials'!E91-'Historical Financials'!E121-'Historical Financials'!E127 -> 11639 | F50: ='Historical Financials'!F100+'Historical Financials'!F98+'Historical Financials'!F90+'Historical Financials'!F91-'Historical Financials'!F121-'Historical Financials'!F127 -> 14615
B51: Interest Coverage (x) | C51: ='Historical Financials'!C61/('Historical Financials'!C63+'Historical Financials'!C64) -> -63.291667 | D51: ='Historical Financials'!D61/('Historical Financials'!D63+'Historical Financials'!D64) -> -20.646154 | E51: -6.7 | F51: -1.5
A54: # | B54: SEGMENT FINANCIAL KPIs
B55: Food Delivery | C55: ='Historical Financials'!C7 -> 3415 | D55: ='Historical Financials'!D7 -> 4533 | E55: ='Historical Financials'!E7 -> 6361 | F55: ='Historical Financials'!F7 -> 8080
B56: Blinkit | C56: ='Historical Financials'!C8 -> - | D56: ='Historical Financials'!D8 -> 806 | E56: ='Historical Financials'!E8 -> 2301 | F56: ='Historical Financials'!F8 -> 5206
B57: Hyperpure | C57: ='Historical Financials'!C9 -> 538 | D57: ='Historical Financials'!D9 -> 1506 | E57: ='Historical Financials'!E9 -> 3172 | F57: ='Historical Financials'!F9 -> 6196
B58: District / Going Out | C58: ='Historical Financials'!C10 -> - | D58: ='Historical Financials'!D10 -> - | E58: ='Historical Financials'!E10 -> 258 | F58: ='Historical Financials'!F10 -> 737
B59: Others | C59: ='Historical Financials'!C11 -> 240 | D59: ='Historical Financials'!D11 -> 234 | E59: ='Historical Financials'!E11 -> 22 | F59: ='Historical Financials'!F11 -> 24
B61: SEGMENT REVENUE YoY GROWTH (%)
B62: Food Delivery | C62: - | D62: =(D55-C55)/C55 -> 0.32737921 | E62: =(E55-D55)/D55 -> 0.40326495 | F62: =(F55-E55)/E55 -> 0.27024053
B63: Blinkit | C63: - | D63: - | E63: =(E56-D56)/D56 -> 1.8548387 | F63: =(F56-E56)/E56 -> 1.2624946
B64: Hyperpure | C64: - | D64: =(D57-C57)/C57 -> 1.7992565 | E64: =(E57-D57)/D57 -> 1.1062417 | F64: =(F57-E57)/E57 -> 0.95334174
B65: District / Going Out | C65: - | D65: - | E65: - | F65: =(F58-E58)/E58 -> 1.8565891
B67: SEGMENT REVENUE MIX (% of Total)
B68: Food Delivery | C68: =C55/C6 -> 0.81445266 | D68: =D55/D6 -> 0.64034468 | E68: =E55/E6 -> 0.52509493 | F68: =F55/F6 -> 0.39915032
B69: Blinkit | C69: - | D69: =D56/D6 -> 0.11385789 | E69: =E56/E6 -> 0.18994552 | F69: =F56/F6 -> 0.25717532
B70: Hyperpure | C70: =C57/C8 -> 0.28770053 | D70: =D57/D8 -> 0.48084291 | E70: =E57/E8 -> 0.59657702 | F70: =F57/F8 -> 0.6922905
B71: District / Going Out | C71: - | D71: - | E71: =E58/E6 -> 0.021297672 | F71: =F58/F6 -> 0.036407647
B73: SEGMENT ADJUSTED EBITDA (₹ Cr)
B74: Food Delivery | C74: ='Historical Financials'!C46 -> -766 | D74: ='Historical Financials'!D46 -> -5 | E74: ='Historical Financials'!E46 -> 912 | F74: ='Historical Financials'!F46 -> 1505
B75: Blinkit | C75: ='Historical Financials'!C47 -> - | D75: ='Historical Financials'!D47 -> -1016 | E75: ='Historical Financials'!E47 -> -384 | F75: ='Historical Financials'!F47 -> -292
B76: Hyperpure | C76: ='Historical Financials'!C48 -> -139 | D76: ='Historical Financials'!D48 -> -194 | E76: ='Historical Financials'!E48 -> -126 | F76: ='Historical Financials'!F48 -> -84
B77: District / Going Out | C77: ='Historical Financials'!C49 -> - | D77: ='Historical Financials'!D49 -> - | E77: ='Historical Financials'!E49 -> -6 | F77: ='Historical Financials'!F49 -> -38
B78: Others | C78: ='Historical Financials'!C50 -> -68 | D78: ='Historical Financials'!D50 -> -3 | E78: ='Historical Financials'!E50 -> -24 | F78: ='Historical Financials'!F50 -> -
B80: SEGMENT ADJUSTED EBITDA MARGIN (%)
B81: Food Delivery | C81: =C74/C55 -> -0.22430454 | D81: =D74/D55 -> -0.0011030223 | E81: =E74/E55 -> 0.14337368 | F81: =F74/F55 -> 0.18626238
B82: Blinkit | C82: - | D82: =D75/D56 -> -1.2605459 | E82: =E75/E56 -> -0.16688396 | F82: =F75/F56 -> -0.056089128
B83: Hyperpure | C83: =C76/C57 -> -0.25836431 | D83: =D76/D57 -> -0.12881806 | E83: =E76/E57 -> -0.039722573 | F83: =F76/F57 -> -0.013557134
B84: District / Going Out | C84: - | D84: - | E84: =E77/E58 -> -0.023255814 | F84: =F77/F58 -> -0.05156038
A87: # | B87: FOOD DELIVERY OPERATIONAL KPIs
B88: ORDER & VALUE METRICS
B89: Gross Order Value (₹ Cr) | C89: 21300 | D89: 26305 | E89: 32224 | F89: 38646
B90: Net Order Value (₹ Cr) | C90: - | D90: 22501 | E90: 27478 | F90: 32862
B91: Platform Revenue | C91: 3415 | D91: 4533 | E91: 6361 | F91: 8080
B92: Adjusted Revenue (₹ Cr) | C92: 4763 | D92: 6147 | E92: 7792 | F92: 9418
B93: Adjusted Revenue (% of GOV) | C93: 0.224 | D93: 0.234 | E93: 0.242 | F93: 0.244
B94: Adjusted Revenue (% of NOV) | C94: - | D94: 0.273 | E94: 0.284 | F94: 0.287
B96: VOLUME & CUSTOMER METRICS
B97: Number of Orders (millions) | C97: 535 | D97: 647 | E97: 753 | F97: 853
B98: Average Order Value - AOV (₹) | C98: 398 | D98: 407 | E98: 428 | F98: 453
B99: Net AOV - NAOV (₹) | C99: - | D99: 348 | E99: 365 | F99: 385
B100: Monthly Transacting Users - MTU (millions) | C100: 14.7 | D100: 17 | E100: 18.4 | F100: 20.6
B101: Annual Transacting Customers - ATC (millions) | C101: - | D101: 58 | E101: 63 | F101: n/a
B102: Annual Order Frequency | C102: - | D102: 11.1 | E102: 11.9 | F102: n/a
B103: Delivery Partners ('000) | C103: 285 | D103: 326 | E103: 400 | F103: 473
B104: Contribution (₹ Cr) | C104: - | D104: 1196 | E104: 2225 | F104: 3092
B105: Take Rate | D105: 0.172 | E105: 0.197 | F105: 0.209
B107: SUPPLY-SIDE METRICS
B108: Active Restaurant Partners ('000) | C108: 180 | D108: 210 | E108: 247 | F108: 297
B109: Active Delivery Partners ('000) | C109: 285 | D109: 326 | E109: 400 | F109: 473
B110: Active Cities | C110: 1,000+ | D110: - | E110: - | F110: -
B112: PROFITABILITY & UNIT ECONOMICS
B113: Contribution (₹ Cr) | C113: - | D113: 1196 | E113: 2225 | F113: 3092
B114: Contribution Margin | C114: 1.7% (of GOV) | D114: 0.053 | E114: 0.081 | F114: 0.094
B115: Adj EBITDA (₹ Cr) | C115: -766 | D115: -10 | E115: 912 | F115: 1505
B116: Adj EBITDA Margin (% of NOV) | C116: -0.036 | D116: 0 | E116: 0.033 | F116: 0.046
A119: # | B119: BLINKIT QUICK COMMERCE OPERATIONAL KPIs
...

Sheet Assumptions
B2: Assumptions - ETERNAL LIMITED | ₹ Crores
B3: Scenario | C3: Base Case
B4: =MATCH(TRIM(C3),{"Bear Case","Base Case","Bull Case"},0) -> 2
B5: Items | C5: Scenario | D5: FY25A | E5: FY26E | F5: FY27E | G5: FY28E | H5: FY29E | I5: Notes/Sources
A7: # | B7: FOOD DELIVERY ASSUMPTIONS
B8: FD GOV Growth % YoY | C8: Bear Case | E8: 0.13 | F8: 0.15 | G8: 0.14 | H8: 0.12
C9: Base Case | E9: 0.18 | F9: 0.2 | G9: 0.19 | H9: 0.17
C10: Bull Case | E10: 0.23 | F10: 0.25 | G10: 0.22 | H10: 0.2
B11: FD GOV Growth % YoY | C11: Active | E11: =IF($B$4=1,E8,IF($B$4=2,E9,E10)) -> 0.18 | F11: =IF($B$4=1,F8,IF($B$4=2,F9,F10)) -> 0.2 | G11: =IF($B$4=1,G8,IF($B$4=2,G9,G10)) -> 0.19 | H11: =IF($B$4=1,H8,IF($B$4=2,H9,H10)) -> 0.17 | I11: Q2FY26 concall: 'expecting 15% this year; 20%+ long term'
B13: FD Take Rate (Rev÷GOV) | C13: Bear Case | D13: 0.209 | E13: 0.205 | F13: 0.21 | G13: 0.215 | H13: 0.215
C14: Base Case | E14: 0.215 | F14: 0.22 | G14: 0.225 | H14: 0.225
C15: Bull Case | E15: 0.22 | F15: 0.225 | G15: 0.23 | H15: 0.235
B16: FD Take Rate (Rev÷GOV) | C16: Active | D16: =D13 -> 0.209 | E16: =IF($B$4=1,E13,IF($B$4=2,E14,E15)) -> 0.215 | F16: =IF($B$4=1,F13,IF($B$4=2,F14,F15)) -> 0.22 | G16: =IF($B$4=1,G13,IF($B$4=2,G14,G15)) -> 0.225 | H16: =IF($B$4=1,H13,IF($B$4=2,H14,H15)) -> 0.225 | I16: FY22: 16% → FY25: 20.9%. Ceiling 22.5% - rest. pushback risk
B18: FD EBITDA Margin % NOV | C18: Bear Case | D18: 0.046 | E18: 0.048 | F18: 0.05 | G18: 0.052 | H18: 0.053
C19: Base Case | E19: 0.052 | F19: 0.055 | G19: 0.057 | H19: 0.058
C20: Bull Case | E20: 0.056 | F20: 0.058 | G20: 0.06 | H20: 0.06
B21: FD EBITDA Margin % NOV | C21: Active | D21: =D18 -> 0.046 | E21: =IF($B$4=1,E18,IF($B$4=2,E19,E20)) -> 0.052 | F21: =IF($B$4=1,F18,IF($B$4=2,F19,F20)) -> 0.055 | G21: =IF($B$4=1,G18,IF($B$4=2,G19,G20)) -> 0.057 | H21: =IF($B$4=1,H18,IF($B$4=2,H19,H20)) -> 0.058 | I21: Postal ballot Feb 2026: steady state 5-6% of NOV confirmed
B23: FD MTU (mn) | C23: Bear Case | D23: 20.6 | E23: 21.5 | F23: 23 | G23: 24.5 | H23: 26
C24: Base Case | E24: 22.5 | F24: 24.5 | G24: 26.5 | H24: 28.5
C25: Bull Case | E25: 23.5 | F25: 26 | G25: 28.5 | H25: 31
B26: FD MTU (mn) | C26: Active | D26: =D23 -> 20.6 | E26: =IF($B$4=1,E23,IF($B$4=2,E24,E25)) -> 22.5 | F26: =IF($B$4=1,F23,IF($B$4=2,F24,F25)) -> 24.5 | G26: =IF($B$4=1,G23,IF($B$4=2,G24,G25)) -> 26.5 | H26: =IF($B$4=1,H23,IF($B$4=2,H24,H25)) -> 28.5 | I26: FY22-25 avg 12% growth; decelerating to 9%
B28: FD AOV (₹) | C28: Bear Case | D28: 453 | E28: 468 | F28: 487 | G28: 507 | H28: 527
C29: Base Case | E29: 473 | F29: 493 | G29: 514 | H29: 536
C30: Bull Case | E30: 478 | F30: 500 | G30: 522 | H30: 545
B31: FD AOV (₹) | C31: Active | D31: =D28 -> 453 | E31: =IF($B$4=1,E28,IF($B$4=2,E29,E30)) -> 473 | F31: =IF($B$4=1,F28,IF($B$4=2,F29,F30)) -> 493 | G31: =IF($B$4=1,G28,IF($B$4=2,G29,G30)) -> 514 | H31: =IF($B$4=1,H28,IF($B$4=2,H29,H30)) -> 536 | I31: Historical CAGR 4.4%; using 4.5%/yr premium mix
A34: # | B34: BLINKIT QUICK COMMERCE (Probability-Weighted: 40% Rational / 60% Irrational)
B35: Blinkit NOV Growth % YoY | C35: Bear Case | D35: 1.13 | E35: 0.35 | F35: 0.35 | G35: 0.25 | H35: 0.15
C36: Base Case | E36: 0.5 | F36: 0.5 | G36: 0.35 | H36: 0.2
C37: Bull Case | E37: 0.9 | F37: 0.65 | G37: 0.45 | H37: 0.28
B38: Blinkit NOV Growth % YoY | C38: Active | D38: =D35 -> 1.13 | E38: =IF($B$4=1,E35,IF($B$4=2,E36,E37)) -> 0.5 | F38: =IF($B$4=1,F35,IF($B$4=2,F36,F37)) -> 0.5 | G38: =IF($B$4=1,G35,IF($B$4=2,G36,G37)) -> 0.35 | H38: =IF($B$4=1,H35,IF($B$4=2,H36,H37)) -> 0.2 | I38: Q2FY26 run-rate 137%; H2FY26 suppressed by competition
B40: Blinkit Take Rate (Rev÷NOV) | C40: Bear Case | D40: 0.233 | E40: 0.225 | F40: 0.23 | G40: 0.235 | H40: 0.24
C41: Base Case | E41: 0.235 | F41: 0.24 | G41: 0.245 | H41: 0.25
C42: Bull Case | E42: 0.24 | F42: 0.25 | G42: 0.26 | H42: 0.27
B43: Blinkit Take Rate (Rev÷NOV) | C43: Active | D43: =D40 -> 0.233 | E43: =IF($B$4=1,E40,IF($B$4=2,E41,E42)) -> 0.235 | F43: =IF($B$4=1,F40,IF($B$4=2,F41,F42)) -> 0.24 | G43: =IF($B$4=1,G40,IF($B$4=2,G41,G42)) -> 0.245 | H43: =IF($B$4=1,H40,IF($B$4=2,H41,H42)) -> 0.25 | I43: 1P model 90% → full gross revenue recognition; ad rev growing
B45: Blinkit EBITDA Margin % NOV | C45: Bear Case | E45: 0 | F45: 0.005 | G45: 0.015 | H45: 0.025
C46: Base Case | E46: 0.01 | F46: 0.02 | G46: 0.035 | H46: 0.045
C47: Bull Case | E47: 0.025 | F47: 0.04 | G47: 0.055 | H47: 0.065
B48: Blinkit EBITDA Margin % NOV | C48: Active | E48: =IF($B$4=1,E45,IF($B$4=2,E46,E47)) -> 0.01 | F48: =IF($B$4=1,F45,IF($B$4=2,F46,F47)) -> 0.02 | G48: =IF($B$4=1,G45,IF($B$4=2,G46,G47)) -> 0.035 | H48: =IF($B$4=1,H45,IF($B$4=2,H46,H47)) -> 0.045 | I48: Base=prob.weighted. Mgmt SS target 5-6% NOV. Q3FY26 breakeven achieved
B50: Dark Store Count (EoY) | C50: Bear Case | D50: 1301 | E50: 1800 | F50: 2300 | G50: 2900 | H50: 3400
C51: Base Case | E51: 1950 | F51: 2600 | G51: 3300 | H51: 3700
C52: Bull Case | E52: 2100 | F52: 3100 | G52: 4200 | H52: 5000
B53: Dark Store Count (EoY) | C53: Active | D53: =D50 -> 1301 | E53: =IF($B$4=1,E50,IF($B$4=2,E51,E52)) -> 1950 | F53: =IF($B$4=1,F50,IF($B$4=2,F51,F52)) -> 2600 | G53: =IF($B$4=1,G50,IF($B$4=2,G51,G52)) -> 3300 | H53: =IF($B$4=1,H50,IF($B$4=2,H51,H52)) -> 3700 | I53: FY25AR p.17: aim 2,000 by Dec'25. Base=prob.weighted
B55: Blinkit AOV (₹) | C55: Bear Case | D55: 667 | E55: 678 | F55: 698 | G55: 718 | H55: 740
C56: Base Case | E56: 687 | F56: 708 | G56: 729 | H56: 751
C57: Bull Case | E57: 697 | F57: 718 | G57: 740 | H57: 762
B58: Blinkit AOV (₹) | C58: Active | D58: =D55 -> 667 | E58: =IF($B$4=1,E55,IF($B$4=2,E56,E57)) -> 687 | F58: =IF($B$4=1,F55,IF($B$4=2,F56,F57)) -> 708 | G58: =IF($B$4=1,G55,IF($B$4=2,G56,G57)) -> 729 | H58: =IF($B$4=1,H55,IF($B$4=2,H56,H57)) -> 751 | I58: 3%/yr - general merch + premium categories growing
B60: Blinkit MTU (mn) | C60: Bear Case | D60: 10.2 | E60: 14 | F60: 19 | G60: 26 | H60: 32
C61: Base Case | E61: 17 | F61: 24 | G61: 32 | H61: 39
C62: Bull Case | E62: 20 | F62: 28 | G62: 38 | H62: 47
B63: Blinkit MTU (mn) | C63: Active | D63: =D60 -> 10.2 | E63: =IF($B$4=1,E60,IF($B$4=2,E61,E62)) -> 17 | F63: =IF($B$4=1,F60,IF($B$4=2,F61,F62)) -> 24 | G63: =IF($B$4=1,G60,IF($B$4=2,G61,G62)) -> 32 | H63: =IF($B$4=1,H60,IF($B$4=2,H61,H62)) -> 39 | I63: Store expansion doubles addressable coverage
B65: Capex/Net New Store (₹ Cr) | C65: Bear Case | D65: 1.21 | E65: 1.3 | F65: 1.5 | G65: 1.6 | H65: 1.7
C66: Base Case | E66: 1.4 | F66: 1.6 | G66: 1.7 | H66: 1.8
C67: Bull Case | E67: 1.5 | F67: 1.7 | G67: 1.8 | H67: 1.9
B68: Capex/Net New Store (₹ Cr) | C68: Active | D68: =D65 -> 1.21 | E68: =IF($B$4=1,E65,IF($B$4=2,E66,E67)) -> 1.4 | F68: =IF($B$4=1,F65,IF($B$4=2,F66,F67)) -> 1.6 | G68: =IF($B$4=1,G65,IF($B$4=2,G66,G67)) -> 1.7 | H68: =IF($B$4=1,H65,IF($B$4=2,H66,H67)) -> 1.8 | I68: Q3FY26 concall: 'capex/store will increase - automation + larger stores'
A71: # | B71: HYPERPURE ASSUMPTIONS
B72: Hyperpure Revenue Growth % | C72: Bear Case | D72: 0.95 | E72: 0.4 | F72: 0.3 | G72: 0.22 | H72: 0.18
C73: Base Case | E73: 0.6 | F73: 0.45 | G73: 0.35 | H73: 0.25
C74: Bull Case | E74: 0.75 | F74: 0.55 | G74: 0.4 | H74: 0.3
B75: Hyperpure Revenue Growth % | C75: Active | D75: =D72 -> 0.95 | E75: =IF($B$4=1,E72,IF($B$4=2,E73,E74)) -> 0.6 | F75: =IF($B$4=1,F72,IF($B$4=2,F73,F74)) -> 0.45 | G75: =IF($B$4=1,G72,IF($B$4=2,G73,G74)) -> 0.35 | H75: =IF($B$4=1,H72,IF($B$4=2,H73,H74)) -> 0.25 | I75: Decelerating from 95%; FY29 at 25% - mature B2B distribution
B77: Hyperpure EBITDA Margin % Rev | C77: Bear Case | D77: -0.014 | E77: 0.003 | F77: 0.01 | G77: 0.025 | H77: 0.035
C78: Base Case | E78: 0.01 | F78: 0.02 | G78: 0.035 | H78: 0.045
C79: Bull Case | E79: 0.02 | F79: 0.03 | G79: 0.045 | H79: 0.05
B80: Hyperpure EBITDA Margin % Rev | C80: Active | D80: =D77 -> -0.014 | E80: =IF($B$4=1,E77,IF($B$4=2,E78,E79)) -> 0.01 | F80: =IF($B$4=1,F77,IF($B$4=2,F78,F79)) -> 0.02 | G80: =IF($B$4=1,G77,IF($B$4=2,G78,G79)) -> 0.035 | H80: =IF($B$4=1,H77,IF($B$4=2,H78,H79)) -> 0.045 | I80: Postal ballot: SS target 4-5% revenue. Breakeven Q3FY26 confirmed
A83: # | B83: DISTRICT / GOING OUT (10% Execution Haircut Applied)
B84: District NOV Growth % YoY | C84: Bear Case | E84: 0.5 | F84: 0.35 | G84: 0.28 | H84: 0.25
C85: Base Case | E85: 0.7 | F85: 0.5 | G85: 0.4 | H85: 0.35
C86: Bull Case | E86: 0.9 | F86: 0.65 | G86: 0.5 | H86: 0.42
B87: District NOV Growth % YoY | C87: Active | E87: =IF($B$4=1,E84,IF($B$4=2,E85,E86)) -> 0.7 | F87: =IF($B$4=1,F84,IF($B$4=2,F85,F86)) -> 0.5 | G87: =IF($B$4=1,G84,IF($B$4=2,G85,G86)) -> 0.4 | H87: =IF($B$4=1,H84,IF($B$4=2,H85,H86)) -> 0.35 | I87: Base 70% (not 80%) - 10% M&A execution haircut. FY25 NOV=₹6,618 Cr
B89: District Rev as % of NOV | C89: Bear Case | D89: 0.111 | E89: 0.08 | F89: 0.085 | G89: 0.09 | H89: 0.095
C90: Base Case | E90: 0.09 | F90: 0.095 | G90: 0.1 | H90: 0.105
C91: Bull Case | E91: 0.095 | F91: 0.1 | G91: 0.11 | H91: 0.115
B92: District Rev as % of NOV | C92: Active | D92: =D89 -> 0.111 | E92: =IF($B$4=1,E89,IF($B$4=2,E90,E91)) -> 0.09 | F92: =IF($B$4=1,F89,IF($B$4=2,F90,F91)) -> 0.095 | G92: =IF($B$4=1,G89,IF($B$4=2,G90,G91)) -> 0.1 | H92: =IF($B$4=1,H89,IF($B$4=2,H90,H91)) -> 0.105 | I92: Ticketing gross in NOV; commission only in P&L
B94: District EBITDA Margin % NOV | C94: Bear Case | D94: -0.006 | E94: -0.025 | F94: -0.015 | G94: 0 | H94: 0.015
C95: Base Case | E95: -0.015 | F95: -0.005 | G95: 0.015 | H95: 0.03
C96: Bull Case | E96: -0.005 | F96: 0.005 | G96: 0.03 | H96: 0.045
B97: District EBITDA Margin % NOV | C97: Active | D97: =D94 -> -0.006 | E97: =IF($B$4=1,E94,IF($B$4=2,E95,E96)) -> -0.015 | F97: =IF($B$4=1,F94,IF($B$4=2,F95,F96)) -> -0.005 | G97: =IF($B$4=1,G94,IF($B$4=2,G95,G96)) -> 0.015 | H97: =IF($B$4=1,H94,IF($B$4=2,H95,H96)) -> 0.03 | I97: Q3FY26: 'breakeven in next 4-6 quarters'. FY28 = first profitable year
A100: # | B100: OTHERS / BISTRO (Immaterial — Conservative)
B101: Bistro Revenue (₹ Cr) | C101: All scenarios | E101: 25 | F101: 25 | G101: 25 | H101: 25 | I101: Early stage. Modelled flat - upside optionality not captured (conservative)
B103: COST ASSUMPTIONS
B105: Delivery & Fulfilment % Rev | C105: Bear Case | D105: 0.283 | E105: 0.285 | F105: 0.278 | G105: 0.27 | H105: 0.265
C106: Base Case | E106: 0.275 | F106: 0.265 | G106: 0.255 | H106: 0.245
C107: Bull Case | E107: 0.265 | F107: 0.25 | G107: 0.238 | H107: 0.225
B108: Delivery & Fulfilment % Rev | C108: Active | D108: =D105 -> 0.283 | E108: =IF($B$4=1,E105,IF($B$4=2,E106,E107)) -> 0.275 | F108: =IF($B$4=1,F105,IF($B$4=2,F106,F107)) -> 0.265 | G108: =IF($B$4=1,G105,IF($B$4=2,G106,G107)) -> 0.255 | H108: =IF($B$4=1,H105,IF($B$4=2,H106,H107)) -> 0.245 | I108: FY22: 43.3% → FY25: 28.3%. 1pp/yr improvement assumed
B110: Advertising & Marketing % Rev | C110: Bear Case | D110: 0.043 | E110: 0.065 | F110: 0.06 | G110: 0.055 | H110: 0.052
C111: Base Case | E111: 0.05 | F111: 0.048 | G111: 0.045 | H111: 0.045
C112: Bull Case | E112: 0.04 | F112: 0.038 | G112: 0.035 | H112: 0.032
B113: Advertising & Marketing % Rev | C113: Active | D113: =D110 -> 0.043 | E113: =IF($B$4=1,E110,IF($B$4=2,E111,E112)) -> 0.05 | F113: =IF($B$4=1,F110,IF($B$4=2,F111,F112)) -> 0.048 | G113: =IF($B$4=1,F110,IF($B$4=2,G111,G112)) -> 0.045 | H113: =IF($B$4=1,H110,IF($B$4=2,H111,H112)) -> 0.045 | I113: 0.5pp/yr decline - ecosystem drives organic traffic
B115: Technology % Revenue | C115: Bear Case | D115: 0.032 | E115: 0.032 | F115: 0.03 | G115: 0.028 | H115: 0.027
C116: Base Case | E116: 0.03 | F116: 0.028 | G116: 0.026 | H116: 0.025
C117: Bull Case | E117: 0.028 | F117: 0.026 | G117: 0.024 | H117: 0.023
B118: Technology % Revenue | C118: Active | D118: =D115 -> 0.032 | E118: =IF($B$4=1,E115,IF($B$4=2,E116,E117)) -> 0.03 | F118: =IF($B$4=1,F115,IF($B$4=2,F116,F117)) -> 0.028 | G118: =IF($B$4=1,G115,IF($B$4=2,G116,G117)) -> 0.026 | H118: =IF($B$4=1,H115,IF($B$4=2,H116,H117)) -> 0.025 | I118: Classic op. leverage - tech fixed costs on fast-growing rev base
B120: Effective Tax Rate | C120: Bear Case | D120: 0.24 | E120: 0.24 | F120: 0.25 | G120: 0.25 | H120: 0.25
C121: Base Case | E121: 0.22 | F121: 0.22 | G121: 0.25 | H121: 0.25
C122: Bull Case | E122: 0.16 | F122: 0.2 | G122: 0.24 | H122: 0.25
B123: Effective Tax Rate | C123: Active | D123: =D120 -> 0.24 | E123: =IF($B$4=1,E120,IF($B$4=2,E121,E122)) -> 0.22 | F123: =IF($B$4=1,F120,IF($B$4=2,F121,F122)) -> 0.22 | G123: =IF($B$4=1,G120,IF($B$4=2,G121,G122)) -> 0.25 | H123: =IF($B$4=1,H120,IF($B$4=2,H121,H122)) -> 0.25 | I123: CF losses ₹5,908 Cr (FY25 AR Note 34). Setoff FY26-27 → lower ETR
A126: # | B126: DEPRECIATION & AMORTISATION (Base Case — Hard Inputs)
B127: Depreciation on PPE (₹ Cr) | C127: Base | D127: 247 | E127: 380 | F127: 480 | G127: 560 | H127: 620 | I127: 25% on opening PPE blended 4yr life per AR policy
B128: Amortisation of Intangibles (₹ Cr) | C128: Base | D128: 287 | E128: 250 | F128: 200 | G128: 160 | H128: 130 | I128: Blinkit/Orbgen intangibles winding down. No new M&A
B129: Depreciation on ROU Assets (₹ Cr) | C129: Base | D129: 329 | E129: 500 | F129: 700 | G129: 870 | H129: 990 | I129: IND-AS 116. Avg ROU/store ₹1.5 Cr × 25% dep rate
B130: Total D&A (₹ Cr) | D130: =SUM(D127:D129) -> 863 | E130: =SUM(E127:E129) -> 1130 | F130: =SUM(F127:F129) -> 1380 | G130: =SUM(G127:G129) -> 1590 | H130: =SUM(H127:H129) -> 1740
...

Sheet Revenue Model
B2: REVENUE MODEL - ETERNAL LIMITED
B3: Particulars | C3: FY22A | D3: FY23A | E3: FY24A | F3: FY25A | G3: FY26E | H3: FY27E | I3: FY28E | J3: FY29E
B5: A. FOOD DELIVERY
B6: Operating Metrics
B7: Gross Order Value - GOV | C7: =KPIs!C89 -> 21300 | D7: =KPIs!D89 -> 26305 | E7: =KPIs!E89 -> 32224 | F7: =KPIs!F89 -> 38646 | G7: =F7*(1+Assumptions!E11) -> 45602.28 | H7: =G7*(1+Assumptions!F11) -> 54722.736 | I7: =H7*(1+Assumptions!G11) -> 65120.056 | J7: =I7*(1+Assumptions!H11) -> 76190.465
B8: NOV % of GOV | C8: - | D8: 0.855 | E8: 0.853 | F8: 0.85 | G8: 0.85 | H8: 0.845 | I8: 0.84 | J8: 0.835
B9: Net Order Value - NOV | C9: - | D9: =D7*D8 -> 22490.775 | E9: =E7*E8 -> 27487.072 | F9: =F7*F8 -> 32849.1 | G9: =G7*G8 -> 38761.938 | H9: =H7*H8 -> 46240.712 | I9: =I7*I8 -> 54700.847 | J9: =J7*J8 -> 63619.039
B10: MTU (mn) | C10: =KPIs!C100 -> 14.7 | D10: =KPIs!D100 -> 17 | E10: =KPIs!E100 -> 18.4 | F10: =KPIs!F100 -> 20.6 | G10: =Assumptions!E26 -> 22.5 | H10: =Assumptions!F26 -> 24.5 | I10: =Assumptions!G26 -> 26.5 | J10: =Assumptions!H26 -> 28.5
B11: AOV (₹) | C11: =KPIs!C98 -> 398 | D11: =KPIs!D98 -> 407 | E11: =KPIs!E98 -> 428 | F11: =KPIs!F98 -> 453 | G11: =Assumptions!E31 -> 473 | H11: =Assumptions!F31 -> 493 | I11: =Assumptions!G31 -> 514 | J11: =Assumptions!H31 -> 536
B12: Annual Orders (mn) | C12: =KPIs!C97 -> 535 | D12: =KPIs!D97 -> 647 | E12: =KPIs!E97 -> 753 | F12: =KPIs!F97 -> 853 | G12: =G10*12*3.45 -> 931.5 | H12: =H10*12*3.45 -> 1014.3 | I12: =I10*12*3.45 -> 1097.1 | J12: =J10*12*3.45 -> 1179.9
B13: Avg Monthly Active Restaurants ('000) | C13: =KPIs!C108 -> 180 | D13: =KPIs!D108 -> 210 | E13: =KPIs!E108 -> 247 | F13: =KPIs!F108 -> 297 | G13: =F13*1.11 -> 329.67 | H13: =G13*1.1 -> 362.637 | I13: =H13*1.1 -> 398.9007 | J13: =I13*1.09 -> 434.80176
B14: Avg Monthly Active Delivery Partners ('000) | C14: =KPIs!C103 -> 285 | D14: =KPIs!D103 -> 326 | E14: =KPIs!E103 -> 400 | F14: =KPIs!F103 -> 473 | G14: =F14*1.11 -> 525.03 | H14: =G14*1.1 -> 577.533 | I14: =H14*1.1 -> 635.2863 | J14: =I14*1.09 -> 692.46207
B16: Revenue Build
B17: Take Rate | C17: - | D17: =KPIs!D105 -> 0.172 | E17: =KPIs!E105 -> 0.197 | F17: =KPIs!F105 -> 0.209 | G17: =Assumptions!E16 -> 0.215 | H17: =Assumptions!F16 -> 0.22 | I17: =Assumptions!G16 -> 0.225 | J17: =Assumptions!H16 -> 0.225
B18: Food Delivery Platform Revenue | C18: =KPIs!C91 -> 3415 | D18: =KPIs!D91 -> 4533 | E18: =KPIs!E91 -> 6361 | F18: =KPIs!F91 -> 8080 | G18: =G7*G17 -> 9804.4902 | H18: =H7*H17 -> 12039.002 | I18: =I7*I17 -> 14652.013 | J18: =J7*J17 -> 17142.855
B20: Profitability
B21: Adj EBITDA Margin % of NOV | C21: =KPIs!C116 -> -0.036 | D21: =KPIs!D116 -> 0 | E21: =KPIs!E116 -> 0.033 | F21: =KPIs!F116 -> 0.046 | G21: =Assumptions!E21 -> 0.052 | H21: =Assumptions!F21 -> 0.055 | I21: =Assumptions!G21 -> 0.057 | J21: =Assumptions!H21 -> 0.058
B22: Adj EBITDA - Food Delivery | C22: =KPIs!C115 -> -766 | D22: =KPIs!D115 -> -10 | E22: =KPIs!E115 -> 912 | F22: =KPIs!F115 -> 1505 | G22: =G9*G21 -> 2015.6208 | H22: =H9*H21 -> 2543.2392 | I22: =I9*I21 -> 3117.9483 | J22: =J9*J21 -> 3689.9042
B25: B. BLINKIT
B26: Store Metrics
B27: Dark Store Count (EoY) | C27: - | D27: =KPIs!D133 -> 377 | E27: =KPIs!E133 -> 526 | F27: =KPIs!F133 -> 1301 | G27: =Assumptions!E53 -> 1950 | H27: =Assumptions!F53 -> 2600 | I27: =Assumptions!G53 -> 3300 | J27: =Assumptions!H53 -> 3700
B28: Net New Store Additions | C28: - | D28: 0 | E28: =KPIs!E134 -> 149 | F28: =KPIs!F134 -> 775 | G28: =G27-F27 -> 649 | H28: =H27-G27 -> 650 | I28: =I27-H27 -> 700 | J28: =J27-I27 -> 400
B29: Capex / New Store (₹ Cr) | C29: - | D29: - | E29: - | F29: =Assumptions!D68 -> 1.21 | G29: =Assumptions!E68 -> 1.4 | H29: =Assumptions!F68 -> 1.6 | I29: =Assumptions!G68 -> 1.7 | J29: =Assumptions!H68 -> 1.8
B30: Blinkit Capex (₹ Cr) | C30: - | D30: - | E30: - | F30: =F29*F28 -> 937.75 | G30: =G29*G28 -> 908.6 | H30: =H29*H28 -> 1040 | I30: =I29*I28 -> 1190 | J30: =J29*J28 -> 720
B32: Revenue Build
B33: NOV Growth % YoY | C33: - | D33: - | E33: 0.85 | F33: 1.13 | G33: =Assumptions!E38 -> 0.5 | H33: =Assumptions!F38 -> 0.5 | I33: =Assumptions!G38 -> 0.35 | J33: =Assumptions!H38 -> 0.2
B34: NOV (₹ Cr) [FY23 = Unaudited MIS] | C34: - | D34: =KPIs!D122 -> 5690 | E34: =KPIs!E122 -> 10503 | F34: =KPIs!F122 -> 22371 | G34: =F34*(1+G33) -> 33556.5 | H34: =G34*(1+H33) -> 50334.75 | I34: =H34*(1+I33) -> 67951.913 | J34: =I34*(1+J33) -> 81542.295
B35: Take Rate (Revenue ÷ NOV) | C35: - | D35: 0.142 | E35: 0.219 | F35: 0.233 | G35: =Assumptions!E43 -> 0.235 | H35: =Assumptions!F43 -> 0.24 | I35: =Assumptions!G43 -> 0.245 | J35: =Assumptions!H43 -> 0.25
B36: Blinkit Revenue (₹ Cr) | C36: - | D36: =KPIs!D123 -> 806 | E36: =KPIs!E123 -> 2301 | F36: =KPIs!F123 -> 5206 | G36: =G34*G35 -> 7885.7775 | H36: =H34*H35 -> 12080.34 | I36: =I34*I35 -> 16648.219 | J36: =J34*J35 -> 20385.574
B38: Profitability [Probability-Weighted: 40% Rational + 60% Irrational]
B39: EBITDA Margin - Rational Scenario (40%) | C39: - | D39: - | E39: - | F39: - | G39: 0.02 | H39: 0.035 | I39: 0.05 | J39: 0.06
B40: EBITDA Margin - Irrational Scenario (60%) | C40: - | D40: - | E40: - | F40: - | G40: 0.003 | H40: 0.01 | I40: 0.025 | J40: 0.035
B41: EBITDA Margin % of NOV - Probability-Weighted | C41: - | D41: - | E41: - | F41: - | G41: =0.4*G39+0.6*G40 -> 0.0098 | H41: =0.4*H39+0.6*H40 -> 0.02 | I41: =0.4*I39+0.6*I40 -> 0.035 | J41: =0.4*J39+0.6*J40 -> 0.045
B42: Adj EBITDA - Blinkit (₹ Cr) | C42: - | D42: =KPIs!D145 -> -1016 | E42: =KPIs!E145 -> -384 | F42: =KPIs!F145 -> -292 | G42: =G34*G41 -> 328.8537 | H42: =H34*H41 -> 1006.695 | I42: =I34*I41 -> 2378.3169 | J42: =J34*J41 -> 3669.4033
B45: C. HYPERPURE B2B SUPPLIES
B46: Revenue (₹ Cr) | C46: =KPIs!C151 -> 538 | D46: =KPIs!D151 -> 1506 | E46: =KPIs!E151 -> 3172 | F46: =KPIs!F151 -> 6196 | G46: =F46*(1+Assumptions!E75) -> 9913.6 | H46: =G46*(1+Assumptions!F75) -> 14374.72 | I46: =H46*(1+Assumptions!G75) -> 19405.872 | J46: =I46*(1+Assumptions!H75) -> 24257.34
B47: YoY Revenue Growth % | C47: =KPIs!C152 -> 1.7 | D47: =KPIs!D152 -> 1.8 | E47: =KPIs!E152 -> 1.11 | F47: =KPIs!F152 -> 0.95 | G47: =Assumptions!E75 -> 0.6 | H47: =Assumptions!F75 -> 0.45 | I47: =Assumptions!G75 -> 0.35 | J47: =Assumptions!H75 -> 0.25
B48: Adj EBITDA - Hyperpure (₹ Cr) | C48: =KPIs!C159 -> -139 | D48: =KPIs!D159 -> -194 | E48: =KPIs!E159 -> -126 | F48: =KPIs!F159 -> -84 | G48: =G46*G49 -> 99.136 | H48: =H46*H49 -> 287.4944 | I48: =I46*I49 -> 679.20552 | J48: =J46*J49 -> 1091.5803
B49: Adj EBITDA Margin % of Revenue | C49: =KPIs!C160 -> -0.258 | D49: =KPIs!D160 -> -0.129 | E49: =KPIs!E160 -> -0.039 | F49: =KPIs!F160 -> -0.014 | G49: =Assumptions!E80 -> 0.01 | H49: =Assumptions!F80 -> 0.02 | I49: =Assumptions!G80 -> 0.035 | J49: =Assumptions!H80 -> 0.045
B51: D. DISTRICT / GOING OUT [10% execution haircut on NOV growth]
B52: NOV (₹ Cr) | C52: =KPIs!C166 -> - | D52: =KPIs!D166 -> 1132 | E52: =KPIs!E166 -> 2581 | F52: =KPIs!F166 -> 6618 | G52: =F52*(1+Assumptions!E87) -> 11250.6 | H52: =G52*(1+Assumptions!F87) -> 16875.9 | I52: =H52*(1+Assumptions!G87) -> 23626.26 | J52: =I52*(1+Assumptions!H87) -> 31895.451
B53: Revenue as % of NOV | C53: - | D53: - | E53: - | F53: =Assumptions!D92 -> 0.111 | G53: =Assumptions!E92 -> 0.09 | H53: =Assumptions!F92 -> 0.095 | I53: =Assumptions!G92 -> 0.1 | J53: =Assumptions!H92 -> 0.105
B54: District Revenue (₹ Cr) | C54: =KPIs!C169 -> - | D54: =KPIs!D169 -> 171 | E54: =KPIs!E169 -> 258 | F54: =KPIs!F169 -> 737 | G54: =G52*G53 -> 1012.554 | H54: =H52*H53 -> 1603.2105 | I54: =I52*I53 -> 2362.626 | J54: =J52*J53 -> 3349.0224
B55: EBITDA Margin % of NOV - Base | C55: =KPIs!C171 -> - | D55: =KPIs!D171 -> -0.011 | E55: =KPIs!E171 -> -0.002 | F55: =KPIs!F171 -> -0.006 | G55: =Assumptions!E97 -> -0.015 | H55: =Assumptions!F97 -> -0.005 | I55: =Assumptions!G97 -> 0.015 | J55: =Assumptions!H97 -> 0.03
B56: Adj EBITDA - District (₹ Cr) | C56: =KPIs!C170 -> - | D56: =KPIs!D170 -> -13 | E56: =KPIs!E170 -> -6 | F56: =KPIs!F170 -> -38 | G56: =G52*G55 -> -168.759 | H56: =H52*H55 -> -84.3795 | I56: =I52*I55 -> 354.3939 | J56: =J52*J55 -> 956.86353
B58: E. OTHERS / BISTRO
B59: Others Revenue (₹ Cr) | C59: ='Historical Financials'!C11 -> 240 | D59: ='Historical Financials'!D11 -> 234 | E59: ='Historical Financials'!E11 -> 22 | F59: ='Historical Financials'!F11 -> 24 | G59: =Assumptions!E101 -> 25 | H59: =Assumptions!F101 -> 25 | I59: =Assumptions!G101 -> 25 | J59: =Assumptions!H101 -> 25
B60: Others Adj EBITDA (₹ Cr) | C60: - | D60: - | E60: - | F60: - | G60: -15 | H60: -10 | I60: -8 | J60: -5
B62: F. GROUP CONSOLIDATION
B63: TOTAL REVENUE FROM OPERATIONS | C63: =KPIs!C6 -> 4193 | D63: =D18+D36+D46+D54+D59 -> 7250 | E63: =E18+E36+E46+E54+E59 -> 12114 | F63: =F18+F36+F46+F54+F59 -> 20243 | G63: =G18+G36+G46+G54+G59 -> 28641.422 | H63: =H18+H36+H46+H54+H59 -> 40122.272 | I63: =I18+I36+I46+I54+I59 -> 53093.729 | J63: =J18+J36+J46+J54+J59 -> 65159.791
B64: YoY Revenue Growth % | C64: - | D64: =D63/C63-1 -> 0.72907226 | E64: =E63/D63-1 -> 0.67089655 | F64: =F63/E63-1 -> 0.67104177 | G64: =G63/F63-1 -> 0.41488029 | H64: =H63/G63-1 -> 0.40084779 | I64: =I63/H63-1 -> 0.32329816 | J64: =J63/I63-1 -> 0.22725964
B65: Revenue CAGR FY25–FY29 | J65: =(J63/F63)^(1/4)-1 -> 0.33944906
B66: Food Delivery Mix % | C66: =C18/C63 -> 0.81445266 | D66: =D18/D63 -> 0.62524138 | E66: =E18/E63 -> 0.52509493 | F66: =F18/F63 -> 0.39915032 | G66: =G18/G63 -> 0.34231856 | H66: =H18/H63 -> 0.30005783 | I66: =I18/I63 -> 0.27596503 | J66: =J18/J63 -> 0.26308947
B67: Blinkit Mix % | C67: - | D67: =D36/D63 -> 0.11117241 | E67: =E36/E63 -> 0.18994552 | F67: =F36/F63 -> 0.25717532 | G67: =G36/G63 -> 0.27532773 | H67: =H36/H63 -> 0.30108813 | I67: =I36/I63 -> 0.3135628 | J67: =J36/J63 -> 0.31285511
B68: Hyperpure Mix % | C68: =C46/C63 -> 0.12830909 | D68: =D46/D63 -> 0.20772414 | E68: =E46/E63 -> 0.2618458 | F68: =F46/F63 -> 0.30608111 | G68: =G46/G63 -> 0.34612807 | H68: =H46/H63 -> 0.35827283 | I68: =I46/I63 -> 0.36550215 | J68: =J46/J63 -> 0.37227468
B69: TOTAL ADJ. EBITDA (₹ Cr) | C69: ='Historical Financials'!C42 -> -973 | D69: ='Historical Financials'!D42 -> -765 | E69: ='Historical Financials'!E42 -> 372 | F69: ='Historical Financials'!F42 -> 1079 | G69: =SUM(G42,G22,G56,G48) -> 2274.8515 | H69: =SUM(H42,H22,H56,H48) -> 3753.0491 | I69: =SUM(I42,I22,I56,I48) -> 6529.8646 | J69: =SUM(J42,J22,J56,J48) -> 9407.7513
B70: Adj EBITDA Margin % | C70: =C69/C63 -> -0.23205342 | D70: =D69/D63 -> -0.10551724 | E70: =E69/E63 -> 0.030708271 | F70: =F69/F63 -> 0.053302376 | G70: =G69/G63 -> 0.079425229 | H70: =H69/H63 -> 0.093540291 | I70: =I69/I63 -> 0.12298749 | J70: =J69/J63 -> 0.1443797

Sheet 3-Statement
B2: 3-STATEMENT MODEL - ETERNAL LIMITED | ₹ Crores
B3: Particulars | C3: FY22A | D3: FY23A | E3: FY24A | F3: FY25A | G3: FY26E | H3: FY27E | I3: FY28E | J3: FY29E
B5: INCOME STATEMENT (₹ Crores)
B6: REVENUE FROM OPERATIONS
B7: Total Revenue from Operations | C7: ='Historical Financials'!C12 -> 4193 | D7: ='Historical Financials'!D12 -> 7079 | E7: ='Historical Financials'!E12 -> 12114 | F7: ='Historical Financials'!F12 -> 20243 | G7: ='Revenue Model'!G63 -> 28641.422 | H7: ='Revenue Model'!H63 -> 40122.272 | I7: ='Revenue Model'!I63 -> 53093.729 | J7: ='Revenue Model'!J63 -> 65159.791
B8: - Food Delivery | C8: ='Historical Financials'!C7 -> 3415 | D8: ='Historical Financials'!D7 -> 4533 | E8: ='Historical Financials'!E7 -> 6361 | F8: ='Historical Financials'!F7 -> 8080 | G8: ='Revenue Model'!G18 -> 9804.4902 | H8: ='Revenue Model'!H18 -> 12039.002 | I8: ='Revenue Model'!I18 -> 14652.013 | J8: ='Revenue Model'!J18 -> 17142.855
B9: - Blinkit Quick Commerce | C9: - | D9: ='Historical Financials'!D8 -> 806 | E9: ='Historical Financials'!E8 -> 2301 | F9: ='Historical Financials'!F8 -> 5206 | G9: ='Revenue Model'!G36 -> 7885.7775 | H9: ='Revenue Model'!H36 -> 12080.34 | I9: ='Revenue Model'!I36 -> 16648.219 | J9: ='Revenue Model'!J36 -> 20385.574
B10: - Hyperpure B2B | C10: ='Historical Financials'!C9 -> 538 | D10: ='Historical Financials'!D9 -> 1506 | E10: ='Historical Financials'!E9 -> 3172 | F10: ='Historical Financials'!F9 -> 6196 | G10: ='Revenue Model'!G46 -> 9913.6 | H10: ='Revenue Model'!H46 -> 14374.72 | I10: ='Revenue Model'!I46 -> 19405.872 | J10: ='Revenue Model'!J46 -> 24257.34
B11: - District / Going Out | C11: ='Historical Financials'!C10 -> - | D11: ='Historical Financials'!D10 -> - | E11: ='Historical Financials'!E10 -> 258 | F11: ='Historical Financials'!F10 -> 737 | G11: ='Revenue Model'!G54 -> 1012.554 | H11: ='Revenue Model'!H54 -> 1603.2105 | I11: ='Revenue Model'!I54 -> 2362.626 | J11: ='Revenue Model'!J54 -> 3349.0224
B12: - Others | C12: ='Historical Financials'!C11 -> 240 | D12: ='Historical Financials'!D11 -> 234 | E12: ='Historical Financials'!E11 -> 22 | F12: ='Historical Financials'!F11 -> 24 | G12: ='Revenue Model'!G59 -> 25 | H12: ='Revenue Model'!H59 -> 25 | I12: ='Revenue Model'!I59 -> 25 | J12: ='Revenue Model'!J59 -> 25
B13: YoY Revenue Growth % | C13: - | D13: =D7/C7-1 -> 0.68829001 | E13: =E7/D7-1 -> 0.71125865 | F13: =F7/E7-1 -> 0.67104177 | G13: =G7/F7-1 -> 0.41488029 | H13: =H7/G7-1 -> 0.40084779 | I13: =I7/H7-1 -> 0.32329816 | J13: =J7/I7-1 -> 0.22725964
B14: Other Income (Treasury Returns) | C14: ='Historical Financials'!C15 -> 495 | D14: ='Historical Financials'!D15 -> 681 | E14: ='Historical Financials'!E15 -> 847 | F14: ='Historical Financials'!F15 -> 1077 | G14: =Assumptions!E138*0.07 -> 1085 | H14: =Assumptions!F138*0.07 -> 945 | I14: =Assumptions!G138*0.07 -> 840 | J14: =Assumptions!H138*0.07 -> 770
B15: TOTAL INCOME | C15: =C7+C14 -> 4688 | D15: =D7+D14 -> 7760 | E15: =E7+E14 -> 12961 | F15: =F7+F14 -> 21320 | G15: =G7+G14 -> 29726.422 | H15: =H7+H14 -> 41067.272 | I15: =I7+I14 -> 53933.729 | J15: =J7+J14 -> 65929.791
B17: COST STRUCTURE
B18: Purchases of Stock-in-Trade | C18: ='Historical Financials'!C19 -> 552 | D18: ='Historical Financials'!D19 -> 1438 | E18: ='Historical Financials'!E19 -> 2887 | F18: ='Historical Financials'!F19 -> 5653 | G18: =ROUND(('Revenue Model'!G36+'Revenue Model'!G46)*Assumptions!E161,0) -> 8828 | H18: =ROUND(('Revenue Model'!H36+'Revenue Model'!H46)*Assumptions!F161,0) -> 13122 | I18: =ROUND(('Revenue Model'!I36+'Revenue Model'!I46)*Assumptions!G161,0) -> 17919 | J18: =ROUND(('Revenue Model'!J36+'Revenue Model'!J46)*Assumptions!H161,0) -> 22143
B19: Changes in Inventories | C19: ='Historical Financials'!C20 -> -43 | D19: ='Historical Financials'!D20 -> -28 | E19: ='Historical Financials'!E20 -> -5 | F19: ='Historical Financials'!F20 -> -88 | G19: =-(G73-F73) -> -114 | H19: =-(H73-G73) -> -141 | I19: =-(I73-H73) -> -109 | J19: =-(J73-I73) -> -67
B20: Delivery Partner & Fulfilment Costs | C20: ='Historical Financials'!C21 -> 1814 | D20: ='Historical Financials'!D21 -> 2537 | E20: ='Historical Financials'!E21 -> 3915 | F20: ='Historical Financials'!F21 -> 5728 | G20: =ROUND(G7*Assumptions!E108,0) -> 7876 | H20: =ROUND(H7*Assumptions!F108,0) -> 10632 | I20: =ROUND(I7*Assumptions!G108,0) -> 13539 | J20: =ROUND(J7*Assumptions!H108,0) -> 15964
B21: Cash Employee Benefits | C21: ='Historical Financials'!C27 -> 755 | D21: ='Historical Financials'!D27 -> 959 | E21: ='Historical Financials'!E27 -> 1144 | F21: ='Historical Financials'!F27 -> 1760 | G21: =ROUND(G7*Assumptions!E162,0) -> 2091 | H21: =ROUND(H7*Assumptions!F162,0) -> 2528 | I21: =ROUND(I7*Assumptions!G162,0) -> 2920 | J21: =ROUND(J7*Assumptions!H162,0) -> 3323
B22: ESOP / Share-Based Compensation | C22: ='Historical Financials'!C28 -> 878 | D22: ='Historical Financials'!D28 -> 506 | E22: ='Historical Financials'!E28 -> 515 | F22: ='Historical Financials'!F28 -> 798 | G22: =Assumptions!E163 -> 900 | H22: =Assumptions!F163 -> 950 | I22: =Assumptions!G163 -> 900 | J22: =Assumptions!H163 -> 850
B23: Advertising & Marketing | C23: ='Historical Financials'!C32 -> 1633 | D23: ='Historical Financials'!D32 -> 1465 | E23: ='Historical Financials'!E32 -> 526 | F23: ='Historical Financials'!F32 -> 863 | G23: =ROUND(G7*Assumptions!E113,0) -> 1432 | H23: =ROUND(H7*Assumptions!F113,0) -> 1926 | I23: =ROUND(I7*Assumptions!G113,0) -> 2389 | J23: =ROUND(J7*Assumptions!H113,0) -> 2932
B24: Technology & Platform Costs | C24: ='Historical Financials'!C33 -> 289 | D24: ='Historical Financials'!D33 -> 387 | E24: ='Historical Financials'!E33 -> 485 | F24: ='Historical Financials'!F33 -> 644 | G24: =ROUND(G7*Assumptions!E118,0) -> 859 | H24: =ROUND(H7*Assumptions!F118,0) -> 1123 | I24: =ROUND(I7*Assumptions!G118,0) -> 1380 | J24: =ROUND(J7*Assumptions!H118,0) -> 1629
B25: Other Operating Expenses (residual) | C25: ='Historical Financials'!C40-C20-'Historical Financials'!C32-'Historical Financials'!C33 -> 119 | D25: ='Historical Financials'!D40-D20-'Historical Financials'!D32-'Historical Financials'!D33 -> 1041 | E25: ='Historical Financials'!E40-E20-'Historical Financials'!E32-'Historical Financials'!E33 -> 2605 | F25: ='Historical Financials'!F40-F20-'Historical Financials'!F32-'Historical Financials'!F33 -> 4248 | G25: =ROUND(G7*0.08,0) -> 2291 | H25: =ROUND(H7*0.08,0) -> 3210 | I25: =ROUND(I7*0.08,0) -> 4247 | J25: =ROUND(J7*0.08,0) -> 5213
B27: ADJUSTED EBITDA | C27: ='Historical Financials'!C42 -> -973 | D27: ='Historical Financials'!D42 -> -765 | E27: ='Historical Financials'!E42 -> 372 | F27: ='Historical Financials'!F42 -> 1079 | G27: ='Revenue Model'!G69 -> 2274.8515 | H27: ='Revenue Model'!H69 -> 3753.0491 | I27: ='Revenue Model'!I69 -> 6529.8646 | J27: ='Revenue Model'!J69 -> 9407.7513
B28: Adj EBITDA Margin % | C28: =C27/C7 -> -0.23205342 | D28: =D27/D7 -> -0.10806611 | E28: =E27/E7 -> 0.030708271 | F28: =F27/F7 -> 0.053302376 | G28: =G27/G7 -> 0.079425229 | H28: =H27/H7 -> 0.093540291 | I28: =I27/I7 -> 0.12298749 | J28: =J27/J7 -> 0.1443797
B29: Less: ESOP Expense | C29: =C22 -> 878 | D29: =D22 -> 506 | E29: =E22 -> 515 | F29: =F22 -> 798 | G29: =G22 -> 900 | H29: =H22 -> 950 | I29: =I22 -> 900 | J29: =J22 -> 850
B30: REPORTED EBITDA | C30: =C27-C29 -> -1851 | D30: =D27-D29 -> -1271 | E30: =E27-E29 -> -143 | F30: =F27-F29 -> 281 | G30: =G27-G29 -> 1374.8515 | H30: =H27-H29 -> 2803.0491 | I30: =I27-I29 -> 5629.8646 | J30: =J27-J29 -> 8557.7513
B32: DEPRECIATION & AMORTISATION
B33: Depreciation on PPE | C33: ='Historical Financials'!C54 -> 287 | D33: ='Historical Financials'!D54 -> 212 | E33: ='Historical Financials'!E54 -> 524 | F33: ='Historical Financials'!F54 -> 247 | G33: =Assumptions!E127 -> 380 | H33: =Assumptions!F127 -> 480 | I33: =Assumptions!G127 -> 560 | J33: =Assumptions!H127 -> 620
B34: Amortisation of Intangibles | C34: ='Historical Financials'!C55 -> 108 | D34: ='Historical Financials'!D55 -> 256 | E34: ='Historical Financials'!E55 -> 242 | F34: ='Historical Financials'!F55 -> 287 | G34: =Assumptions!E128 -> 250 | H34: =Assumptions!F128 -> 200 | I34: =Assumptions!G128 -> 160 | J34: =Assumptions!H128 -> 130
B35: Depreciation on ROU Assets | C35: ='Historical Financials'!C56 -> 151 | D35: ='Historical Financials'!D56 -> 109 | E35: ='Historical Financials'!E56 -> 159 | F35: ='Historical Financials'!F56 -> 329 | G35: =Assumptions!E129 -> 500 | H35: =Assumptions!F129 -> 700 | I35: =Assumptions!G129 -> 870 | J35: =Assumptions!H129 -> 990
B36: Total D&A | C36: =SUM(C33:C35) -> 546 | D36: =SUM(D33:D35) -> 577 | E36: =SUM(E33:E35) -> 925 | F36: =SUM(F33:F35) -> 863 | G36: =SUM(G33:G35) -> 1130 | H36: =SUM(H33:H35) -> 1380 | I36: =SUM(I33:I35) -> 1590 | J36: =SUM(J33:J35) -> 1740
B38: EBIT | C38: =C27-C36 -> -1519 | D38: =D27-D36 -> -1342 | E38: =E27-E36 -> -553 | F38: =F27-F36 -> 216 | G38: =G27-G36 -> 1144.8515 | H38: =H27-H36 -> 2373.0491 | I38: =I27-I36 -> 4939.8646 | J38: =J27-J36 -> 7667.7513
B39: EBIT Margin % | C39: =C38/C7 -> -0.36227045 | D39: =D38/D7 -> -0.1895748 | E39: =E38/E7 -> -0.045649662 | F39: =F38/F7 -> 0.010670355 | G39: =G38/G7 -> 0.03997188 | H39: =H38/H7 -> 0.05914543 | I39: =I38/I7 -> 0.093040453 | J39: =J38/J7 -> 0.11767612
B41: FINANCE COSTS
B42: Interest on Lease Liabilities (INDAS 116) | C42: ='Historical Financials'!C64 -> 9 | D42: ='Historical Financials'!D64 -> 41 | E42: ='Historical Financials'!E64 -> 67 | F42: ='Historical Financials'!F64 -> 147 | G42: =ROUND(Assumptions!E140*0.085,0) -> 264 | H42: =ROUND(Assumptions!F140*0.085,0) -> 357 | I42: =ROUND(Assumptions!G140*0.085,0) -> 417 | J42: =ROUND(Assumptions!H140*0.085,0) -> 442
B43: Interest on Borrowings | C43: ='Historical Financials'!C63 -> 15 | D43: ='Historical Financials'!D63 -> 24 | E43: ='Historical Financials'!E63 -> - | F43: ='Historical Financials'!F63 -> - | G43: =Assumptions!E168 -> 5 | H43: =Assumptions!F168 -> 5 | I43: =Assumptions!G168 -> 5 | J43: =Assumptions!H168 -> 5
B44: Exceptional Items | C44: ='Historical Financials'!C66 -> 297 | D44: ='Historical Financials'!D66 -> 0 | E44: ='Historical Financials'!E66 -> 0 | F44: ='Historical Financials'!F66 -> 0 | G44: =Assumptions!E169 -> 0 | H44: =Assumptions!F169 -> 0 | I44: =Assumptions!G169 -> 0 | J44: =Assumptions!H169 -> 0
B45: PROFIT BEFORE TAX (PBT) | C45: ='Historical Financials'!C68 -> -1221 | D45: ='Historical Financials'!D68 -> -1015 | E45: ='Historical Financials'!E68 -> 291 | F45: ='Historical Financials'!F68 -> 697 | G45: =G38-G42-G43+G14+G44 -> 1960.8515 | H45: =H38-H42-H43+H14+H44 -> 2956.0491 | I45: =I38-I42-I43+I14+I44 -> 5357.8646 | J45: =J38-J42-J43+J14+J44 -> 7990.7513
B46: PBT Margin % | C46: =C45/C7 -> -0.29119962 | D46: =D45/D7 -> -0.14338183 | E46: =E45/E7 -> 0.024021793 | F46: =F45/F7 -> 0.034431655 | G46: =G45/G7 -> 0.068462086 | H46: =H45/H7 -> 0.073676013 | I46: =I45/I7 -> 0.10091332 | J46: =J45/J7 -> 0.12263316
B48: TAX
B49: Current Tax | C49: ='Historical Financials'!C72 -> 0 | D49: ='Historical Financials'!D72 -> 0 | E49: ='Historical Financials'!E72 -> 200 | F49: ='Historical Financials'!F72 -> 267 | G49: =ROUND(MAX(0,G45)*Assumptions!E123,0) -> 431 | H49: =ROUND(MAX(0,H45)*Assumptions!F123,0) -> 650 | I49: =ROUND(MAX(0,I45)*Assumptions!G123,0) -> 1339 | J49: =ROUND(MAX(0,J45)*Assumptions!H123,0) -> 1998
B50: Deferred Tax (Credit) / Charge | C50: ='Historical Financials'!C73 -> -4 | D50: ='Historical Financials'!D73 -> -44 | E50: ='Historical Financials'!E73 -> -60 | F50: ='Historical Financials'!F73 -> -97 | G50: =Assumptions!E170 -> -64 | H50: =Assumptions!F170 -> -51 | I50: =Assumptions!G170 -> -46 | J50: =Assumptions!H170 -> -46
B51: Total Tax Expense | C51: - | D51: - | E51: =E49+E50 -> 140 | F51: =F49+F50 -> 170 | G51: =G49+G50 -> 367 | H51: =H49+H50 -> 599 | I51: =I49+I50 -> 1293 | J51: =J49+J50 -> 1952
B53: PROFIT AFTER TAX (PAT) | C53: ='Historical Financials'!C76 -> -1223 | D53: ='Historical Financials'!D76 -> -971 | E53: ='Historical Financials'!E76 -> 351 | F53: ='Historical Financials'!F76 -> 527 | G53: =G45-G51 -> 1593.8515 | H53: =H45-H51 -> 2357.0491 | I53: =I45-I51 -> 4064.8646 | J53: =J45-J51 -> 6038.7513
B54: PAT Margin % | C54: =C53/C7 -> -0.2916766 | D54: =D53/D7 -> -0.13716627 | E54: =E53/E7 -> 0.02897474 | F54: =F53/F7 -> 0.026033691 | G54: =G53/G7 -> 0.055648476 | H54: =H53/H7 -> 0.058746649 | I54: =I53/I7 -> 0.076560164 | J54: =J53/J7 -> 0.092676039
B55: Basic EPS (₹) | C55: ='Historical Financials'!C79 -> -1.6007853 | D55: ='Historical Financials'!D79 -> -1.1614833 | E55: ='Historical Financials'!E79 -> 0.40437788 | F55: ='Historical Financials'!F79 -> 0.58103638 | G55: =G53/Assumptions!E158 -> 1.6955867 | H55: =H53/Assumptions!F158 -> 2.4552594 | I55: =I53/Assumptions!G158 -> 4.1690919 | J55: =J53/Assumptions!H158 -> 6.130712
B56: CHECK: PAT matches AR? (0=OK) | C56: 0 | D56: 0 | E56: 0 | F56: 0
B59: BALANCE SHEET (₹ Crores)
B60: NON-CURRENT ASSETS
B61: Property, Plant & Equipment (Net) | C61: ='Historical Financials'!C85 -> 51 | D61: ='Historical Financials'!D85 -> 209 | E61: ='Historical Financials'!E85 -> 287 | F61: ='Historical Financials'!F85 -> 965 | G61: =F61+Assumptions!E137-Assumptions!E127-5 -> 1680 | H61: =G61+Assumptions!F137-Assumptions!F127-5 -> 2645 | I61: =H61+Assumptions!G137-Assumptions!G127-5 -> 3380 | J61: =I61+Assumptions!H137-Assumptions!H127-5 -> 3755
B62: Capital Work-in-Progress | C62: ='Historical Financials'!C86 -> 18 | D62: ='Historical Financials'!D86 -> 18 | E62: ='Historical Financials'!E86 -> 51 | F62: ='Historical Financials'!F86 -> 0 | G62: =Assumptions!E175 -> 60 | H62: =Assumptions!F175 -> 70 | I62: =Assumptions!G175 -> 65 | J62: =Assumptions!H175 -> 50
B63: Right-of-Use Assets (IND-AS 116) | C63: ='Historical Financials'!C87 -> 64 | D63: ='Historical Financials'!D87 -> 427 | E63: ='Historical Financials'!E87 -> 690 | F63: ='Historical Financials'!F87 -> 1918 | G63: =Assumptions!E139 -> 2900 | H63: =Assumptions!F139 -> 4000 | I63: =Assumptions!G139 -> 4800 | J63: =Assumptions!H139 -> 5200
B64: Goodwill | C64: ='Historical Financials'!C88 -> 1209 | D64: ='Historical Financials'!D88 -> 4717 | E64: ='Historical Financials'!E88 -> 4717 | F64: ='Historical Financials'!F88 -> 5737 | G64: =F64 -> 5737 | H64: =G64 -> 5737 | I64: =H64 -> 5737 | J64: =I64 -> 5737
B65: Other Intangible Assets | C65: ='Historical Financials'!C89 -> 63 | D65: ='Historical Financials'!D89 -> 991 | E65: ='Historical Financials'!E89 -> 754 | F65: ='Historical Financials'!F89 -> 912 | G65: =F65-Assumptions!E128 -> 662 | H65: =G65-Assumptions!F128 -> 462 | I65: =H65-Assumptions!G128 -> 302 | J65: =I65-Assumptions!H128 -> 172
B66: Non-Current Investments | C66: ='Historical Financials'!C90 -> 3086 | D66: ='Historical Financials'!D90 -> 2280 | E66: ='Historical Financials'!E90 -> 10365 | F66: ='Historical Financials'!F90 -> 10920 | G66: =G107-(G61+G62+G63+G64+G65+G67+G68+G69)-G81 -> 11414 | H66: =H107-(H61+H62+H63+H64+H65+H67+H68+H69)-H81 -> 12035 | I66: =I107-(I61+I62+I63+I64+I65+I67+I68+I69)-I81 -> 13361 | J66: =J107-(J61+J62+J63+J64+J65+J67+J68+J69)-J81 -> 15114
B67: Other Non-Current Financial Assets | C67: ='Historical Financials'!C91 -> 5219 | D67: ='Historical Financials'!D91 -> 1894 | E67: ='Historical Financials'!E91 -> 747 | F67: ='Historical Financials'!F91 -> 2744 | G67: =Assumptions!E176 -> 3200 | H67: =Assumptions!F176 -> 3900 | I67: =Assumptions!G176 -> 4500 | J67: =Assumptions!H176 -> 5000
B68: Deferred Tax Assets | C68: ='Historical Financials'!C92 -> 67 | D68: ='Historical Financials'!D92 -> 116 | E68: ='Historical Financials'!E92 -> 221 | F68: ='Historical Financials'!F92 -> 129 | G68: =Assumptions!E177 -> 193 | H68: =Assumptions!F177 -> 244 | I68: =Assumptions!G177 -> 290 | J68: =Assumptions!H177 -> 336
B69: Other Non-Current Assets | C69: ='Historical Financials'!C93 -> 5 | D69: ='Historical Financials'!D93 -> 118 | E69: ='Historical Financials'!E93 -> 66 | F69: ='Historical Financials'!F93 -> 597 | G69: =Assumptions!E185 -> 140 | H69: =Assumptions!F185 -> 165 | I69: =Assumptions!G185 -> 185 | J69: =Assumptions!H185 -> 205
B70: TOTAL NON-CURRENT ASSETS | C70: ='Historical Financials'!C94 -> 9782 | D70: ='Historical Financials'!D94 -> 10770 | E70: ='Historical Financials'!E94 -> 17898 | F70: ='Historical Financials'!F94 -> 23922 | G70: =SUM(G61:G69) -> 25986 | H70: =SUM(H61:H69) -> 29258 | I70: =SUM(I61:I69) -> 32620 | J70: =SUM(J61:J69) -> 35569
B72: CURRENT ASSETS
B73: Inventories | C73: ='Historical Financials'!C97 -> 40 | D73: ='Historical Financials'!D97 -> 83 | E73: ='Historical Financials'!E97 -> 88 | F73: ='Historical Financials'!F97 -> 176 | G73: =ROUND(G18*Assumptions!E134/365,0) -> 290 | H73: =ROUND(H18*Assumptions!F134/365,0) -> 431 | I73: =ROUND(I18*Assumptions!G134/365,0) -> 540 | J73: =ROUND(J18*Assumptions!H134/365,0) -> 607
B74: Current Investment | C74: ='Historical Financials'!C98 -> 1632 | D74: ='Historical Financials'!D98 -> 4485 | E74: ='Historical Financials'!E98 -> 1280 | F74: ='Historical Financials'!F98 -> 2272 | G74: =Assumptions!E179 -> 2100 | H74: =Assumptions!F179 -> 1800 | I74: =Assumptions!G179 -> 1600 | J74: =Assumptions!H179 -> 1500
B75: Trade Receivables | C75: ='Historical Financials'!C99 -> 16 | D75: ='Historical Financials'!D99 -> 45 | E75: ='Historical Financials'!E99 -> 779 | F75: ='Historical Financials'!F99 -> 1946 | G75: =ROUND(G7*Assumptions!E135/365,0) -> 2982 | H75: =ROUND(H7*Assumptions!F135/365,0) -> 4177 | I75: =ROUND(I7*Assumptions!G135/365,0) -> 5237 | J75: =ROUND(J7*Assumptions!H135/365,0) -> 6248
B76: Cash & Cash Equivalents | C76: ='Historical Financials'!C100 -> 392 | D76: ='Historical Financials'!D100 -> 218 | E76: ='Historical Financials'!E100 -> 309 | F76: ='Historical Financials'!F100 -> 666 | G76: =G180 -> 28.851476 | H76: =H180 -> 371.90053 | I76: =I180 -> 1820.7652 | J76: =J180 -> 5090.5165
B77: Bank Balances (FDs > 3 months) | C77: ='Historical Financials'!C101 -> 1183 | D77: ='Historical Financials'!D101 -> 799 | E77: ='Historical Financials'!E101 -> 422 | F77: ='Historical Financials'!F101 -> 2948 | G77: =Assumptions!E180 -> 3000 | H77: =Assumptions!F180 -> 2500 | I77: =Assumptions!G180 -> 2200 | J77: =Assumptions!H180 -> 2000
B78: Loans (Current) | C78: ='Historical Financials'!C102 -> 375 | D78: ='Historical Financials'!D102 -> 0 | E78: ='Historical Financials'!E102 -> 0 | F78: ='Historical Financials'!F102 -> 0 | G78: 0 | H78: 0 | I78: 0 | J78: 0
B79: Other Current Financial Assets | C79: ='Historical Financials'!C103 -> 3667 | D79: ='Historical Financials'!D103 -> 4830 | E79: ='Historical Financials'!E103 -> 2324 | F79: ='Historical Financials'!F103 -> 2769 | G79: =Assumptions!E181 -> 3200 | H79: =Assumptions!F181 -> 4000 | I79: =Assumptions!G181 -> 4800 | J79: =Assumptions!H181 -> 5500
B80: Other Current Assets | C80: 96 | D80: 372 | E80: 241 | F80: 924 | G80: =Assumptions!E182 -> 1100 | H80: =Assumptions!F182 -> 1400 | I80: =Assumptions!G182 -> 1700 | J80: =Assumptions!H182 -> 2000
B81: TOTAL CURRENT ASSETS | C81: ='Historical Financials'!C105 -> 7545 | D81: ='Historical Financials'!D105 -> 10832 | E81: ='Historical Financials'!E105 -> 5458 | F81: ='Historical Financials'!F105 -> 11701 | G81: =SUM(G73:G80) -> 12700.851 | H81: =SUM(H73:H80) -> 14679.901 | I81: =SUM(I73:I80) -> 17897.765 | J81: =SUM(J73:J80) -> 22945.517
B83: TOTAL ASSETS | C83: ='Historical Financials'!C107 -> 17327 | D83: ='Historical Financials'!D107 -> 21602 | E83: ='Historical Financials'!E107 -> 23356 | F83: ='Historical Financials'!F107 -> 35623 | G83: =G70+G81 -> 38686.851 | H83: =H70+H81 -> 43937.901 | I83: =I70+I81 -> 50517.765 | J83: =J70+J81 -> 58514.517
B85: EQUITY
B86: Share Capital | C86: ='Historical Financials'!C110 -> 764 | D86: ='Historical Financials'!D110 -> 836 | E86: ='Historical Financials'!E110 -> 868 | F86: ='Historical Financials'!F110 -> 907 | G86: =Assumptions!E183 -> 940 | H86: =Assumptions!F183 -> 957 | I86: =Assumptions!G183 -> 967 | J86: =Assumptions!H183 -> 977
B87: Other Equity | C87: ='Historical Financials'!C111 -> 15742 | D87: ='Historical Financials'!D111 -> 18623 | E87: ='Historical Financials'!E111 -> 19545 | F87: ='Historical Financials'!F111 -> 29410 | G87: =F87+G53+G22 -> 31903.851 | H87: =G87+H53+H22 -> 35210.901 | I87: =H87+I53+I22 -> 40175.765 | J87: =I87+J53+J22 -> 47064.517
B88: Non-Controlling Interests | C88: ='Historical Financials'!C112 -> -7 | D88: ='Historical Financials'!D112 -> -7 | E88: ='Historical Financials'!E112 -> -7 | F88: ='Historical Financials'!F112 -> -7 | G88: =F88 -> -7 | H88: =G88 -> -7 | I88: =H88 -> -7 | J88: =I88 -> -7
B89: TOTAL EQUITY | C89: ='Historical Financials'!C113 -> 16499 | D89: ='Historical Financials'!D113 -> 19452 | E89: ='Historical Financials'!E113 -> 20406 | F89: ='Historical Financials'!F113 -> 30310 | G89: =SUM(G86:G88) -> 32836.851 | H89: =SUM(H86:H88) -> 36160.901 | I89: =SUM(I86:I88) -> 41135.765 | J89: =SUM(J86:J88) -> 48034.517
B91: NON-CURRENT LIABILITIES
B92: Lease Liabilities | C92: ='Historical Financials'!C116 -> 52 | D92: ='Historical Financials'!D116 -> 351 | E92: ='Historical Financials'!E116 -> 585 | F92: ='Historical Financials'!F116 -> 1654 | G92: =ROUND(Assumptions!E140*0.75,0) -> 2325 | H92: =ROUND(Assumptions!F140*0.75,0) -> 3150 | I92: =ROUND(Assumptions!G140*0.75,0) -> 3675 | J92: =ROUND(Assumptions!H140*0.75,0) -> 3900
B93: Borrowing | C93: ='Historical Financials'!C117 -> 0 | D93: ='Historical Financials'!D117 -> 0 | E93: ='Historical Financials'!E117 -> 6 | F93: ='Historical Financials'!F117 -> 0 | G93: 0 | H93: 0 | I93: 0 | J93: 0
B94: Deferred Tax Liabilities | C94: ='Historical Financials'!C118 -> 0 | D94: ='Historical Financials'!D118 -> 250 | E94: ='Historical Financials'!E118 -> 188 | F94: ='Historical Financials'!F118 -> 212 | G94: =Assumptions!E184 -> 178 | H94: =Assumptions!F184 -> 148 | I94: =Assumptions!G184 -> 118 | J94: =Assumptions!H184 -> 88
B95: Non-Current Provisions | C95: ='Historical Financials'!C119 -> 65 | D95: ='Historical Financials'!D119 -> 94 | E95: ='Historical Financials'!E119 -> 88 | F95: ='Historical Financials'!F119 -> 120 | G95: =Assumptions!E185 -> 140 | H95: =Assumptions!F185 -> 165 | I95: =Assumptions!G185 -> 185 | J95: =Assumptions!H185 -> 205
B96: Other Non-Current Financial Liabilities | C96: ='Historical Financials'!C120 -> 0 | D96: ='Historical Financials'!D120 -> 10 | E96: ='Historical Financials'!E120 -> - | F96: ='Historical Financials'!F120 -> 1 | G96: =Assumptions!E186 -> 2 | H96: =Assumptions!F186 -> 2 | I96: =Assumptions!G186 -> 2 | J96: =Assumptions!H186 -> 2
B97: TOTAL NON-CURRENT LIABILITIES | C97: ='Historical Financials'!C121 -> 117 | D97: ='Historical Financials'!D121 -> 705 | E97: ='Historical Financials'!E121 -> 867 | F97: ='Historical Financials'!F121 -> 1987 | G97: =SUM(G92:G96) -> 2645 | H97: =SUM(H92:H96) -> 3465 | I97: =SUM(I92:I96) -> 3980 | J97: =SUM(J92:J96) -> 4195
B99: CURRENT LIABILITIES
B100: Lease Liabilities | C100: ='Historical Financials'!C124 -> 19 | D100: ='Historical Financials'!D124 -> 115 | E100: ='Historical Financials'!E124 -> 161 | F100: 391 | G100: =ROUND(Assumptions!E140*0.25,0) -> 775 | H100: =ROUND(Assumptions!F140*0.25,0) -> 1050 | I100: =ROUND(Assumptions!G140*0.25,0) -> 1225 | J100: =ROUND(Assumptions!H140*0.25,0) -> 1300
B101: Trade Payables – MSME | C101: ='Historical Financials'!C125 -> 7 | D101: ='Historical Financials'!D125 -> 9 | E101: ='Historical Financials'!E125 -> 15 | F101: 75 | G101: =Assumptions!E187 -> 150 | H101: =Assumptions!F187 -> 200 | I101: =Assumptions!G187 -> 250 | J101: =Assumptions!H187 -> 300
B102: Trade Payables – Others | C102: ='Historical Financials'!C126 -> 422 | D102: ='Historical Financials'!D126 -> 671 | E102: ='Historical Financials'!E126 -> 871 | F102: 1461 | G102: =ROUND(G7*Assumptions!E136/365*0.9,0) -> 530 | H102: =ROUND(H7*Assumptions!F136/365*0.9,0) -> 742 | I102: =ROUND(I7*Assumptions!G136/365*0.9,0) -> 1047 | J102: =ROUND(J7*Assumptions!H136/365*0.9,0) -> 1285
B103: Other Current Financial Liabilities | C103: ='Historical Financials'!C128 -> 175 | D103: ='Historical Financials'!D128 -> 223 | E103: ='Historical Financials'!E128 -> 449 | F103: 486 | G103: =Assumptions!E188 -> 1200 | H103: =Assumptions!F188 -> 1600 | I103: =Assumptions!G188 -> 2000 | J103: =Assumptions!H188 -> 2400
B104: Other Current Liabilities | C104: ='Historical Financials'!C129 -> 88 | D104: ='Historical Financials'!D129 -> 302 | E104: ='Historical Financials'!E129 -> 392 | F104: ='Historical Financials'!F129 -> 486 | G104: =Assumptions!E189 -> 550 | H104: =Assumptions!F189 -> 720 | I104: =Assumptions!G189 -> 880 | J104: =Assumptions!H189 -> 1000
B105: TOTAL CURRENT LIABILITIES | C105: ='Historical Financials'!C130 -> 711 | D105: ='Historical Financials'!D130 -> 1445 | E105: ='Historical Financials'!E130 -> 2083 | F105: ='Historical Financials'!F130 -> 3326 | G105: =SUM(G100:G104) -> 3205 | H105: =SUM(H100:H104) -> 4312 | I105: =SUM(I100:I104) -> 5402 | J105: =SUM(J100:J104) -> 6285
B106: TOTAL LIABILITIES | C106: ='Historical Financials'!C130+'Historical Financials'!C121 -> 828 | D106: ='Historical Financials'!D130+'Historical Financials'!D121 -> 2150 | E106: ='Historical Financials'!E130+'Historical Financials'!E121 -> 2950 | F106: ='Historical Financials'!F130+'Historical Financials'!F121 -> 5313 | G106: =SUM(G105,G97) -> 5850 | H106: =SUM(H105,H97) -> 7777 | I106: =SUM(I105,I97) -> 9382 | J106: =SUM(J105,J97) -> 10480
B107: TOTAL EQUITY & LIABILITIES | C107: ='Historical Financials'!C132 -> 17327 | D107: ='Historical Financials'!D132 -> 21602 | E107: ='Historical Financials'!E132 -> 23356 | F107: ='Historical Financials'!F132 -> 35623 | G107: =SUM(G106,G89) -> 38686.851 | H107: =SUM(H106,H89) -> 43937.901 | I107: =SUM(I106,I89) -> 50517.765 | J107: =SUM(J106,J89) -> 58514.517
B109: ✅ BALANCE SHEET CHECK | C109: =C107-C83 -> 0 | D109: =D107-D83 -> 0 | E109: =E107-E83 -> 0 | F109: =F107-F83 -> 0 | G109: =G107-G83 -> 0 | H109: =H107-H83 -> 0 | I109: =I107-I83 -> 0 | J109: =J107-J83 -> 0
B111: CASH FLOW STATEMENT (₹ Crores)
B112: A. OPERATING ACTIVITIES
B113: Profit After Tax | C113: =C53 -> -1223 | D113: =D53 -> -971 | E113: =E53 -> 351 | F113: =F53 -> 527 | G113: =G53 -> 1593.8515 | H113: =H53 -> 2357.0491 | I113: =I53 -> 4064.8646 | J113: =J53 -> 6038.7513
B114: Non-cash adjustments
B115: Liabilities Written Back | C115: ='Historical Financials'!C140 -> -9 | D115: ='Historical Financials'!D140 -> -28 | E115: ='Historical Financials'!E140 -> -9 | F115: ='Historical Financials'!F140 -> -10 | G115: =F115 -> -10 | H115: =G115 -> -10 | I115: =H115 -> -10 | J115: =I115 -> -10
B116: Depreciation on PPE + ROU Assets | C116: =C33+C35 -> 438 | D116: =D33+D35 -> 321 | E116: =E33+E35 -> 683 | F116: =F33+F35 -> 576 | G116: =G33+G35 -> 880 | H116: =H33+H35 -> 1180 | I116: =I33+I35 -> 1430 | J116: =J33+J35 -> 1610
B117: Amortisation of Intangible Assets | C117: =C34 -> 108 | D117: =D34 -> 256 | E117: =E34 -> 242 | F117: =F34 -> 287 | G117: =G34 -> 250 | H117: =H34 -> 200 | I117: =I34 -> 160 | J117: =J34 -> 130
B118: Provision for Doubtful Debts | C118: ='Historical Financials'!C143 -> 21 | D118: ='Historical Financials'!D143 -> 30 | E118: ='Historical Financials'!E143 -> 68 | F118: ='Historical Financials'!F143 -> 71 | G118: =Assumptions!E195 -> 75 | H118: =Assumptions!F195 -> 85 | I118: =Assumptions!G195 -> 90 | J118: =Assumptions!H195 -> 95
...

Sheet DCF + Sensitivity
B2: DCF VALUATION - ETERNAL LIMITED | Two-Stage DCF | Operating FCFF (Treasury Excluded)
B3: CMP: ₹249 per share | Market Cap: ₹2,40,303 Cr | 52-Week Range: ₹212–₹368 | April 2026
B4: SECTION 1 - WACC CALCULATION
B6: Metric | C6: Bear | D6: Base | E6: Bull | F6: Source / Notes
B7: Risk-Free Rate (10Y G-Sec) | C7: =Assumptions!$F$145 -> 0.068 | D7: =Assumptions!$F$145 -> 0.068 | E7: =Assumptions!$F$145 -> 0.068 | F7: RBI 10Y G-Sec, early 2026 - Assumptions!D149
B8: Equity Risk Premium (ERP) | C8: =Assumptions!$F$146 -> 0.055 | D8: =Assumptions!$F$146 -> 0.055 | E8: =Assumptions!$F$146 -> 0.055 | F8: Damodaran: US ERP 4.5% + India CRP 2.0% - Assumptions!D150
B9: Beta (Relevered) | C9: 1.2 | D9: =Assumptions!F147 -> 0.95 | E9: 0.75 | F9: Comps: DoorDash 1.30, Del.Hero 1.45, Sea 1.60 - Assumptions!D151
B10: Cost of Equity | C10: =C7+C9*C8 -> 0.134 | D10: =D7+D9*D8 -> 0.12025 | E10: =E7+E9*E8 -> 0.10925 | F10: CAPM: Rf+β×ERP = 6.8%+(1.3/1.1/0.95)×5.5%
B11: MODEL WACC | C11: =Assumptions!F150 -> 0.1395 | D11: =Assumptions!F149 -> 0.13125 | E11: =Assumptions!F151 -> 0.1175 | F11: Eternal is DEBT-FREE → WACC = Ke - Assumptions!D153/154/155
B12: Terminal Growth Rate | C12: =Assumptions!F153 -> 0.04 | D12: =Assumptions!F152 -> 0.045 | E12: =Assumptions!F154 -> 0.055 | F12: India nominal GDP 8-10%; conservative TGR
B14: SECTION 2 - STAGE 1 FCFF (FY26E–FY29E, from 3-Statement Tab FCFF Schedule)
B16: Metric | C16: FY26E | D16: FY27E | E16: FY28E | F16: FY29E | G16: Notes / Source
B17: EBIT (₹ Cr) | C17: ='3-Statement'!G38 -> 1144.8515 | D17: ='3-Statement'!H38 -> 2373.0491 | E17: ='3-Statement'!I38 -> 4939.8646 | F17: ='3-Statement'!J38 -> 7667.7513 | G17: From 3-Statement IS EBIT row
B18: Tax Rate | C18: =Assumptions!E123 -> 0.22 | D18: =Assumptions!F123 -> 0.22 | E18: =Assumptions!G123 -> 0.25 | F18: =Assumptions!H123 -> 0.25 | G18: From Assumptions tab row 127
B19: NOPAT | C19: =ROUND(C17*(1-C18),0) -> 893 | D19: =ROUND(D17*(1-D18),0) -> 1851 | E19: =ROUND(E17*(1-E18),0) -> 3705 | F19: =ROUND(F17*(1-F18),0) -> 5751
B20: Add: Total D&A (₹ Cr) | C20: ='3-Statement'!G36 -> 1130 | D20: ='3-Statement'!H36 -> 1380 | E20: ='3-Statement'!I36 -> 1590 | F20: ='3-Statement'!J36 -> 1740 | G20: From Assumptions tab rows 131+132+133
B21: Less: Total Capex (₹ Cr) | C21: =-(Assumptions!E137) -> -1100 | D21: =-(Assumptions!F137) -> -1450 | E21: =-(Assumptions!G137) -> -1300 | F21: =-(Assumptions!H137) -> -1000 | G21: From Assumptions tab row 141 - Blinkit 80% of total
B22: Less: Change in NWC (₹ Cr) | C22: =(30219*18/365)-(20243*18/365) -> 491.96712 | D22: =(42538*18/365)-(30219*18/365) -> 607.51233 | E22: =(56423*18/365)-(42538*18/365) -> 684.73973 | F22: =-(('3-Statement'!J7-'3-Statement'!I7)*18/365) -> -595.03866 | G22: Revenue×18days/365 change; Q3FY26 concall: Akshant "NWC ≤18 days target
B23: FCFF Stage 1 (₹ Cr) | C23: =SUM(C19:C22) -> 1414.9671 | D23: =SUM(D19:D22) -> 2388.5123 | E23: =SUM(E19:E22) -> 4679.7397 | F23: =SUM(F19:F22) -> 5895.9613
B25: SECTION 3 - STAGE 2 TRANSITION (FY30E–FY34E, Indicative Extrapolation)
B26: Metric | C26: FY30E | D26: FY31E | E26: FY32E | F26: FY33E | G26: FY34E | H26: FY35E | I26: FY36E | J26: Notes/Source
B27: Revenue Growth % | C27: 0.2 | D27: 0.18 | E27: 0.15 | F27: 0.13 | G27: 0.12 | H27: 0.1 | I27: 0.09 | J27: Tapering from 22.7% FY29 toward 12% steady state
B28: Revenue (₹ Cr) | C28: ='3-Statement'!J7*(1+C27) -> 78191.749 | D28: =C28*(1+D27) -> 92266.264 | E28: =D28*(1+E27) -> 106106.2 | F28: =E28*(1+F27) -> 119900.01 | G28: =F28*(1+G27) -> 134288.01 | H28: =G28*(1+H27) -> 147716.81 | I28: =H28*(1+I27) -> 161011.33 | J28: FY29E (₹69,238) × growth chain
B29: EBIT Margin % | C29: 0.15 | D29: 0.17 | E29: 0.19 | F29: 0.2 | G29: 0.21 | H29: 0.22 | I29: 0.22 | J29: DoorDash FY25 EBITDA 15%+; Eternal 22% EBIT by FY36 justified by Food+Blinkit maturity
B30: NOPAT (₹ Cr) | C30: =C28*C29*0.75 -> 8796.5718 | D30: =D28*D29*0.75 -> 11763.949 | E30: =E28*E29*0.75 -> 15120.134 | F30: =F28*F29*0.75 -> 17985.001 | G30: =G28*G29*0.75 -> 21150.362 | H30: =H28*H29*0.75 -> 24373.274 | I30: =I28*I29*0.75 -> 26566.869 | J30: Rev × EBIT% × (1−25%); 25% tax rate
B31: D&A (₹ Cr) | C31: =ROUND(C28*0.025,0) -> 1955 | D31: =ROUND(D28*0.023,0) -> 2122 | E31: =ROUND(E28*0.022,0) -> 2334 | F31: =ROUND(F28*0.021,0) -> 2518 | G31: =ROUND(G28*0.02,0) -> 2686 | H31: 2982 | I31: 3080 | J31: 2.5% tapering to 2.0% of revenue
B32: Capex (₹ Cr) | C32: =-ROUND(C28*0.012,0) -> -938 | D32: =-ROUND(D28*0.01,0) -> -923 | E32: =-ROUND(E28*0.01,0) -> -1061 | F32: =-ROUND(F28*0.01,0) -> -1199 | G32: =-ROUND(G28*0.01,0) -> -1343 | H32: =-ROUND(H28*0.015,0) -> -2216 | I32: =-ROUND(I28*0.015,0) -> -2415 | J32: 1.2% tapering to 1.0% - maintenance capex
B33: Change in NWC (₹ Cr) | C33: -300 | D33: -250 | E33: -200 | F33: -150 | G33: -100 | H33: -80 | I33: -60 | J33: Declining as growth slows
B34: FCFF Stage 2 (₹ Cr) | C34: =SUM(C30,C31)+C32+C33 -> 9513.5718 | D34: =SUM(D30,D31)+D32+D33 -> 12712.949 | E34: =SUM(E30,E31)+E32+E33 -> 16193.134 | F34: =SUM(F30,F31)+F32+F33 -> 19154.001 | G34: =SUM(G30,G31)+G32+G33 -> 22393.362 | H34: =SUM(H30,H31)+H32+H33 -> 25059.274 | I34: =SUM(I30,I31)+I32+I33 -> 27171.869 | J34: NOPAT + DA - Capex - NWC
B36: SECTION 4 - DCF VALUATION SUMMARY (Bear | Base | Bull)
B38: Metric | D38: Bear | E38: Base | F38: Bull
B39: WACC Used | D39: =C11 -> 0.1395 | E39: =D11 -> 0.13125 | F39: =E11 -> 0.1175
B40: TGR Used | D40: =C12 -> 0.04 | E40: =D12 -> 0.045 | F40: =E12 -> 0.055
B41: PV of Stage 1 FCFFs | D41: =$C$23/(1+D39)^0.5+$D$23/(1+D39)^1.5+$E$23/(1+D39)^2.5+$F$23/(1+D39)^3.5 -> 10398.372 | E41: =$C$23/(1+E39)^0.5+$D$23/(1+E39)^1.5+$E$23/(1+E39)^2.5+$F$23/(1+E39)^3.5 -> 10582.765 | F41: =$C$23/(1+F39)^0.5+$D$23/(1+F39)^1.5+$E$23/(1+F39)^2.5+$F$23/(1+F39)^3.5 -> 10901.865
B42: PV of Stage 2 FCFFs | D42: =$C$34/(1+D39)^4.5+$D$34/(1+D39)^5.5+$E$34/(1+D39)^6.5+$F$34/(1+D39)^7.5+$G$34/(1+D39)^8.5+$H$34/(1+D39)^9.5+$I$34/(1+D39)^10.5 -> 47130.704 | E42: =$C$34/(1+E39)^4.5+$D$34/(1+E39)^5.5+$E$34/(1+E39)^6.5+$F$34/(1+E39)^7.5+$G$34/(1+E39)^8.5+$H$34/(1+E39)^9.5+$I$34/(1+E39)^10.5 -> 49832.07 | F42: =$C$34/(1+F39)^4.5+$D$34/(1+F39)^5.5+$E$34/(1+F39)^6.5+$F$34/(1+F39)^7.5+$G$34/(1+F39)^8.5+$H$34/(1+F39)^9.5+$I$34/(1+F39)^10.5 -> 54756.948
B43: Terminal Value | D43: =$I$34*(1+D40)/(D39-D40) -> 284007.47 | E43: =$I$34*(1+E40)/(E39-E40) -> 329212.79 | F43: =$I$34*(1+F40)/(F39-F40) -> 458661.14
B44: PV of Terminal Value | D44: =D43/(1+D39)^11 -> 67526.174 | E44: =E43/(1+E39)^11 -> 84787.568 | F44: =F43/(1+F39)^11 -> 135135.39
B45: Terminal Value as % of Total EV | D45: =D44/(D41+D42+D44) -> 0.53997072 | E45: =E44/(E41+E42+E44) -> 0.58392675 | F45: =F44/(F41+F42+F44) -> 0.67300444
B46: ENTERPRISE VALUE (₹ Cr) | D46: =D41+D42+D44 -> 125055.25 | E46: =E41+E42+E44 -> 145202.4 | F46: =F41+F42+F44 -> 200794.2
B48: EV TO EQUITY BRIDGE
B49: Enterprise Value (₹ Cr) | D49: =D46 -> 125055.25 | E49: =E46 -> 145202.4 | F49: =F46 -> 200794.2
B50: Add: Liquid Assets - FY25A | D50: ='3-Statement'!$F$76+'3-Statement'!$F$74+'3-Statement'!$F$77+'3-Statement'!$F$66 -> 16806 | E50: ='3-Statement'!$F$76+'3-Statement'!$F$74+'3-Statement'!$F$77+'3-Statement'!$F$66 -> 16806 | F50: ='3-Statement'!$F$76+'3-Statement'!$F$74+'3-Statement'!$F$77+'3-Statement'!$F$66 -> 16806
B51: Less: Total Lease Liabilities - FY25A | D51: =-('3-Statement'!$F$92+'3-Statement'!$F$100) -> -2045 | E51: =-('3-Statement'!$F$92+'3-Statement'!$F$100) -> -2045 | F51: =-('3-Statement'!$F$92+'3-Statement'!$F$100) -> -2045
B52: Less: Financial Debt | D52: 0 | E52: 0 | F52: 0
B53: EQUITY VALUE (₹ Cr) | D53: =SUM(D49:D52) -> 139816.25 | E53: =SUM(E49:E52) -> 159963.4 | F53: =SUM(F49:F52) -> 215555.2
B54: Diluted Shares Outstanding - FY26E (Cr) | D54: =Assumptions!$E$158 -> 940 | E54: =Assumptions!$E$158 -> 940 | F54: =Assumptions!$E$158 -> 940
B56: INTRINSIC VALUE PER SHARE (₹) | C56: =D53/D54 -> 148.74069 | D56: =E53/E54 -> 170.17383 | E56: =F53/F54 -> 229.31405
B57: CMP - April 16, 2026 (₹) | C57: 249 | D57: 249 | E57: 249
B58: Upside / (Downside) vs CMP | C58: =C56/C57-1 -> -0.40264783 | D58: =D56/D57-1 -> -0.31657095 | E58: =E56/E57-1 -> -0.079060055
B59: Implied EV/Adj.EBITDA FY26E | C59: =D46/'3-Statement'!$G$27 -> 54.972929 | D59: =E46/'3-Statement'!$G$27 -> 63.829399 | E59: =F46/'3-Statement'!$G$27 -> 88.266951
B60: Implied EV/Revenue FY26E | C60: =D46/'3-Statement'!$G$7 -> 4.3662375 | D60: =E46/'3-Statement'!$G$7 -> 5.0696647 | E60: =F46/'3-Statement'!$G$7 -> 7.0106228
B62: SECTION 5 - SENSITIVITY: Price Per Share vs WACC × TGR
B64: ← TGR / WACC ↓ | C64: 0.04 | D64: 0.045 | E64: 0.05 | F64: 0.055 | G64: 0.06 | H64: 0.065 | I64: 0.07
B65: 0.11 | C65: =ROUND( ($C$23/(1+$B65)^0.5 + $D$23/(1+$B65)^1.5 + $E$23/(1+$B65)^2.5 + $F$23/(1+$B65)^3.5 +$C$34/(1+$B65)^4.5 + $D$34/(1+$B65)^5.5 + $E$34/(1+$B65)^6.5 + $F$34/(1+$B65)^7.5 +$G$34/(1+$B65)^8.5 + $H$34/(1+$B65)^9.5 + $I$34/(1+$B65)^10.5 +$I$34*(1+C$64)/($B65-C$64)/(1+$B65)^11 +Assumptions!$D$138-Assumptions!$D$140) /Assumptions!$E$158,0) -> 225 | D65: =ROUND( ($C$23/(1+$B65)^0.5 + $D$23/(1+$B65)^1.5 + $E$23/(1+$B65)^2.5 + $F$23/(1+$B65)^3.5 +$C$34/(1+$B65)^4.5 + $D$34/(1+$B65)^5.5 + $E$34/(1+$B65)^6.5 + $F$34/(1+$B65)^7.5 +$G$34/(1+$B65)^8.5 + $H$34/(1+$B65)^9.5 + $I$34/(1+$B65)^10.5 +$I$34*(1+D$64)/($B65-D$64)/(1+$B65)^11 +Assumptions!$D$138-Assumptions!$D$140) /Assumptions!$E$158,0) -> 236 | E65: =ROUND( ($C$23/(1+$B65)^0.5 + $D$23/(1+$B65)^1.5 + $E$23/(1+$B65)^2.5 + $F$23/(1+$B65)^3.5 +$C$34/(1+$B65)^4.5 + $D$34/(1+$B65)^5.5 + $E$34/(1+$B65)^6.5 + $F$34/(1+$B65)^7.5 +$G$34/(1+$B65)^8.5 + $H$34/(1+$B65)^9.5 + $I$34/(1+$B65)^10.5 +$I$34*(1+E$64)/($B65-E$64)/(1+$B65)^11 +Assumptions!$D$138-Assumptions!$D$140) /Assumptions!$E$158,0) -> 249 | F65: =ROUND( ($C$23/(1+$B65)^0.5 + $D$23/(1+$B65)^1.5 + $E$23/(1+$B65)^2.5 + $F$23/(1+$B65)^3.5 +$C$34/(1+$B65)^4.5 + $D$34/(1+$B65)^5.5 + $E$34/(1+$B65)^6.5 + $F$34/(1+$B65)^7.5 +$G$34/(1+$B65)^8.5 + $H$34/(1+$B65)^9.5 + $I$34/(1+$B65)^10.5 +$I$34*(1+F$64)/($B65-F$64)/(1+$B65)^11 +Assumptions!$D$138-Assumptions!$D$140) /Assumptions!$E$158,0) -> 265 | G65: =ROUND( ($C$23/(1+$B65)^0.5 + $D$23/(1+$B65)^1.5 + $E$23/(1+$B65)^2.5 + $F$23/(1+$B65)^3.5 +$C$34/(1+$B65)^4.5 + $D$34/(1+$B65)^5.5 + $E$34/(1+$B65)^6.5 + $F$34/(1+$B65)^7.5 +$G$34/(1+$B65)^8.5 + $H$34/(1+$B65)^9.5 + $I$34/(1+$B65)^10.5 +$I$34*(1+G$64)/($B65-G$64)/(1+$B65)^11 +Assumptions!$D$138-Assumptions!$D$140) /Assumptions!$E$158,0) -> 283 | H65: =ROUND( ($C$23/(1+$B65)^0.5 + $D$23/(1+$B65)^1.5 + $E$23/(1+$B65)^2.5 + $F$23/(1+$B65)^3.5 +$C$34/(1+$B65)^4.5 + $D$34/(1+$B65)^5.5 + $E$34/(1+$B65)^6.5 + $F$34/(1+$B65)^7.5 +$G$34/(1+$B65)^8.5 + $H$34/(1+$B65)^9.5 + $I$34/(1+$B65)^10.5 +$I$34*(1+H$64)/($B65-H$64)/(1+$B65)^11 +Assumptions!$D$138-Assumptions!$D$140) /Assumptions!$E$158,0) -> 306 | I65: =ROUND( ($C$23/(1+$B65)^0.5 + $D$23/(1+$B65)^1.5 + $E$23/(1+$B65)^2.5 + $F$23/(1+$B65)^3.5 +$C$34/(1+$B65)^4.5 + $D$34/(1+$B65)^5.5 + $E$34/(1+$B65)^6.5 + $F$34/(1+$B65)^7.5 +$G$34/(1+$B65)^8.5 + $H$34/(1+$B65)^9.5 + $I$34/(1+$B65)^10.5 +$I$34*(1+I$64)/($B65-I$64)/(1+$B65)^11 +Assumptions!$D$138-Assumptions!$D$140) /Assumptions!$E$158,0) -> 334
B66: 0.115 | C66: =ROUND( ($C$23/(1+$B66)^0.5 + $D$23/(1+$B66)^1.5 + $E$23/(1+$B66)^2.5 + $F$23/(1+$B66)^3.5 +$C$34/(1+$B66)^4.5 + $D$34/(1+$B66)^5.5 + $E$34/(1+$B66)^6.5 + $F$34/(1+$B66)^7.5 +$G$34/(1+$B66)^8.5 + $H$34/(1+$B66)^9.5 + $I$34/(1+$B66)^10.5 +$I$34*(1+C$64)/($B66-C$64)/(1+$B66)^11 +Assumptions!$D$138-Assumptions!$D$140) /Assumptions!$E$158,0) -> 208 | D66: =ROUND( ($C$23/(1+$B66)^0.5 + $D$23/(1+$B66)^1.5 + $E$23/(1+$B66)^2.5 + $F$23/(1+$B66)^3.5 +$C$34/(1+$B66)^4.5 + $D$34/(1+$B66)^5.5 + $E$34/(1+$B66)^6.5 + $F$34/(1+$B66)^7.5 +$G$34/(1+$B66)^8.5 + $H$34/(1+$B66)^9.5 + $I$34/(1+$B66)^10.5 +$I$34*(1+D$64)/($B66-D$64)/(1+$B66)^11 +Assumptions!$D$138-Assumptions!$D$140) /Assumptions!$E$158,0) -> 217 | E66: =ROUND( ($C$23/(1+$B66)^0.5 + $D$23/(1+$B66)^1.5 + $E$23/(1+$B66)^2.5 + $F$23/(1+$B66)^3.5 +$C$34/(1+$B66)^4.5 + $D$34/(1+$B66)^5.5 + $E$34/(1+$B66)^6.5 + $F$34/(1+$B66)^7.5 +$G$34/(1+$B66)^8.5 + $H$34/(1+$B66)^9.5 + $I$34/(1+$B66)^10.5 +$I$34*(1+E$64)/($B66-E$64)/(1+$B66)^11 +Assumptions!$D$138-Assumptions!$D$140) /Assumptions!$E$158,0) -> 228 | F66: =ROUND( ($C$23/(1+$B66)^0.5 + $D$23/(1+$B66)^1.5 + $E$23/(1+$B66)^2.5 + $F$23/(1+$B66)^3.5 +$C$34/(1+$B66)^4.5 + $D$34/(1+$B66)^5.5 + $E$34/(1+$B66)^6.5 + $F$34/(1+$B66)^7.5 +$G$34/(1+$B66)^8.5 + $H$34/(1+$B66)^9.5 + $I$34/(1+$B66)^10.5 +$I$34*(1+F$64)/($B66-F$64)/(1+$B66)^11 +Assumptions!$D$138-Assumptions!$D$140) /Assumptions!$E$158,0) -> 240 | G66: =ROUND( ($C$23/(1+$B66)^0.5 + $D$23/(1+$B66)^1.5 + $E$23/(1+$B66)^2.5 + $F$23/(1+$B66)^3.5 +$C$34/(1+$B66)^4.5 + $D$34/(1+$B66)^5.5 + $E$34/(1+$B66)^6.5 + $F$34/(1+$B66)^7.5 +$G$34/(1+$B66)^8.5 + $H$34/(1+$B66)^9.5 + $I$34/(1+$B66)^10.5 +$I$34*(1+G$64)/($B66-G$64)/(1+$B66)^11 +Assumptions!$D$138-Assumptions!$D$140) /Assumptions!$E$158,0) -> 255 | H66: =ROUND( ($C$23/(1+$B66)^0.5 + $D$23/(1+$B66)^1.5 + $E$23/(1+$B66)^2.5 + $F$23/(1+$B66)^3.5 +$C$34/(1+$B66)^4.5 + $D$34/(1+$B66)^5.5 + $E$34/(1+$B66)^6.5 + $F$34/(1+$B66)^7.5 +$G$34/(1+$B66)^8.5 + $H$34/(1+$B66)^9.5 + $I$34/(1+$B66)^10.5 +$I$34*(1+H$64)/($B66-H$64)/(1+$B66)^11 +Assumptions!$D$138-Assumptions!$D$140) /Assumptions!$E$158,0) -> 273 | I66: =ROUND( ($C$23/(1+$B66)^0.5 + $D$23/(1+$B66)^1.5 + $E$23/(1+$B66)^2.5 + $F$23/(1+$B66)^3.5 +$C$34/(1+$B66)^4.5 + $D$34/(1+$B66)^5.5 + $E$34/(1+$B66)^6.5 + $F$34/(1+$B66)^7.5 +$G$34/(1+$B66)^8.5 + $H$34/(1+$B66)^9.5 + $I$34/(1+$B66)^10.5 +$I$34*(1+I$64)/($B66-I$64)/(1+$B66)^11 +Assumptions!$D$138-Assumptions!$D$140) /Assumptions!$E$158,0) -> 294
B67: 0.125 | C67: =ROUND( ($C$23/(1+$B67)^0.5 + $D$23/(1+$B67)^1.5 + $E$23/(1+$B67)^2.5 + $F$23/(1+$B67)^3.5 +$C$34/(1+$B67)^4.5 + $D$34/(1+$B67)^5.5 + $E$34/(1+$B67)^6.5 + $F$34/(1+$B67)^7.5 +$G$34/(1+$B67)^8.5 + $H$34/(1+$B67)^9.5 + $I$34/(1+$B67)^10.5 +$I$34*(1+C$64)/($B67-C$64)/(1+$B67)^11 +Assumptions!$D$138-Assumptions!$D$140) /Assumptions!$E$158,0) -> 179 | D67: =ROUND( ($C$23/(1+$B67)^0.5 + $D$23/(1+$B67)^1.5 + $E$23/(1+$B67)^2.5 + $F$23/(1+$B67)^3.5 +$C$34/(1+$B67)^4.5 + $D$34/(1+$B67)^5.5 + $E$34/(1+$B67)^6.5 + $F$34/(1+$B67)^7.5 +$G$34/(1+$B67)^8.5 + $H$34/(1+$B67)^9.5 + $I$34/(1+$B67)^10.5 +$I$34*(1+D$64)/($B67-D$64)/(1+$B67)^11 +Assumptions!$D$138-Assumptions!$D$140) /Assumptions!$E$158,0) -> 186 | E67: =ROUND( ($C$23/(1+$B67)^0.5 + $D$23/(1+$B67)^1.5 + $E$23/(1+$B67)^2.5 + $F$23/(1+$B67)^3.5 +$C$34/(1+$B67)^4.5 + $D$34/(1+$B67)^5.5 + $E$34/(1+$B67)^6.5 + $F$34/(1+$B67)^7.5 +$G$34/(1+$B67)^8.5 + $H$34/(1+$B67)^9.5 + $I$34/(1+$B67)^10.5 +$I$34*(1+E$64)/($B67-E$64)/(1+$B67)^11 +Assumptions!$D$138-Assumptions!$D$140) /Assumptions!$E$158,0) -> 193 | F67: =ROUND( ($C$23/(1+$B67)^0.5 + $D$23/(1+$B67)^1.5 + $E$23/(1+$B67)^2.5 + $F$23/(1+$B67)^3.5 +$C$34/(1+$B67)^4.5 + $D$34/(1+$B67)^5.5 + $E$34/(1+$B67)^6.5 + $F$34/(1+$B67)^7.5 +$G$34/(1+$B67)^8.5 + $H$34/(1+$B67)^9.5 + $I$34/(1+$B67)^10.5 +$I$34*(1+F$64)/($B67-F$64)/(1+$B67)^11 +Assumptions!$D$138-Assumptions!$D$140) /Assumptions!$E$158,0) -> 202 | G67: =ROUND( ($C$23/(1+$B67)^0.5 + $D$23/(1+$B67)^1.5 + $E$23/(1+$B67)^2.5 + $F$23/(1+$B67)^3.5 +$C$34/(1+$B67)^4.5 + $D$34/(1+$B67)^5.5 + $E$34/(1+$B67)^6.5 + $F$34/(1+$B67)^7.5 +$G$34/(1+$B67)^8.5 + $H$34/(1+$B67)^9.5 + $I$34/(1+$B67)^10.5 +$I$34*(1+G$64)/($B67-G$64)/(1+$B67)^11 +Assumptions!$D$138-Assumptions!$D$140) /Assumptions!$E$158,0) -> 211 | H67: =ROUND( ($C$23/(1+$B67)^0.5 + $D$23/(1+$B67)^1.5 + $E$23/(1+$B67)^2.5 + $F$23/(1+$B67)^3.5 +$C$34/(1+$B67)^4.5 + $D$34/(1+$B67)^5.5 + $E$34/(1+$B67)^6.5 + $F$34/(1+$B67)^7.5 +$G$34/(1+$B67)^8.5 + $H$34/(1+$B67)^9.5 + $I$34/(1+$B67)^10.5 +$I$34*(1+H$64)/($B67-H$64)/(1+$B67)^11 +Assumptions!$D$138-Assumptions!$D$140) /Assumptions!$E$158,0) -> 223 | I67: =ROUND( ($C$23/(1+$B67)^0.5 + $D$23/(1+$B67)^1.5 + $E$23/(1+$B67)^2.5 + $F$23/(1+$B67)^3.5 +$C$34/(1+$B67)^4.5 + $D$34/(1+$B67)^5.5 + $E$34/(1+$B67)^6.5 + $F$34/(1+$B67)^7.5 +$G$34/(1+$B67)^8.5 + $H$34/(1+$B67)^9.5 + $I$34/(1+$B67)^10.5 +$I$34*(1+I$64)/($B67-I$64)/(1+$B67)^11 +Assumptions!$D$138-Assumptions!$D$140) /Assumptions!$E$158,0) -> 236
B68: 0.13 | C68: =ROUND( ($C$23/(1+$B68)^0.5 + $D$23/(1+$B68)^1.5 + $E$23/(1+$B68)^2.5 + $F$23/(1+$B68)^3.5 +$C$34/(1+$B68)^4.5 + $D$34/(1+$B68)^5.5 + $E$34/(1+$B68)^6.5 + $F$34/(1+$B68)^7.5 +$G$34/(1+$B68)^8.5 + $H$34/(1+$B68)^9.5 + $I$34/(1+$B68)^10.5 +$I$34*(1+C$64)/($B68-C$64)/(1+$B68)^11 +Assumptions!$D$138-Assumptions!$D$140) /Assumptions!$E$158,0) -> 168 | D68: =ROUND( ($C$23/(1+$B68)^0.5 + $D$23/(1+$B68)^1.5 + $E$23/(1+$B68)^2.5 + $F$23/(1+$B68)^3.5 +$C$34/(1+$B68)^4.5 + $D$34/(1+$B68)^5.5 + $E$34/(1+$B68)^6.5 + $F$34/(1+$B68)^7.5 +$G$34/(1+$B68)^8.5 + $H$34/(1+$B68)^9.5 + $I$34/(1+$B68)^10.5 +$I$34*(1+D$64)/($B68-D$64)/(1+$B68)^11 +Assumptions!$D$138-Assumptions!$D$140) /Assumptions!$E$158,0) -> 173 | E68: =ROUND( ($C$23/(1+$B68)^0.5 + $D$23/(1+$B68)^1.5 + $E$23/(1+$B68)^2.5 + $F$23/(1+$B68)^3.5 +$C$34/(1+$B68)^4.5 + $D$34/(1+$B68)^5.5 + $E$34/(1+$B68)^6.5 + $F$34/(1+$B68)^7.5 +$G$34/(1+$B68)^8.5 + $H$34/(1+$B68)^9.5 + $I$34/(1+$B68)^10.5 +$I$34*(1+E$64)/($B68-E$64)/(1+$B68)^11 +Assumptions!$D$138-Assumptions!$D$140) /Assumptions!$E$158,0) -> 179 | F68: =ROUND( ($C$23/(1+$B68)^0.5 + $D$23/(1+$B68)^1.5 + $E$23/(1+$B68)^2.5 + $F$23/(1+$B68)^3.5 +$C$34/(1+$B68)^4.5 + $D$34/(1+$B68)^5.5 + $E$34/(1+$B68)^6.5 + $F$34/(1+$B68)^7.5 +$G$34/(1+$B68)^8.5 + $H$34/(1+$B68)^9.5 + $I$34/(1+$B68)^10.5 +$I$34*(1+F$64)/($B68-F$64)/(1+$B68)^11 +Assumptions!$D$138-Assumptions!$D$140) /Assumptions!$E$158,0) -> 186 | G68: =ROUND( ($C$23/(1+$B68)^0.5 + $D$23/(1+$B68)^1.5 + $E$23/(1+$B68)^2.5 + $F$23/(1+$B68)^3.5 +$C$34/(1+$B68)^4.5 + $D$34/(1+$B68)^5.5 + $E$34/(1+$B68)^6.5 + $F$34/(1+$B68)^7.5 +$G$34/(1+$B68)^8.5 + $H$34/(1+$B68)^9.5 + $I$34/(1+$B68)^10.5 +$I$34*(1+G$64)/($B68-G$64)/(1+$B68)^11 +Assumptions!$D$138-Assumptions!$D$140) /Assumptions!$E$158,0) -> 195 | H68: =ROUND( ($C$23/(1+$B68)^0.5 + $D$23/(1+$B68)^1.5 + $E$23/(1+$B68)^2.5 + $F$23/(1+$B68)^3.5 +$C$34/(1+$B68)^4.5 + $D$34/(1+$B68)^5.5 + $E$34/(1+$B68)^6.5 + $F$34/(1+$B68)^7.5 +$G$34/(1+$B68)^8.5 + $H$34/(1+$B68)^9.5 + $I$34/(1+$B68)^10.5 +$I$34*(1+H$64)/($B68-H$64)/(1+$B68)^11 +Assumptions!$D$138-Assumptions!$D$140) /Assumptions!$E$158,0) -> 204 | I68: =ROUND( ($C$23/(1+$B68)^0.5 + $D$23/(1+$B68)^1.5 + $E$23/(1+$B68)^2.5 + $F$23/(1+$B68)^3.5 +$C$34/(1+$B68)^4.5 + $D$34/(1+$B68)^5.5 + $E$34/(1+$B68)^6.5 + $F$34/(1+$B68)^7.5 +$G$34/(1+$B68)^8.5 + $H$34/(1+$B68)^9.5 + $I$34/(1+$B68)^10.5 +$I$34*(1+I$64)/($B68-I$64)/(1+$B68)^11 +Assumptions!$D$138-Assumptions!$D$140) /Assumptions!$E$158,0) -> 215
B69: 0.145 | C69: =ROUND( ($C$23/(1+$B69)^0.5 + $D$23/(1+$B69)^1.5 + $E$23/(1+$B69)^2.5 + $F$23/(1+$B69)^3.5 +$C$34/(1+$B69)^4.5 + $D$34/(1+$B69)^5.5 + $E$34/(1+$B69)^6.5 + $F$34/(1+$B69)^7.5 +$G$34/(1+$B69)^8.5 + $H$34/(1+$B69)^9.5 + $I$34/(1+$B69)^10.5 +$I$34*(1+C$64)/($B69-C$64)/(1+$B69)^11 +Assumptions!$D$138-Assumptions!$D$140) /Assumptions!$E$158,0) -> 140 | D69: =ROUND( ($C$23/(1+$B69)^0.5 + $D$23/(1+$B69)^1.5 + $E$23/(1+$B69)^2.5 + $F$23/(1+$B69)^3.5 +$C$34/(1+$B69)^4.5 + $D$34/(1+$B69)^5.5 + $E$34/(1+$B69)^6.5 + $F$34/(1+$B69)^7.5 +$G$34/(1+$B69)^8.5 + $H$34/(1+$B69)^9.5 + $I$34/(1+$B69)^10.5 +$I$34*(1+D$64)/($B69-D$64)/(1+$B69)^11 +Assumptions!$D$138-Assumptions!$D$140) /Assumptions!$E$158,0) -> 143 | E69: =ROUND( ($C$23/(1+$B69)^0.5 + $D$23/(1+$B69)^1.5 + $E$23/(1+$B69)^2.5 + $F$23/(1+$B69)^3.5 +$C$34/(1+$B69)^4.5 + $D$34/(1+$B69)^5.5 + $E$34/(1+$B69)^6.5 + $F$34/(1+$B69)^7.5 +$G$34/(1+$B69)^8.5 + $H$34/(1+$B69)^9.5 + $I$34/(1+$B69)^10.5 +$I$34*(1+E$64)/($B69-E$64)/(1+$B69)^11 +Assumptions!$D$138-Assumptions!$D$140) /Assumptions!$E$158,0) -> 147 | F69: =ROUND( ($C$23/(1+$B69)^0.5 + $D$23/(1+$B69)^1.5 + $E$23/(1+$B69)^2.5 + $F$23/(1+$B69)^3.5 +$C$34/(1+$B69)^4.5 + $D$34/(1+$B69)^5.5 + $E$34/(1+$B69)^6.5 + $F$34/(1+$B69)^7.5 +$G$34/(1+$B69)^8.5 + $H$34/(1+$B69)^9.5 + $I$34/(1+$B69)^10.5 +$I$34*(1+F$64)/($B69-F$64)/(1+$B69)^11 +Assumptions!$D$138-Assumptions!$D$140) /Assumptions!$E$158,0) -> 151 | G69: =ROUND( ($C$23/(1+$B69)^0.5 + $D$23/(1+$B69)^1.5 + $E$23/(1+$B69)^2.5 + $F$23/(1+$B69)^3.5 +$C$34/(1+$B69)^4.5 + $D$34/(1+$B69)^5.5 + $E$34/(1+$B69)^6.5 + $F$34/(1+$B69)^7.5 +$G$34/(1+$B69)^8.5 + $H$34/(1+$B69)^9.5 + $I$34/(1+$B69)^10.5 +$I$34*(1+G$64)/($B69-G$64)/(1+$B69)^11 +Assumptions!$D$138-Assumptions!$D$140) /Assumptions!$E$158,0) -> 156 | H69: =ROUND( ($C$23/(1+$B69)^0.5 + $D$23/(1+$B69)^1.5 + $E$23/(1+$B69)^2.5 + $F$23/(1+$B69)^3.5 +$C$34/(1+$B69)^4.5 + $D$34/(1+$B69)^5.5 + $E$34/(1+$B69)^6.5 + $F$34/(1+$B69)^7.5 +$G$34/(1+$B69)^8.5 + $H$34/(1+$B69)^9.5 + $I$34/(1+$B69)^10.5 +$I$34*(1+H$64)/($B69-H$64)/(1+$B69)^11 +Assumptions!$D$138-Assumptions!$D$140) /Assumptions!$E$158,0) -> 162 | I69: =ROUND( ($C$23/(1+$B69)^0.5 + $D$23/(1+$B69)^1.5 + $E$23/(1+$B69)^2.5 + $F$23/(1+$B69)^3.5 +$C$34/(1+$B69)^4.5 + $D$34/(1+$B69)^5.5 + $E$34/(1+$B69)^6.5 + $F$34/(1+$B69)^7.5 +$G$34/(1+$B69)^8.5 + $H$34/(1+$B69)^9.5 + $I$34/(1+$B69)^10.5 +$I$34*(1+I$64)/($B69-I$64)/(1+$B69)^11 +Assumptions!$D$138-Assumptions!$D$140) /Assumptions!$E$158,0) -> 168
B70: 0.15 | C70: =ROUND( ($C$23/(1+$B70)^0.5 + $D$23/(1+$B70)^1.5 + $E$23/(1+$B70)^2.5 + $F$23/(1+$B70)^3.5 +$C$34/(1+$B70)^4.5 + $D$34/(1+$B70)^5.5 + $E$34/(1+$B70)^6.5 + $F$34/(1+$B70)^7.5 +$G$34/(1+$B70)^8.5 + $H$34/(1+$B70)^9.5 + $I$34/(1+$B70)^10.5 +$I$34*(1+C$64)/($B70-C$64)/(1+$B70)^11 +Assumptions!$D$138-Assumptions!$D$140) /Assumptions!$E$158,0) -> 132 | D70: =ROUND( ($C$23/(1+$B70)^0.5 + $D$23/(1+$B70)^1.5 + $E$23/(1+$B70)^2.5 + $F$23/(1+$B70)^3.5 +$C$34/(1+$B70)^4.5 + $D$34/(1+$B70)^5.5 + $E$34/(1+$B70)^6.5 + $F$34/(1+$B70)^7.5 +$G$34/(1+$B70)^8.5 + $H$34/(1+$B70)^9.5 + $I$34/(1+$B70)^10.5 +$I$34*(1+D$64)/($B70-D$64)/(1+$B70)^11 +Assumptions!$D$138-Assumptions!$D$140) /Assumptions!$E$158,0) -> 135 | E70: =ROUND( ($C$23/(1+$B70)^0.5 + $D$23/(1+$B70)^1.5 + $E$23/(1+$B70)^2.5 + $F$23/(1+$B70)^3.5 +$C$34/(1+$B70)^4.5 + $D$34/(1+$B70)^5.5 + $E$34/(1+$B70)^6.5 + $F$34/(1+$B70)^7.5 +$G$34/(1+$B70)^8.5 + $H$34/(1+$B70)^9.5 + $I$34/(1+$B70)^10.5 +$I$34*(1+E$64)/($B70-E$64)/(1+$B70)^11 +Assumptions!$D$138-Assumptions!$D$140) /Assumptions!$E$158,0) -> 139 | F70: =ROUND( ($C$23/(1+$B70)^0.5 + $D$23/(1+$B70)^1.5 + $E$23/(1+$B70)^2.5 + $F$23/(1+$B70)^3.5 +$C$34/(1+$B70)^4.5 + $D$34/(1+$B70)^5.5 + $E$34/(1+$B70)^6.5 + $F$34/(1+$B70)^7.5 +$G$34/(1+$B70)^8.5 + $H$34/(1+$B70)^9.5 + $I$34/(1+$B70)^10.5 +$I$34*(1+F$64)/($B70-F$64)/(1+$B70)^11 +Assumptions!$D$138-Assumptions!$D$140) /Assumptions!$E$158,0) -> 142 | G70: =ROUND( ($C$23/(1+$B70)^0.5 + $D$23/(1+$B70)^1.5 + $E$23/(1+$B70)^2.5 + $F$23/(1+$B70)^3.5 +$C$34/(1+$B70)^4.5 + $D$34/(1+$B70)^5.5 + $E$34/(1+$B70)^6.5 + $F$34/(1+$B70)^7.5 +$G$34/(1+$B70)^8.5 + $H$34/(1+$B70)^9.5 + $I$34/(1+$B70)^10.5 +$I$34*(1+G$64)/($B70-G$64)/(1+$B70)^11 +Assumptions!$D$138-Assumptions!$D$140) /Assumptions!$E$158,0) -> 146 | H70: =ROUND( ($C$23/(1+$B70)^0.5 + $D$23/(1+$B70)^1.5 + $E$23/(1+$B70)^2.5 + $F$23/(1+$B70)^3.5 +$C$34/(1+$B70)^4.5 + $D$34/(1+$B70)^5.5 + $E$34/(1+$B70)^6.5 + $F$34/(1+$B70)^7.5 +$G$34/(1+$B70)^8.5 + $H$34/(1+$B70)^9.5 + $I$34/(1+$B70)^10.5 +$I$34*(1+H$64)/($B70-H$64)/(1+$B70)^11 +Assumptions!$D$138-Assumptions!$D$140) /Assumptions!$E$158,0) -> 151 | I70: =ROUND( ($C$23/(1+$B70)^0.5 + $D$23/(1+$B70)^1.5 + $E$23/(1+$B70)^2.5 + $F$23/(1+$B70)^3.5 +$C$34/(1+$B70)^4.5 + $D$34/(1+$B70)^5.5 + $E$34/(1+$B70)^6.5 + $F$34/(1+$B70)^7.5 +$G$34/(1+$B70)^8.5 + $H$34/(1+$B70)^9.5 + $I$34/(1+$B70)^10.5 +$I$34*(1+I$64)/($B70-I$64)/(1+$B70)^11 +Assumptions!$D$138-Assumptions!$D$140) /Assumptions!$E$158,0) -> 156
B72: SECTION 6 - FOOTBALL FIELD CHART DATA
B74: Valuation Method | C74: Low (₹) | D74: High (₹)
B75: DCF Bear Case | C75: ="₹"&ROUND($C$56,0) -> ₹149 | D75: ="₹"&ROUND($C$56,0) -> ₹149
B76: DCF Base Case | C76: ="₹"&ROUND($D$56,0) -> ₹170 | D76: ="₹"&ROUND($D$56,0) -> ₹170
B77: DCF Bull Case | C77: ="₹"&ROUND($E$56,0) -> ₹229 | D77: ="₹"&ROUND($E$56,0) -> ₹229
B78: EV/Revenue Comps 4–9x FY26E | C78: ₹144 | D78: ₹290
B79: EV/EBITDA Comps 35–80x FY26E | C79: ₹101 | D79: ₹202
B80: 52-Week Trading Range | C80: ₹213 | D80: ₹368
B81: CMP (Feb 2026) | C81: ₹249 | D81: ₹249

Sheet SOTP Valution
B2: STOP VALUATION - ETERNAL LIMITED
B3: Sum-of-the-Parts Valuation | FY28E Forward Multiples | Bear / Base / Bull Scenarios | April 2026
B5: SECTION 1 - METHODOLOGY & RATIONALE
B6: Food Delivery on EV/Adj.EBITDA (mature, profitable). Blinkit on EV/GOV (pre-maturity, GOV-based industry standard). Hyperpure on EV/Revenue (B2B, thin margins). District on EV/GOV (early- stage platform). Net Cash added at book. Leases deducted at book. Three scenarios via multiple ranges.
B8: SECTION 2 — SEGMENT VALUATION TABLE
B9: Segment | C9: Valuation Metric | D9: FY28E Value (₹ Cr) | E9: Bear Multiple | F9: Base Multiple | G9: Bull Multiple | H9: Bear EV (₹ Cr) | I9: Base EV (₹ Cr) | J9: Bull EV (₹ Cr) | K9: Multiple Justification
B10: Food Delivery (Zomato) | C10: EV / Adj. EBITDA (FY28E) | D10: =' SEGMENT P&L'!H15 -> 3117.9483 | E10: 35 | F10: 40 | G10: 48 | H10: =ROUND(E10*D10,0) -> 109128 | I10: =ROUND(F10*D10,0) -> 124718 | J10: =ROUND(G10*D10,0) -> 149662 | K10: Nomura: 40x FY28E. DoorDash ~34x NTM. FD EBITDA FY28E=₹3,118 Cr at 5.7% NOV margin. Bear=35x (competition), Base=40x (Nomura aligned), Bull=48x (India internet premium + leadership).
B11: Blinkit (Quick Commerce) | C11: EV / GOV (FY28E) | D11: =' SEGMENT P&L'!H28 -> 75503 | E11: 0.9 | F11: 1.2 | G11: 1.6 | H11: =ROUND(E11*D11,0) -> 67953 | I11: =ROUND(F11*D11,0) -> 90604 | J11: =ROUND(G11*D11,0) -> 120805 | K11: Nomura: 1.2x EV/GOV. Zepto private 1.0-1.3x. 45% QC market share. GOV FY28E=₹75,503 Cr. Bear=0.9x execution risk, Base=1.2x Nomura aligned, Bull=1.6x market dominance.
B12: Hyperpure (B2B Supply) | C12: EV / Revenue (FY28E) | D12: =' SEGMENT P&L'!H48 -> 19405.872 | E12: 0.5 | F12: 0.7 | G12: 0.9 | H12: =ROUND(E12*D12,0) -> 9703 | I12: =ROUND(F12*D12,0) -> 13584 | J12: =ROUND(G12*D12,0) -> 17465 | K12: B2B food supply chain. Revenue FY28E=₹19,406 Cr at 3.5% EBITDA margin. No listed comp. Bear=0.5x thin margins, Base=0.7x, Bull=0.9x scale benefit.
B13: District (Going-Out/Events) | C13: EV / GOV (FY28E) | D13: =' SEGMENT P&L'!H57 -> 27782 | E13: 0.2 | F13: 0.4 | G13: 0.5 | H13: =ROUND(E13*D13,0) -> 5556 | I13: =ROUND(F13*D13,0) -> 11113 | J13: =ROUND(G13*D13,0) -> 13891 | K13: Early-stage, loss-making. GOV FY28E=₹27,782 Cr. EBITDA turns positive FY28E. Deeply discounted. Bear=0.2x (optionality), Base=0.35x, Bull=0.5x (category proves out).
B14: Others / Platform Services | C14: EV / Revenue (FY28E) | D14: =' SEGMENT P&L'!H72 -> 25 | E14: 0.5 | F14: 0.5 | G14: 0.5 | H14: =ROUND(E14*D14,0) -> 13 | I14: =ROUND(F14*D14,0) -> 13 | J14: =ROUND(G14*D14,0) -> 13 | K14: Negligible contribution. Flat multiple all scenarios.
B16: TOTAL SEGMENT EV (₹ Cr) | H16: =SUM(H10:H15) -> 192353 | I16: =SUM(I10:I15) -> 240032 | J16: =SUM(J10:J15) -> 301836
B17: Food Delivery % of Segment EV | H17: =TEXT(ROUND(H10/H16*100,1),"0.0")&"%" -> 56.7% | I17: =TEXT(ROUND(I10/I16*100,1),"0.0")&"%" -> 52.0% | J17: =TEXT(ROUND(J10/J16*100,1),"0.0")&"%" -> 49.6%
B18: Blinkit % of Segment EV | H18: =TEXT(ROUND(H11/H16*100,1),"0.0")&"%" -> 35.3% | I18: =TEXT(ROUND(I11/I16*100,1),"0.0")&"%" -> 37.7% | J18: =TEXT(ROUND(J11/J16*100,1),"0.0")&"%" -> 40.0%
B20: SECTION 2 - EV TO EQUITY BRIDGE
B21: Total Segment EV (₹ Cr) | H21: =H16 -> 192353 | I21: =I16 -> 240032 | J21: =J16 -> 301836
B22: Add: Net Liquid Assets - FY25A (₹ Cr) | H22: ='DCF + Sensitivity'!D50 -> 16806 | I22: ='DCF + Sensitivity'!E50 -> 16806 | J22: ='DCF + Sensitivity'!F50 -> 16806
B23: Less: Lease Liabilities - FY25A (₹ Cr) | H23: ='DCF + Sensitivity'!D51 -> -2045 | I23: ='DCF + Sensitivity'!E51 -> -2045 | J23: ='DCF + Sensitivity'!F51 -> -2045
B24: Less: Financial Debt (₹ Cr) | H24: ='DCF + Sensitivity'!D52 -> 0 | I24: ='DCF + Sensitivity'!E52 -> 0 | J24: ='DCF + Sensitivity'!F52 -> 0
B26: EQUITY VALUE (₹ Cr) | H26: =H21+H22+H23+H24 -> 207114 | I26: =I21+I22+I23+I24 -> 254793 | J26: =J21+J22+J23+J24 -> 316597
B27: Diluted Shares Outstanding (Cr) | H27: ='DCF + Sensitivity'!D54 -> 940 | I27: ='DCF + Sensitivity'!E54 -> 940 | J27: ='DCF + Sensitivity'!F54 -> 940
B29: SECTION 3 - SOTP VALUATION SUMMARY
B30: Metric | C30: Bear Case | D30: Base Case | E30: Bull Case | F30: Notes
B31: Equity Value (₹ Cr) | C31: =H26 -> 207114 | D31: =I26 -> 254793 | E31: =J26 -> 316597 | F31: Post net cash add & lease deduction
B32: SOTP Intrinsic Value Per Share (₹) | C32: =ROUND(H26/H27,0) -> 220 | D32: =ROUND(I26/I27,0) -> 271 | E32: =ROUND(J26/J27,0) -> 337 | F32: FY28E multiples - Nomura aligned
B33: CMP — April 2026 (₹) | C33: 249 | D33: 249 | E33: 249 | F33: Consol FY28E Adj EBITDA = ₹6,609 Cr (sanity check)
B34: Upside / (Downside) vs CMP | C34: =TEXT(ROUND((C32/C33-1)*100,1),"0.0")&"%" -> -11.6% | D34: =TEXT(ROUND((D32/D33-1)*100,1),"0.0")&"%" -> 8.8% | E34: =TEXT(ROUND((E32/E33-1)*100,1),"0.0")&"%" -> 35.3%
B35: Implied EV / Consol Adj EBITDA FY28E | C35: =TEXT(ROUND(H16/' SEGMENT P&L'!$H$73,1),"0.0")&"x" -> 29.5x | D35: =TEXT(ROUND(I16/' SEGMENT P&L'!$H$73,1),"0.0")&"x" -> 36.8x | E35: =TEXT(ROUND(J16/' SEGMENT P&L'!$H$73,1),"0.0")&"x" -> 46.2x
B36: Implied P/E FY28E | C36: =TEXT(ROUND(C32*'DCF + Sensitivity'!$E$54/'3-Statement'!$I$53,1),"0.0")&"x" -> 50.9x | D36: =TEXT(ROUND(D32*'DCF + Sensitivity'!$E$54/'3-Statement'!$I$53,1),"0.0")&"x" -> 62.7x | E36: =TEXT(ROUND(E32*'DCF + Sensitivity'!$E$54/'3-Statement'!$I$53,1),"0.0")&"x" -> 77.9x | F36: PAT FY28E = ₹4,124 Cr per 3-Statement
B38: SECTION 5 — SOTP vs DCF RECONCILIATION
B39: Method | C39: Bear (₹) | D39: Base (₹) | E39: Bull (₹) | F39: Weight | G39: Rationale
B40: DCF Valuation | C40: ='DCF + Sensitivity'!C56 -> 148.74069 | D40: ='DCF + Sensitivity'!D56 -> 170.17383 | E40: ='DCF + Sensitivity'!E56 -> 229.31405 | F40: 0.6 | G40: Captures long-run terminal economics - majority weight
B41: SOTP Valuation | C41: =C32 -> 220 | D41: =D32 -> 271 | E41: =E32 -> 337 | F41: 0.4 | G41: Near-term segment multiples - Blinkit optionality captured
B43: BLENDED INTRINSIC VALUE (₹) | C43: =ROUND(C40*0.6+C41*0.4,0) -> 177 | D43: =ROUND(D40*0.6+D41*0.4,0) -> 211 | E43: =ROUND(E40*0.6+E41*0.4,0) -> 272
B44: Investment Rating | D44: HOLD
B45: 12-Month Target Price — Base Case (₹) | D45: =D43 -> 211
B46: CMP (₹) | D46: 249
B47: Upside / (Downside) to Target | D47: =TEXT(ROUND((D45/D46-1)*100,1),"0.0")&"%" -> -15.3%
B49: SECTION 6 — KEY ASSUMPTIONS & ANALYST BENCHMARKS
B50: 1. FOOD DELIVERY (EV/EBITDA 35–48x FY28E): Nomura uses 40x FY28E EBITDA. DoorDash 34x NTM. FD EBITDA FY28E = ₹3,118 Cr (5.7% NOV margin, 19% GOV growth). Base=40x Nomura-aligned. Bull=48x India internet premium + margin expansion.
B51: 2. BLINKIT (EV/GOV 0.9–1.6x FY28E): Nomura uses 1.2x EV/GOV implying 25x steady-state EBITDA at 5.2% margin. GOV FY28E = ₹75,503 Cr. 2,600+ dark stores. 45% QC market share. Bear=0.9x competition/execution, Bull=1.6x dominance.
B52: 3. HYPERPURE (EV/Revenue 0.5–0.9x FY28E): Revenue ₹19,406 Cr FY28E. EBITDA margin 3.5%. B2B supply chain - no listed comp. Revenue multiple appropriate for thin-margin business. Path to 4-5% margin post FY28E.
B53: 4. DISTRICT (EV/GOV 0.2–0.5x FY28E): GOV ₹27,782 Cr FY28E. EBITDA turns positive FY28E (₹354 Cr). Early-stage events/dining platform. Deeply discounted vs Blinkit. Bull=0.5x if category achieves platform-level adoption.
B54: 5. BLENDED WEIGHT (DCF 60%, SOTP 40%): DCF captures terminal EBITDA expansion through FY36 (22% margin). SOTP anchors near-term multiples. SOTP > DCF - Blinkit GOV multiple captures optionality that DCF's WACC discounts heavily. Blended = appropriate convergence.
B55: Source: Nomura Sep 2025 (₹370 target, 40x FY28E FD EBITDA, 1.2x Blinkit GOV); Axis Securities May 2025 (₹230 HOLD SOTP); Motilal Oswal Jan 2025 (₹270 Buy DCF). All multiples cross-checked vs published brokerage reports.

Sheet Comps
B2: COMPARABLE COMPANY ANALYSIS - ETERNAL LIMITED | April 2026
B3: Sources: NSE/BSE live prices | DoorDash FY2025 10-K | Swiggy FY25 Annual Report | Conversion: ₹84/$
B5: SECTION 1 — PEER UNIVERSE
B6: Company | C6: Ticker | D6: CMP | E6: Mkt Cap (₹ Cr) | F6: EV (₹ Cr) | G6: Why Included
B7: ETERNAL LIMITED ← Subject | C7: NSE: ETERNAL | D7: ₹249 | E7: 240303 | F7: 225524 | G7: Subject company - food+QC+B2B+GoingOut
B8: SWIGGY LIMITED | C8: NSE: SWIGGY | D8: ₹272 | E8: 70767 | F8: 69162 | G8: Only direct Indian comp - food+QC+OOH
B9: DOORDASH INC | C9: NASDAQ: DASH | D9: 195 | E9: 646800 | F9: 621600 | G9: Global food delivery leader, profitable FY25
B10: DELIVERY HERO SE | C10: XETRA: DHER | D10: €0.85 | E10: 23000 | F10: 22000 | G10: Intl QC pioneer - verify Bloomberg
B11: SEA LIMITED | C11: NYSE: SE | D11: 29 | E11: 117600 | F11: 115000 | G11: SE Asia multi-vertical platform - proxy
B13: SECTION 2 — FINANCIAL METRICS SUMMARY
B14: Metric | C14: Eternal FY25A | D14: Eternal FY26E | E14: Swiggy FY25A | F14: DoorDash FY2025 | G14: Notes
B15: Revenue (₹ Cr) | C15: ='Historical Financials'!F12 -> 20243 | D15: ='3-Statement'!G7 -> 28641.422 | E15: 11247 | F15: 1152232 | G15: DoorDash $13.717B × 84 = ₹11.52L Cr
B16: Revenue Growth % (YoY) | C16: ='Historical Financials'!F13 -> 0.67104177 | D16: ='3-Statement'!G13 -> 0.41488029 | E16: 0.449 | F16: 0.279 | G16: Eternal 67% FY25 - highest among peers
B17: Adj. EBITDA (₹ Cr) | C17: ='3-Statement'!F27 -> 1079 | D17: ='3-Statement'!G27 -> 2274.8515 | E17: -2786 | F17: 129948 | G17: Swiggy still deeply loss-making -n/m for multiples
B18: Adj. EBITDA Margin % | C18: ='3-Statement'!F28 -> 0.053302376 | D18: ='3-Statement'!G28 -> 0.079425229 | E18: -0.248 | F18: 0.113 | G18: DoorDash 11.3% = Eternal's steady-state target
B19: PAT (₹ Cr) | C19: ='3-Statement'!F53 -> 527 | D19: ='3-Statement'!G53 -> 1593.8515 | E19: -3117 | F19: 78540 | G19: DoorDash $935M FY25 net income × 84
B21: SECTION 3 — TRADING MULTIPLES
B22: Multiple | C22: Eternal | D22: Swiggy | E22: DoorDash | F22: Peer Median | G22: Notes
B23: EV / Revenue - LTM (FY25A) | C23: 11.1x | D23: 6.1x | E23: 0.5x | F23: 5.8x | G23: Eternal 83% premium vs peers — Blinkit QC optionality
B24: EV / Revenue - NTM (FY26E) | C24: 7.5x | D24: 4.5x | E24: 4.1x | F24: 4.3x | G24: Eternal still at significant premium even on NTM
B25: EV / Adj. EBITDA - NTM | C25: 96.6x | D25: n/m | E25: 34.5x | F25: 34.5x | G25: Swiggy negative EBITDA → n/m; DoorDash = benchmark
B26: P/E - NTM | C26: 239x | D26: n/m | E26: 55x | F26: 55x | G26: All high-growth; P/E less meaningful here
B27: EV / B2C GOV (FY25A) | C27: 3.0x | D27: 2.0x | E27: 0.7x | F27: 1.5x | G27: India premium justified by higher GOV growth rate
B29: SECTION 4 — IMPLIED VALUATION FOR ETERNAL (Applying Peer Multiples to FY26E)
B30: Method | C30: Multiple Applied | D30: Eternal FY26E Metric (₹ Cr) | E30: Implied EV (₹ Cr) | F30: Implied Price (₹) | G30: vs CMP ₹249
B31: EV/Revenue 4.0x (Peer Median) | C31: 4 | D31: ='3-Statement'!$G$7 -> 28641.422 | E31: =C31*D31 -> 114565.69 | F31: =(E31+16806-2045)/940 -> 137.58158 | G31: =F31/249-1 -> -0.44746353
B32: EV/Revenue 5.0x (75th Pct) | C32: 5 | D32: ='3-Statement'!$G$7 -> 28641.422 | E32: =C32*D32 -> 143207.11 | F32: =(E32+16806-2045)/940 -> 168.05118 | G32: =F32/249-1 -> -0.32509567
B33: EV/Revenue 7.5x (Eternal Current NTM) | C33: 7.5 | D33: ='3-Statement'!$G$7 -> 28641.422 | E33: =C33*D33 -> 214810.66 | F33: =(E33+16806-2045)/940 -> 244.22517 | G33: =F33/249-1 -> -0.019176011
B34: EV/Revenue 9.0x (Growth Premium) | C34: 9 | D34: ='3-Statement'!$G$7 -> 28641.422 | E34: =C34*D34 -> 257772.8 | F34: =(E34+16806-2045)/940 -> 289.92957 | G34: =F34/249-1 -> 0.16437578
B35: EV/EBITDA 34.5x (DoorDash benchmark) | C35: 34.5 | D35: ='3-Statement'!$G$27 -> 2274.8515 | E35: =C35*D35 -> 78482.376 | F35: =(E35+16806-2045)/940 -> 99.195081 | G35: =F35/249-1 -> -0.60162618
B36: EV/EBITDA 50x | C36: 50 | D36: ='3-Statement'!$G$27 -> 2274.8515 | E36: =C36*D36 -> 113742.57 | F36: =(E36+16806-2045)/940 -> 136.70593 | G36: =F36/249-1 -> -0.4509802
B37: EV/EBITDA 75x | C37: 75 | D37: ='3-Statement'!$G$27 -> 2274.8515 | E37: =C37*D37 -> 170613.86 | F37: =(E37+16806-2045)/940 -> 197.2073 | G37: =F37/249-1 -> -0.20800282
B39: SECTION 5 — KEY ANALYTICAL OBSERVATIONS
B40: 1. ETERNAL INDIA PREMIUM: Eternal at 7.5x NTM EV/Revenue vs DoorDash 4.1x (+83%). Justified by: (a) India food delivery secular growth >>US, (b) Blinkit = unique QC asset with no DoorDash equivalent, (c) Hyperpure B2B vertical integration adding ecosystem depth.
B41: 2. SWIGGY DISCOUNT: Swiggy at 4.5x NTM vs Eternal 7.5x (−40%). Reason: Swiggy EBITDA deeply negative (−24.8% margin FY25 vs Eternal +7.1%), losing QC market share to Blinkit (Instamart stores: 700 vs Blinkit 1,301 as of FY25), no equivalent to Hyperpure.
B42: 3. DOORDASH TRAJECTORY: DoorDash reached 11.3% Adj EBITDA margin on $13.7B revenue FY2025 - this is Eternal's ~FY28-29 destination. Eternal at 7.1% margin FY25 is 3 years behind DoorDash's margin trajectory. This justifies premium vs DoorDash.
B43: 4. DCF vs COMPS GAP: DCF gives ₹96–₹137 (discount to CMP ₹249). EV/Revenue comps give ₹144–₹290 (straddles CMP). Gap = market pricing in Blinkit hitting 5-6% NOV margins on ₹2L Cr+ NOV beyond FY34. Comps support current valuation; DCF does not - typical for high-growth phase.
B44: 5. INVESTMENT THESIS: Stock is FULLY PRICED at ₹249 on a conservative DCF. However, if Blinkit achieves 6% margins on ₹2L Cr NOV by FY32-33 (DoorDash-like trajectory), intrinsic value = ₹300-350. ACCUMULATE below ₹200 (>25% MoS), HOLD at ₹200-250, REDUCE above ₹300.

Sheet Cost & Margin   
B3: Cost & Margin - ETERNAL LIMITED
B4: Particulars | C4: FY22A | D4: FY23A | E4: FY24A | F4: FY25A | G4: FY26E | H4: FY27E | I4: FY28E | J4: FY29E
A6: # | B6: Revenue Bridge
B7: Total Revenue (₹ Cr) | C7: ='3-Statement'!C7 -> 4193 | D7: ='3-Statement'!D7 -> 7079 | E7: ='3-Statement'!E7 -> 12114 | F7: ='3-Statement'!F7 -> 20243 | G7: ='3-Statement'!G7 -> 28641.422 | H7: ='3-Statement'!H7 -> 40122.272 | I7: ='3-Statement'!I7 -> 53093.729 | J7: ='3-Statement'!J7 -> 65159.791
B8: YoY Growth % | C8: ='3-Statement'!C13 -> - | D8: ='3-Statement'!D13 -> 0.68829001 | E8: ='3-Statement'!E13 -> 0.71125865 | F8: ='3-Statement'!F13 -> 0.67104177 | G8: ='3-Statement'!G13 -> 0.41488029 | H8: ='3-Statement'!H13 -> 0.40084779 | I8: ='3-Statement'!I13 -> 0.32329816 | J8: ='3-Statement'!J13 -> 0.22725964
B9: Revenue CAGR FY22–FY25 | C9: 0.692
B10: Revenue CAGR FY25–FY29E | J10: 0.36
A12: # | B12: Gross Margin Analysis
B13: Stock Purchases | C13: ='3-Statement'!C18 -> 552 | D13: ='3-Statement'!D18 -> 1438 | E13: ='3-Statement'!E18 -> 2887 | F13: ='3-Statement'!F18 -> 5653 | G13: ='3-Statement'!G18 -> 8828 | H13: ='3-Statement'!H18 -> 13122 | I13: ='3-Statement'!I18 -> 17919 | J13: ='3-Statement'!J18 -> 22143
B14: Change in Inventories | C14: ='3-Statement'!C140 -> -28 | D14: ='3-Statement'!D140 -> -43 | E14: ='3-Statement'!E140 -> -5 | F14: ='3-Statement'!F140 -> -88 | G14: ='3-Statement'!G140 -> -114 | H14: ='3-Statement'!H140 -> -141 | I14: ='3-Statement'!I140 -> -109 | J14: ='3-Statement'!J140 -> -67
B15: Delivery & Fulfilment | C15: ='3-Statement'!C20 -> 1814 | D15: ='3-Statement'!D20 -> 2537 | E15: ='3-Statement'!E20 -> 3915 | F15: ='3-Statement'!F20 -> 5728 | G15: ='3-Statement'!G20 -> 7876 | H15: ='3-Statement'!H20 -> 10632 | I15: ='3-Statement'!I20 -> 13539 | J15: ='3-Statement'!J20 -> 15964
B16: Gross Profit (₹ Cr) | C16: =C7-C13-C14-C15 -> 1855 | D16: =D7-D13-D14-D15 -> 3147 | E16: =E7-E13-E14-E15 -> 5317 | F16: =F7-F13-F14-F15 -> 8950 | G16: =G7-G13-G14-G15 -> 12051.422 | H16: =H7-H13-H14-H15 -> 16509.272 | I16: =I7-I13-I14-I15 -> 21744.729 | J16: =J7-J13-J14-J15 -> 27119.791
B17: Gross Margin % | C17: =C16/C7 -> 0.44240401 | D17: =D16/D7 -> 0.44455432 | E17: =E16/E7 -> 0.43891365 | F17: =F16/F7 -> 0.44212814 | G17: =G16/G7 -> 0.42076898 | H17: =H16/H7 -> 0.41147401 | I17: =I16/I7 -> 0.40955362 | J17: =J16/J7 -> 0.41620439
A19: # | B19: Operating Cost Breakdown (% of Revenue)
B20: Delivery & Fulfilment % | C20: ='3-Statement'!C20/'3-Statement'!C7 -> 0.4326258 | D20: ='3-Statement'!D20/'3-Statement'!D7 -> 0.35838395 | E20: ='3-Statement'!E20/'3-Statement'!E7 -> 0.32317979 | F20: ='3-Statement'!F20/'3-Statement'!F7 -> 0.28296201 | G20: ='3-Statement'!G20/'3-Statement'!G7 -> 0.27498635 | H20: ='3-Statement'!H20/'3-Statement'!H7 -> 0.26498998 | I20: ='3-Statement'!I20/'3-Statement'!I7 -> 0.25500187 | J20: ='3-Statement'!J20/'3-Statement'!J7 -> 0.24499772
B21: Advertising & Marketing % | C21: ='3-Statement'!C23/'3-Statement'!C7 -> 0.38945862 | D21: ='3-Statement'!D23/'3-Statement'!D7 -> 0.20695013 | E21: ='3-Statement'!E23/'3-Statement'!E7 -> 0.043420835 | F21: ='3-Statement'!F23/'3-Statement'!F7 -> 0.042632021 | G21: ='3-Statement'!G23/'3-Statement'!G7 -> 0.049997518 | H21: ='3-Statement'!H23/'3-Statement'!H7 -> 0.048003263 | I21: ='3-Statement'!I23/'3-Statement'!I7 -> 0.044995898 | J21: ='3-Statement'!J23/'3-Statement'!J7 -> 0.044997075
B22: Cash Employee % | C22: ='3-Statement'!C21/'3-Statement'!C7 -> 0.18006201 | D22: ='3-Statement'!D21/'3-Statement'!D7 -> 0.13547111 | E22: ='3-Statement'!E21/'3-Statement'!E7 -> 0.09443619 | F22: ='3-Statement'!F21/'3-Statement'!F7 -> 0.086943635 | G22: ='3-Statement'!G21/'3-Statement'!G7 -> 0.073006152 | H22: ='3-Statement'!H21/'3-Statement'!H7 -> 0.063007398 | I22: ='3-Statement'!I21/'3-Statement'!I7 -> 0.054997079 | J22: ='3-Statement'!J21/'3-Statement'!J7 -> 0.050997708
B23: ESOP % | C23: ='3-Statement'!C22/'3-Statement'!C7 -> 0.20939661 | D23: ='3-Statement'!D22/'3-Statement'!D7 -> 0.071479022 | E23: ='3-Statement'!E22/'3-Statement'!E7 -> 0.042512795 | F23: ='3-Statement'!F22/'3-Statement'!F7 -> 0.039421034 | G23: ='3-Statement'!G22/'3-Statement'!G7 -> 0.031423021 | H23: ='3-Statement'!H22/'3-Statement'!H7 -> 0.023677622 | I23: ='3-Statement'!I22/'3-Statement'!I7 -> 0.016951154 | J23: ='3-Statement'!J22/'3-Statement'!J7 -> 0.013044855
B24: Technology % | C24: ='3-Statement'!C24/'3-Statement'!C7 -> 0.068924398 | D24: ='3-Statement'!D24/'3-Statement'!D7 -> 0.054668739 | E24: ='3-Statement'!E24/'3-Statement'!E7 -> 0.040036322 | F24: ='3-Statement'!F24/'3-Statement'!F7 -> 0.031813466 | G24: ='3-Statement'!G24/'3-Statement'!G7 -> 0.029991528 | H24: ='3-Statement'!H24/'3-Statement'!H7 -> 0.027989442 | I24: ='3-Statement'!I24/'3-Statement'!I7 -> 0.02599177 | J24: ='3-Statement'!J24/'3-Statement'!J7 -> 0.02500008
B25: Total Cost % (ex D&A, Finance) | C25: =SUM(C20:C24) -> 1.2804674 | D25: =SUM(D20:D24) -> 0.82695296 | E25: =SUM(E20:E24) -> 0.54358593 | F25: =SUM(F20:F24) -> 0.48377217 | G25: =SUM(G20:G24) -> 0.45940457 | H25: =SUM(H20:H24) -> 0.4276677 | I25: =SUM(I20:I24) -> 0.39793777 | J25: =SUM(J20:J24) -> 0.37903744
A27: # | B27: EBITDA Bridge (Waterfall Data)
B28: Revenue | F28: ='3-Statement'!F7 -> 20243 | G28: ='3-Statement'!G7 -> 28641.422 | H28: ='3-Statement'!H7 -> 40122.272 | I28: ='3-Statement'!I7 -> 53093.729 | J28: ='3-Statement'!J7 -> 65159.791
B29: Less: Stock & Inventory | F29: =-(F13+F14) -> -5565 | G29: =-(G13+G14) -> -8714 | H29: =-(H13+H14) -> -12981 | I29: =-(I13+I14) -> -17810 | J29: =-(J13+J14) -> -22076
B30: Less: Delivery | F30: =-F15 -> -5728 | G30: =-G15 -> -7876 | H30: =-H15 -> -10632 | I30: =-I15 -> -13539 | J30: =-J15 -> -15964
B31: = Gross Profit | F31: =F28+F29+F30 -> 8950 | G31: =G28+G29+G30 -> 12051.422 | H31: =H28+H29+H30 -> 16509.272 | I31: =I28+I29+I30 -> 21744.729 | J31: =J28+J29+J30 -> 27119.791
B32: Less: Cash Employee | F32: =-'3-Statement'!F21 -> -1760 | G32: =-'3-Statement'!G21 -> -2091 | H32: =-'3-Statement'!H21 -> -2528 | I32: =-'3-Statement'!I21 -> -2920 | J32: =-'3-Statement'!J21 -> -3323
B33: Less: ESOP | F33: =-'3-Statement'!F22 -> -798 | G33: =-'3-Statement'!G22 -> -900 | H33: =-'3-Statement'!H22 -> -950 | I33: =-'3-Statement'!I22 -> -900 | J33: =-'3-Statement'!J22 -> -850
B34: Less: Marketing | F34: =-'3-Statement'!F23 -> -863 | G34: =-'3-Statement'!G23 -> -1432 | H34: =-'3-Statement'!H23 -> -1926 | I34: =-'3-Statement'!I23 -> -2389 | J34: =-'3-Statement'!J23 -> -2932
B35: Less: Tech | F35: =-'3-Statement'!F24 -> -644 | G35: =-'3-Statement'!G24 -> -859 | H35: =-'3-Statement'!H24 -> -1123 | I35: =-'3-Statement'!I24 -> -1380 | J35: =-'3-Statement'!J24 -> -1629
B36: Less: Other OpEx | F36: ='3-Statement'!F25 -> 4248 | G36: ='3-Statement'!G25 -> 2291 | H36: ='3-Statement'!H25 -> 3210 | I36: ='3-Statement'!I25 -> 4247 | J36: ='3-Statement'!J25 -> 5213
B37: = Adj EBITDA | F37: ='3-Statement'!F27 -> 1079 | G37: ='3-Statement'!G27 -> 2274.8515 | H37: ='3-Statement'!H27 -> 3753.0491 | I37: ='3-Statement'!I27 -> 6529.8646 | J37: ='3-Statement'!J27 -> 9407.7513
B38: Adj EBITDA Margin % | F38: ='3-Statement'!F28 -> 0.053302376 | G38: ='3-Statement'!G28 -> 0.079425229 | H38: ='3-Statement'!H28 -> 0.093540291 | I38: ='3-Statement'!I28 -> 0.12298749 | J38: ='3-Statement'!J28 -> 0.1443797
A40: # | B40: Cost Efficiency KPIs
B41: Revenue per Employee (₹ Cr) | C41: 1 | D41: 1.15 | E41: 1.47 | F41: 1.2 | G41: - | H41: - | I41: - | J41: -
B42: Cost per Employee (₹ '000) | C42: 388 | D42: 237 | E42: 201 | F42: 152 | G42: - | H42: - | I42: - | J42: -
B43: Marketing Cost per Order (₹) | C43: 22.7 | D43: 19 | E43: 19 | F43: 23.1 | G43: 29.1 | H43: 35.4 | I43: 40.8 | J43: 43.5
B44: Delivery Cost per Order (₹) | C44: 33.9 | D44: 39.2 | E44: 52 | F44: 67.2 | G44: 89.1 | H44: 110.5 | I44: 130.1 | J44: 142.2
B45: Technology Cost per MTU (₹/yr) | C45: 196 | D45: 228 | E45: 264 | F45: 313 | G45: 403 | H45: 486 | I45: 554 | J45: 607
A47: # | B47: DARK STORE ECONOMICS MODEL
B48: Metric | C48: Mature Store | D48: New Store | E48: Target
B49: Store Size (sqft) | C49: 2,500-3,500 | D49: 2500 | E49: Expanding
B50: SKUs | C50: 8k-12k | D50: 3k–5k | E50: Increasing
B51: Daily Orders | C51: 600-800 | D51: 200–300 | E51: -
B52: AOV (INR) | C52: 650-700 | D52: 550–600 | E52: -
B53: Monthly GOV (₹ Lakh) | C53: 126-168 | D53: 33–54 | E53: -
B54: Rent (₹ Lakh) | C54: 2.5-4.0 | D54: 2.0–3.0 | E54: -
B55: Staff Cost (₹ Lakh) | C55: 4.0-6.0 | D55: 3.0–4.0 | E55: -
B56: Other Opex (₹ Lakh) | C56: 2.0-3.0 | D56: 1.5–2.0 | E56: -
B57: Store EBITDA (₹ Lakh) | C57: +8 to +15 | D57: (2) to (1) | E57: -
B58: EBITDA Margin | C58: 5-10% | D58: Negative | E58: 5-6%
B59: Payback (months) | C59: 18-24 | D59: - | E59: -
B60: ROCE | C60: 40-60% | D60: - | E60: 40%+

Sheet  SEGMENT P&L
B2: Segment Profit & Loss - ETERNAL LIMITED
B3: Particulars | C3: FY23A | D3: FY24A | E3: FY25A | F3: FY26E | G3: FY27E | H3: FY28E | I3: FY29E
A5: # | B5: FOOD DELIVERY SEGMENT
B6: Gross Order Value (₹ Cr) | C6: ='Revenue Model'!D7 -> 26305 | D6: ='Revenue Model'!E7 -> 32224 | E6: ='Revenue Model'!F7 -> 38646 | F6: ='Revenue Model'!G7 -> 45602.28 | G6: ='Revenue Model'!H7 -> 54722.736 | H6: ='Revenue Model'!I7 -> 65120.056 | I6: ='Revenue Model'!J7 -> 76190.465
B7: Net Order Value (₹ Cr) | C7: ='Revenue Model'!D9 -> 22490.775 | D7: ='Revenue Model'!E9 -> 27487.072 | E7: ='Revenue Model'!F9 -> 32849.1 | F7: ='Revenue Model'!G9 -> 38761.938 | G7: ='Revenue Model'!H9 -> 46240.712 | H7: ='Revenue Model'!I9 -> 54700.847 | I7: ='Revenue Model'!J9 -> 63619.039
B8: GOV Growth % | C8: - | D8: =(D6-C6)/C6 -> 0.22501426 | E8: =(E6-D6)/D6 -> 0.19929245 | F8: =(F6-E6)/E6 -> 0.18 | G8: =(G6-F6)/F6 -> 0.2 | H8: =(H6-G6)/G6 -> 0.19 | I8: =(I6-H6)/H6 -> 0.17
B9: Platform Revenue (₹ Cr) | C9: ='Revenue Model'!D18 -> 4533 | D9: ='Revenue Model'!E18 -> 6361 | E9: ='Revenue Model'!F18 -> 8080 | F9: ='Revenue Model'!G18 -> 9804.4902 | G9: ='Revenue Model'!H18 -> 12039.002 | H9: ='Revenue Model'!I18 -> 14652.013 | I9: ='Revenue Model'!J18 -> 17142.855
B10: Take Rate (Rev ÷ GOV) | C10: ='Revenue Model'!D17 -> 0.172 | D10: ='Revenue Model'!E17 -> 0.197 | E10: ='Revenue Model'!F17 -> 0.209 | F10: ='Revenue Model'!G17 -> 0.215 | G10: ='Revenue Model'!H17 -> 0.22 | H10: ='Revenue Model'!I17 -> 0.225 | I10: ='Revenue Model'!J17 -> 0.225
B11: Adjusted Revenue (₹ Cr) | C11: 4763 | D11: 6147 | E11: 7792 | F11: 9418 | G11: 11017 | H11: 13543 | I11: 16508
B12: Adj Revenue as % GOV | C12: 0.224 | D12: 0.234 | E12: 0.242 | F12: 0.244 | G12: 0.242 | H12: 0.247 | I12: 0.254
B13: Contribution (₹ Cr) | C13: n/d | D13: 1196 | E13: 2225 | F13: 3092 | G13: 3582 | H13: 4624 | I13: 5897
B14: Contribution Margin % NOV | C14: 1.7% (GOV) | D14: 0.053 | E14: 0.081 | F14: 0.094 | G14: 0.092 | H14: 0.1 | I14: 0.108
B15: Adj. EBITDA (₹ Cr) | C15: ='Revenue Model'!D22 -> -10 | D15: ='Revenue Model'!E22 -> 912 | E15: ='Revenue Model'!F22 -> 1505 | F15: ='Revenue Model'!G22 -> 2015.6208 | G15: ='Revenue Model'!H22 -> 2543.2392 | H15: ='Revenue Model'!I22 -> 3117.9483 | I15: ='Revenue Model'!J22 -> 3689.9042
B16: Adj. EBITDA Margin % NOV | C16: ='Revenue Model'!D21 -> 0 | D16: ='Revenue Model'!E21 -> 0.033 | E16: ='Revenue Model'!F21 -> 0.046 | F16: ='Revenue Model'!G21 -> 0.052 | G16: ='Revenue Model'!H21 -> 0.055 | H16: ='Revenue Model'!I21 -> 0.057 | I16: ='Revenue Model'!J21 -> 0.058
B17: Number of Orders (mn) | D17: 647 | E17: 753 | F17: 853 | G17: 933 | H17: 1020 | I17: 1106
B18: Monthly Transacting Users (mn) | C18: 14.7 | D18: 17 | E18: 18.4 | F18: 20.6 | G18: 22.5 | H18: 24.5 | I18: 26.5
B19: AOV (₹) | C19: ='Revenue Model'!D11 -> 407 | D19: ='Revenue Model'!E11 -> 428 | E19: ='Revenue Model'!F11 -> 453 | F19: ='Revenue Model'!G11 -> 473 | G19: ='Revenue Model'!H11 -> 493 | H19: ='Revenue Model'!I11 -> 514 | I19: ='Revenue Model'!J11 -> 536
B20: NAOV (₹) | C20: n/d | D20: 348 | E20: 365 | F20: 385 | G20: 403 | H20: 420 | I20: 437
B21: Active Restaurants ('000) | C21: ='Revenue Model'!D13 -> 210 | D21: ='Revenue Model'!E13 -> 247 | E21: ='Revenue Model'!F13 -> 297 | F21: ='Revenue Model'!G13 -> 329.67 | G21: ='Revenue Model'!H13 -> 362.637 | H21: ='Revenue Model'!I13 -> 398.9007 | I21: ='Revenue Model'!J13 -> 434.80176
B22: Active Delivery Partners ('000) | C22: ='Revenue Model'!D14 -> 326 | D22: ='Revenue Model'!E14 -> 400 | E22: ='Revenue Model'!F14 -> 473 | F22: ='Revenue Model'!G14 -> 525.03 | G22: ='Revenue Model'!H14 -> 577.533 | H22: ='Revenue Model'!I14 -> 635.2863 | I22: ='Revenue Model'!J14 -> 692.46207
A24: # | B24: BLINKIT SEGMENT
B25: Dark Store Count (EoY) | C25: ='Revenue Model'!D27 -> 377 | D25: ='Revenue Model'!E27 -> 526 | E25: ='Revenue Model'!F27 -> 1301 | F25: ='Revenue Model'!G27 -> 1950 | G25: ='Revenue Model'!H27 -> 2600 | H25: ='Revenue Model'!I27 -> 3300 | I25: ='Revenue Model'!J27 -> 3700
B26: Net New Store Additions | C26: ='Revenue Model'!D28 -> 0 | D26: ='Revenue Model'!E28 -> 149 | E26: ='Revenue Model'!F28 -> 775 | F26: ='Revenue Model'!G28 -> 649 | G26: ='Revenue Model'!H28 -> 650 | H26: ='Revenue Model'!I28 -> 700 | I26: ='Revenue Model'!J28 -> 400
B27: Cities | C27: - | D27: 19 | E27: 26 | F27: 100+ | G27: 120+ | H27: 150+ | I27: 175+
B28: Gross Order Value (₹ Cr) | C28: - | D28: 6449 | E28: 12469 | F28: 28273 | G28: 50335 | H28: 75503 | I28: 101928
B29: Net Order Value (₹ Cr) | C29: ='Revenue Model'!D34 -> 5690 | D29: ='Revenue Model'!E34 -> 10503 | E29: ='Revenue Model'!F34 -> 22371 | F29: ='Revenue Model'!G34 -> 33556.5 | G29: ='Revenue Model'!H34 -> 50334.75 | H29: ='Revenue Model'!I34 -> 67951.913 | I29: ='Revenue Model'!J34 -> 81542.295
B30: NOV Growth % | C30: ='Revenue Model'!D33 -> - | D30: ='Revenue Model'!E33 -> 0.85 | E30: ='Revenue Model'!F33 -> 1.13 | F30: ='Revenue Model'!G33 -> 0.5 | G30: ='Revenue Model'!H33 -> 0.5 | H30: ='Revenue Model'!I33 -> 0.35 | I30: ='Revenue Model'!J33 -> 0.2
B31: Revenue (₹ Cr) | C31: ='Revenue Model'!D36 -> 806 | D31: ='Revenue Model'!E36 -> 2301 | E31: ='Revenue Model'!F36 -> 5206 | F31: ='Revenue Model'!G36 -> 7885.7775 | G31: ='Revenue Model'!H36 -> 12080.34 | H31: ='Revenue Model'!I36 -> 16648.219 | I31: ='Revenue Model'!J36 -> 20385.574
B32: Take Rate (Rev ÷ NOV) | C32: ='Revenue Model'!D35 -> 0.142 | D32: ='Revenue Model'!E35 -> 0.219 | E32: ='Revenue Model'!F35 -> 0.233 | F32: ='Revenue Model'!G35 -> 0.235 | G32: ='Revenue Model'!H35 -> 0.24 | H32: ='Revenue Model'!I35 -> 0.245 | I32: ='Revenue Model'!J35 -> 0.25
B33: Number of Orders (mn) | D33: 119 | E33: 203 | F33: 424 | G33: 767 | H33: 1209 | I33: 1710
B34: AOV (₹) | C34: - | D34: 541 | E34: 613 | F34: 667 | G34: 687 | H34: 708 | I34: 729
B35: NAOV (₹) | C35: - | D35: 478 | E35: 517 | F35: 528 | G35: 542 | H35: 556 | I35: 570
B36: Monthly Transacting Users (mn) | C36: - | D36: 2.9 | E36: 5.1 | F36: 10.2 | G36: 17 | H36: 24 | I36: 32
B37: NOV per Store per Day (₹ '000) | C37: - | D37: 414 | E37: 672 | F37: 766 | G37: 800 | H37: 850 | I37: 900
B38: Warehousing Space (mn sqft) | C38: - | D38: 3.7 | E38: 4.8 | F38: 7.2 | G38: 9 | H38: 11.5 | I38: 14
B39: Contribution (₹ Cr) | C39: - | D39: -445 | E39: 266 | F39: 953 | G39: 1608 | H39: 3627 | I39: 6888
B40: Contribution Margin % NOV | C40: - | D40: -0.078 | E40: 0.025 | F40: 0.043 | G40: 0.04 | H40: 0.06 | I40: 0.085
B41: Adj. EBITDA (₹ Cr) | C41: ='Revenue Model'!D42 -> -1016 | D41: ='Revenue Model'!E42 -> -384 | E41: ='Revenue Model'!F42 -> -292 | F41: ='Revenue Model'!G42 -> 328.8537 | G41: ='Revenue Model'!H42 -> 1006.695 | H41: ='Revenue Model'!I42 -> 2378.3169 | I41: ='Revenue Model'!J42 -> 3669.4033
B42: Adj. EBITDA Margin % NOV | D42: -0.178 | E42: -0.037 | F42: -0.013 | G42: 0.01 | H42: 0.02 | I42: 0.035
B43: Blinkit Capex (₹ Cr) | C43: - | D43: n/a | E43: n/a | F43: 936 | G43: 910 | H43: 1040 | I43: 1190
B44: Capex per New Store (₹ Cr) | C44: - | D44: n/a | E44: n/a | F44: 1.21 | G44: 1.4 | H44: 1.6 | I44: 1.7
B45: Implied ROCE % | C45: - | D45: n/m | E45: n/m | F45: n/m | G45: 0.11 | H45: 0.24 | I45: 0.46
A47: # | B47: HYPERPURE SEGMENT
B48: Revenue (₹ Cr) | C48: ='Revenue Model'!D46 -> 1506 | D48: ='Revenue Model'!E46 -> 3172 | E48: ='Revenue Model'!F46 -> 6196 | F48: ='Revenue Model'!G46 -> 9913.6 | G48: ='Revenue Model'!H46 -> 14374.72 | H48: ='Revenue Model'!I46 -> 19405.872 | I48: ='Revenue Model'!J46 -> 24257.34
B49: YoY Revenue Growth % | C49: ='Revenue Model'!D47 -> 1.8 | D49: ='Revenue Model'!E47 -> 1.11 | E49: ='Revenue Model'!F47 -> 0.95 | F49: ='Revenue Model'!G47 -> 0.6 | G49: ='Revenue Model'!H47 -> 0.45 | H49: ='Revenue Model'!I47 -> 0.35 | I49: ='Revenue Model'!J47 -> 0.25
B50: Unique Restaurant Partners | C50: n/a | D50: n/a | E50: n/a | F50: - | G50: - | H50: - | I50: -
B51: Active Cities | C51: n/a | D51: n/a | E51: n/a | F51: - | G51: - | H51: - | I51: -
B52: Adj. EBITDA (₹ Cr) | C52: ='Revenue Model'!D48 -> -194 | D52: ='Revenue Model'!E48 -> -126 | E52: ='Revenue Model'!F48 -> -84 | F52: ='Revenue Model'!G48 -> 99.136 | G52: ='Revenue Model'!H48 -> 287.4944 | H52: ='Revenue Model'!I48 -> 679.20552 | I52: ='Revenue Model'!J48 -> 1091.5803
B53: Adj. EBITDA Margin % | C53: ='Revenue Model'!D49 -> -0.129 | D53: ='Revenue Model'!E49 -> -0.039 | E53: ='Revenue Model'!F49 -> -0.014 | F53: ='Revenue Model'!G49 -> 0.01 | G53: ='Revenue Model'!H49 -> 0.02 | H53: ='Revenue Model'!I49 -> 0.035 | I53: ='Revenue Model'!J49 -> 0.045
A56: # | B56: GOING-OUT SEGMENT
B57: Gross Order Value (₹ Cr) | C57: 1366 | D57: 3225 | E57: 7796 | F57: 13229 | G57: 19844 | H57: 27782 | I57: 37506
B58: Net Order Value (₹ Cr) | C58: ='Revenue Model'!D52 -> 1132 | D58: ='Revenue Model'!E52 -> 2581 | E58: ='Revenue Model'!F52 -> 6618 | F58: ='Revenue Model'!G52 -> 11250.6 | G58: ='Revenue Model'!H52 -> 16875.9 | H58: ='Revenue Model'!I52 -> 23626.26 | I58: ='Revenue Model'!J52 -> 31895.451
B59: NOV Growth % | C59: ='Revenue Model'!D53 -> - | D59: ='Revenue Model'!E53 -> - | E59: ='Revenue Model'!F53 -> 0.111 | F59: ='Revenue Model'!G53 -> 0.09 | G59: ='Revenue Model'!H53 -> 0.095 | H59: ='Revenue Model'!I53 -> 0.1 | I59: ='Revenue Model'!J53 -> 0.105
B60: Revenue (₹ Cr) | C60: ='Revenue Model'!D54 -> 171 | D60: ='Revenue Model'!E54 -> 258 | E60: ='Revenue Model'!F54 -> 737 | F60: ='Revenue Model'!G54 -> 1012.554 | G60: ='Revenue Model'!H54 -> 1603.2105 | H60: ='Revenue Model'!I54 -> 2362.626 | I60: ='Revenue Model'!J54 -> 3349.0224
B61: Revenue % of NOV | C61: - | D61: - | E61: =E60/E58 -> 0.11136295 | F61: =F60/F58 -> 0.09 | G61: =G60/G58 -> 0.095 | H61: =H60/H58 -> 0.1 | I61: =I60/I58 -> 0.105
B62: Adj. EBITDA (₹ Cr) | C62: ='Revenue Model'!D56 -> -13 | D62: ='Revenue Model'!E56 -> -6 | E62: ='Revenue Model'!F56 -> -38 | F62: ='Revenue Model'!G56 -> -168.759 | G62: ='Revenue Model'!H56 -> -84.3795 | H62: ='Revenue Model'!I56 -> 354.3939 | I62: ='Revenue Model'!J56 -> 956.86353
B63: Adj. EBITDA Margin % (NOV) | C63: -0.011 | D63: -0.002 | E63: -0.006 | F63: -0.015 | G63: -0.005 | H63: 0.015 | I63: 0.03
B66: CONSOLIDATED SEGMENT SUMMARY
B67: Total Revenue (₹ Cr) | C67: ='3-Statement'!D7 -> 7079 | D67: ='3-Statement'!E7 -> 12114 | E67: ='3-Statement'!F7 -> 20243 | F67: ='3-Statement'!G7 -> 28641.422 | G67: ='3-Statement'!H7 -> 40122.272 | H67: ='3-Statement'!I7 -> 53093.729 | I67: ='3-Statement'!J7 -> 65159.791
B68: Food Delivery Revenue | C68: =C9 -> 4533 | D68: =D9 -> 6361 | E68: =E9 -> 8080 | F68: =F9 -> 9804.4902 | G68: =G9 -> 12039.002 | H68: =H9 -> 14652.013 | I68: =I9 -> 17142.855
B69: Blinkit Revenue | C69: =C31 -> 806 | D69: =D31 -> 2301 | E69: =E31 -> 5206 | F69: =F31 -> 7885.7775 | G69: =G31 -> 12080.34 | H69: =H31 -> 16648.219 | I69: =I31 -> 20385.574
B70: Hyperpure Revenue | C70: =C48 -> 1506 | D70: =D48 -> 3172 | E70: =E48 -> 6196 | F70: =F48 -> 9913.6 | G70: =G48 -> 14374.72 | H70: =H48 -> 19405.872 | I70: =I48 -> 24257.34
B71: District Revenue | C71: =C60 -> 171 | D71: =D60 -> 258 | E71: =E60 -> 737 | F71: =F60 -> 1012.554 | G71: =G60 -> 1603.2105 | H71: =H60 -> 2362.626 | I71: =I60 -> 3349.0224
B72: Others | C72: ='3-Statement'!D12 -> 234 | D72: ='3-Statement'!E12 -> 22 | E72: ='3-Statement'!F12 -> 24 | F72: ='3-Statement'!G12 -> 25 | G72: ='3-Statement'!H12 -> 25 | H72: ='3-Statement'!I12 -> 25 | I72: ='3-Statement'!J12 -> 25
B73: Total Adj. EBITDA (₹ Cr) | C73: ='3-Statement'!D27 -> -765 | D73: ='3-Statement'!E27 -> 372 | E73: ='3-Statement'!F27 -> 1079 | F73: ='3-Statement'!G27 -> 2274.8515 | G73: ='3-Statement'!H27 -> 3753.0491 | H73: ='3-Statement'!I27 -> 6529.8646 | I73: ='3-Statement'!J27 -> 9407.7513
B74: Food Delivery EBITDA | C74: =C15 -> -10 | D74: 912 | E74: 1505 | F74: 2016 | G74: 2543 | H74: 3118 | I74: 3690
B75: Blinkit EBITDA | C75: =C41 -> -1016 | D75: -384 | E75: -292 | F75: 403 | G75: 1208 | H75: 2854 | I75: 4403
B76: Hyperpure EBITDA | C76: =C52 -> -194 | D76: -126 | E76: -84 | F76: 99 | G76: 288 | H76: 679 | I76: 1092
B77: District EBITDA | C77: =C62 -> -13 | D77: -6 | E77: -38 | F77: -169 | G77: -84 | H77: 354 | I77: 957
B78: Adj. EBITDA Margin % | C78: ='3-Statement'!D28 -> -0.10806611 | D78: ='3-Statement'!E28 -> 0.030708271 | E78: ='3-Statement'!F28 -> 0.053302376 | F78: ='3-Statement'!G28 -> 0.079425229 | G78: ='3-Statement'!H28 -> 0.093540291 | H78: ='3-Statement'!I28 -> 0.12298749 | I78: ='3-Statement'!J28 -> 0.1443797
B79: Total B2C GOV (₹ Cr) | C79: 34120 | D79: 47918 | E79: 74715 | F79: 109165 | G79: 150069 | H79: 194830 | I79: 236009
B80: Group Revenue CAGR (FY25–29E) | J80: 0.36
